Workbook

Sheet EJECUCION
H2: =SUBTOTAL(9,H4:H1001) -> 54794383 | J2: =SUBTOTAL(9,J4:J1001) -> 60728115 | K2: =SUBTOTAL(9,K4:K1001) -> 5933732
J3: PRESUPUESTO | K3: DIFERENCIA
J4: =IFERROR(VLOOKUP(G4,TD!B:C,2,0),0) -> 39400000 | K4: =J4-H4 -> 6287406
E5: =15000000-C5 -> 1186250 | J5: =IFERROR(VLOOKUP(G5,TD!B:C,2,0),0) -> 8044400 | K5: =J5-H5 -> 1137150
E6: =15000000-C6 -> 1521800 | J6: =IFERROR(VLOOKUP(G6,TD!B:C,2,0),0) -> 4680315 | K6: =J6-H6 -> 219315
E7: =15000000-C7 -> 3162216 | J7: =IFERROR(VLOOKUP(G7,TD!B:C,2,0),0) -> 4000000 | K7: =J7-H7 -> 0
J8: =IFERROR(VLOOKUP(G8,TD!B:C,2,0),0) -> 700000 | K8: =J8-H8 -> -694600
J9: =IFERROR(VLOOKUP(G9,TD!B:C,2,0),0) -> 600000 | K9: =J9-H9 -> -377000
J10: =IFERROR(VLOOKUP(G10,TD!B:C,2,0),0) -> 272000 | K10: =J10-H10 -> -639899
J11: =IFERROR(VLOOKUP(G11,TD!B:C,2,0),0) -> 750000 | K11: =J11-H11 -> 116000
J12: =IFERROR(VLOOKUP(G12,TD!B:C,2,0),0) -> 390000 | K12: =J12-H12 -> -55890
J13: =IFERROR(VLOOKUP(G13,TD!B:C,2,0),0) -> 500000 | K13: =J13-H13 -> 100000
J14: =IFERROR(VLOOKUP(G14,TD!B:C,2,0),0) -> 400000 | K14: =J14-H14 -> 100000
J15: =IFERROR(VLOOKUP(G15,TD!B:C,2,0),0) -> 315600 | K15: =J15-H15 -> 47600
J16: =IFERROR(VLOOKUP(G16,TD!B:C,2,0),0) -> 0 | K16: =J16-H16 -> -266000
J17: =IFERROR(VLOOKUP(G17,TD!B:C,2,0),0) -> 0 | K17: =J17-H17 -> -147850
J18: =IFERROR(VLOOKUP(G18,TD!B:C,2,0),0) -> 0 | K18: =J18-H18 -> -125000
J19: =IFERROR(VLOOKUP(G19,TD!B:C,2,0),0) -> 145800 | K19: =J19-H19 -> 35800
... J31: =IFERROR(VLOOKUP(G31,TD!B:C,2,0),0) -> 0 | K31: =J31-H31 -> 0

Sheet FORMULARIO
A1: Marca temporal | B1: TIPO | C1: Clase ingreso | D1: Columna 3 | E1: Tipo de gasto | F1: Fecha | G1: PERSONA REGISTRA GASTO | H1: Nombre | I1: Detalle | J1: Valor | K1: Forma de pago | L1: Subir soporte
A2: 46171.508 | B2: Inversión Inicial | E2: Arriendo | F2: 46170 | G2: DIANA PAOLA GARZON | H2: Arriendo inicial | I2: Valor de arriendo inicial | J2: 2000000 | K2: Transferencia (Tarjeta Debito, Nequi, Daviplata, Cuentas de ahorro)
A3: 46171.509 | B3: Inversión Inicial | E3: Computador | F3: 46170 | G3: MAURICIO GARZON | H3: Computador | I3: Compra de computador nuevo | J3: 400000 | K3: Transferencia (Tarjeta Debito, Nequi, Daviplata, Cuentas de ahorro)
A4: 46171.511 | B4: Inversión Inicial | E4: Sistema POS | F4: 46171 | G4: MAURICIO GARZON | H4: Creacion de dominio | I4: Creación de dominio de Be | J4: 45700 | K4: Transferencia (Tarjeta Debito, Nequi, Daviplata, Cuentas de ahorro) | L4: https://drive.google.com/open?id=1Pe-Fi_o_UFjPbPbIxoMPnZJBSe1y5oRH
A5: 46172.332 | B5: Gastos Variables de Operación | C5: Otros | E5: Comida | F5: 46172 | G5: ANTONIO RENTERIA | H5: Desayuno | I5: Desayuno | J5: 48000 | K5: Transferencia (Tarjeta Debito, Nequi, Daviplata, Cuentas de ahorro)
A6: 46172.417 | B6: Inversión Inicial | E6: Arreglos locativos | F6: 46171 | G6: MAURICIO GARZON | H6: Vidrios vitrinas entrada | I6: Pago la mitad de los vidrios de la vitrina | J6: 450000 | K6: Transferencia (Tarjeta Debito, Nequi, Daviplata, Cuentas de ahorro) | L6: https://drive.google.com/open?id=18Tfd1glS8YpXxHSYGLsg2fCpZQFm9sym
A7: 46172.418 | B7: Inversión Inicial | E7: Legalización | F7: 46171 | G7: YENI GARZON | H7: Matrícula Mercantil (Cámara de Comercio) | I7: Cámara de comercio Chapinero | J7: 65400 | K7: Transferencia (Tarjeta Debito, Nequi, Daviplata, Cuentas de ahorro)
A8: 46172.419 | B8: Inversión Inicial | E8: Legalización | F8: 46171 | G8: YENI GARZON | H8: Matrícula Mercantil (Cámara de Comercio) | I8: Certificado CCB Chapinero | J8: 6100 | K8: Transferencia (Tarjeta Debito, Nequi, Daviplata, Cuentas de ahorro)
A9: 46172.42 | B9: Inversión Inicial | E9: Comida | F9: 46172 | G9: DIANA PAOLA GARZON | H9: Desayuno | I9: Desayuno de Yeni y diana | J9: 29000 | K9: Efectivo
A10: 46172.423 | B10: Inversión Inicial | E10: Legalización | F10: 46172 | G10: YENI GARZON | H10: Matrícula Mercantil (Cámara de Comercio) | I10: Impresión contrato de arriendo | J10: 4800 | K10: Efectivo | N10: inversion inicial | O10: =RESUMEN!C19*4 -> 59588115
A11: 46172.793 | B11: Inversión Inicial | E11: Legalización | F11: 46172 | G11: DIANA PAOLA GARZON | H11: Matrícula Mercantil (Cámara de Comercio) | I11: Pago de autenticación | J11: 28500 | K11: Efectivo | N11: saldo por ejecutar | O11: =O10-O9 -> 4793732
A12: 46172.794 | B12: Inversión Inicial | E12: Comida | F12: 46172 | G12: DIANA PAOLA GARZON | H12: Almuerzos | I12: Almuerzos de todos | J12: 107000 | K12: Efectivo
A13: 46172.796 | B13: Inversión Inicial | E13: Movilidad | F13: 46172 | G13: DIANA PAOLA GARZON | H13: Parqueadero | I13: Parqueadero carro tio | J13: 21000 | K13: Efectivo
A14: 46172.797 | B14: Inversión Inicial | E14: Arriendo | F14: 46172 | G14: DIANA PAOLA GARZON | H14: Arriendo inicial | I14: Pago de arriendo y depósito 50% | J14: 2000000 | K14: Transferencia (Tarjeta Debito, Nequi, Daviplata, Cuentas de ahorro)
A15: 46172.805 | B15: Inversión Inicial | E15: Camaras | F15: 46172 | G15: DIANA PAOLA GARZON | H15: Camaras de seguridad | I15: Camaras de seguridad | J15: 634000 | K15: Transferencia (Tarjeta Debito, Nequi, Daviplata, Cuentas de ahorro)
A16: 46174.428 | B16: Gastos Variables de Operación | C16: Otros | E16: Gasolina | F16: 46172 | G16: ANTONIO RENTERIA | H16: Gasolina Carro | I16: Gasolina de transporte para las compras | J16: 30000 | K16: Efectivo
A17: 46174.43 | B17: Gastos Variables de Operación | C17: Otros | E17: Movilidad | F17: 46172 | G17: ANTONIO RENTERIA | H17: Parqueadero Carro | I17: Parqueadero del carro para las compras iniciales | J17: 25000 | K17: Efectivo
A18: 46174.596 | B18: Inversión Inicial | E18: Arreglos locativos | F18: 46174 | G18: MAURICIO GARZON | H18: Decoracion, Pintura, Vestier en Drywall | I18: Pago de adecuaciones de infraestructura | J18: 1055000 | K18: Transferencia (Tarjeta Debito, Nequi, Daviplata, Cuentas de ahorro) | L18: https://drive.google.com/open?id=1EsJ-NhcYdHfpSVqCXea9LeKCY3UJ10of
A19: 46174.634 | B19: Inversión Inicial | E19: Maniquies | F19: 46172 | G19: ANTONIO RENTERIA | H19: Cremallera para Flauta, Flautas para Exhibicion, Ganchera tripode, Ganchos de madera, Maniquies cuerpo Completo, Maniquies medio cuerpo, Cortina Negra | I19: 2 barra u de 120, 3 barra sencilla de 120, 4 barra de 120 con malla, 40 flautas para barra, 6 Parales de 3 MTS, 200 gancho pinza, 400 gancho cromo, 1 silla de 2 puesto, 1 burro cascada, 2 hombre, 2 dama, 1 niño 10 blanco, 9 rieles, 3 cortinas negras, 14 barra sencilla de 150, 8 barra u de 150, 1 tabla de 150, 1 burro sencillo negro, 1 la de 6 puestos, 1 palo Chino | J19: 4406000 | K19: Efectivo
A20: 46174.635 | B20: Inversión Inicial | E20: Maniquies | F20: 46172 | G20: YENI GARZON | H20: Mostrador | I20: Cachucheras | J20: 55000 | K20: Transferencia (Tarjeta Debito, Nequi, Daviplata, Cuentas de ahorro)
A21: 46174.638 | B21: Inversión Inicial | E21: Mercancia | F21: 46172 | G21: MAURICIO GARZON | H21: Mercancia | I21: Camisetas Colombia, España y Portugal 2 | J21: 1352000 | K21: Tarjeta de Credito
A22: 46174.641 | B22: Inversión Inicial | E22: Iluminacion | F22: 46172 | G22: MAURICIO GARZON | H22: Iluminacion interna y externa | I22: 40 spot de 20 w, 20 riel de 1 MTS, 3 bombillas para Vestier, 2 reflectores, 15 MTS duplex, 4 MTS luz neón | J22: 977000 | K22: Tarjeta de Credito
A23: 46174.643 | B23: Inversión Inicial | E23: Arreglos locativos | F23: 46173 | G23: YENI GARZON | H23: Pintura | I23: Aerosol y tornillos | J23: 52300 | K23: Efectivo
A24: 46174.644 | B24: Inversión Inicial | E24: Arreglos locativos | F24: 46174 | G24: MAURICIO GARZON | H24: Pintura | I24: Vinilo amarillo | J24: 13000 | K24: Efectivo
A25: 46176.162 | B25: Inversión Inicial | E25: Insumos | F25: 46175 | G25: YENI GARZON | H25: Implementos de aseo | I25: Escoba, recogedor | J25: 15400 | K25: Efectivo
A26: 46176.164 | B26: Inversión Inicial | E26: Arreglos locativos | F26: 46175 | G26: MAURICIO GARZON | H26: Decoracion | I26: Varillas, brocas tornillos | J26: 97450 | K26: Efectivo
A27: 46176.166 | B27: Inversión Inicial | E27: Arreglos locativos | F27: 46175 | G27: MAURICIO GARZON | H27: Decoracion | I27: Canales y amarres | J27: 18100 | K27: Efectivo
A28: 46176.168 | B28: Inversión Inicial | E28: Arreglos locativos | F28: 46175 | G28: MAURICIO GARZON | H28: Decoracion | I28: Parales y cinta | J28: 29800 | K28: Efectivo | P28: =O33-O28 -> 5200
A29: 46176.17 | B29: Inversión Inicial | E29: Insumos | F29: 46175 | G29: YENI GARZON | H29: Implementos de aseo | I29: Jabón rey, vasos, gaseosa | J29: 14400 | K29: Efectivo
A30: 46176.171 | B30: Inversión Inicial | E30: Arreglos locativos | F30: 46175 | G30: YENI GARZON | H30: Decoracion | I30: Pilas láser Anderson | J30: 4800 | K30: Efectivo
A31: 46176.172 | B31: Inversión Inicial | E31: Insumos | F31: 46175 | G31: YENI GARZON | H31: Implementos de aseo | I31: Aseo | J31: 37000 | K31: Efectivo
A32: 46176.774 | B32: Inversión Inicial | E32: Seguridad | F32: 46176 | G32: DIANA PAOLA GARZON | H32: Candados | I32: Candados comprados a la sra Berna | J32: 40000 | K32: Efectivo
A33: 46176.817 | B33: Inversión Inicial | E33: Seguridad | F33: 46176 | G33: DIANA PAOLA GARZON | H33: Candados | I33: Candados egret dorado | J33: 60000 | K33: Efectivo
A34: 46176.821 | B34: Inversión Inicial | E34: Mercancia | F34: 46176 | G34: DIANA PAOLA GARZON | H34: Inversión inicial | I34: Alimentación con Jonathan | J34: 50000 | K34: Efectivo
A35: 46177.795 | B35: Inversión Inicial | E35: Mercancia | F35: 46177 | G35: ANTONIO RENTERIA | H35: Mercancia | I35: Pantalones de hombre | J35: 2090000 | K35: Transferencia (Tarjeta Debito, Nequi, Daviplata, Cuentas de ahorro)
A36: 46177.795 | B36: Inversión Inicial | E36: Mercancia | F36: 46177 | G36: ANTONIO RENTERIA | H36: Mercancia | I36: Pantalones sudadera | J36: 560000 | K36: Transferencia (Tarjeta Debito, Nequi, Daviplata, Cuentas de ahorro)
A37: 46177.796 | B37: Inversión Inicial | E37: Mercancia | F37: 46177 | G37: DIANA PAOLA GARZON | H37: Mercancia | I37: Blusas mujer | J37: 358000 | K37: Transferencia (Tarjeta Debito, Nequi, Daviplata, Cuentas de ahorro)
A38: 46177.799 | B38: Inversión Inicial | E38: Gasolina | F38: 46176 | G38: ANTONIO RENTERIA | H38: Gasolina | I38: Gasolina carro | J38: 25000 | K38: Transferencia (Tarjeta Debito, Nequi, Daviplata, Cuentas de ahorro)
A39: 46177.8 | B39: Inversión Inicial | E39: Movilidad | F39: 46176 | G39: DIANA PAOLA GARZON | H39: Parqueadero | I39: Parqueadero | J39: 70000 | K39: Efectivo
A40: 46177.801 | B40: Inversión Inicial | E40: Comida | F40: 46176 | G40: DIANA PAOLA GARZON | H40: Desayuno | I40: Desayuno con Jonathan | J40: 32500 | K40: Efectivo
... A44: 46178.45 | B44: Inversión Inicial | E44: Insumos | F44: 46177 | G44: YENI GARZON | H44: Papeleria | I44: Cinta ancha transparente | J44: 3800 | K44: Efectivo
A45: 46178.452 | B45: Gastos Variables de Operación | C45: Otros | E45: Envio mercancia | F45: 46177 | G45: YENI GARZON | H45: Envío a Santander de Quilichao | I45: Envío por inter rapidísimo camiseta Colombia m pago por Addi a Jonathan | J45: 18000 | K45: Efectivo
A46: 46178.534 | B46: Inversión Inicial | E46: Mercancia | F46: 46176 | G46: YENI GARZON | H46: Mercancia | I46: Camisetas y conjuntos de fútbol | J46: 2332000 | K46: Transferencia (Tarjeta Debito, Nequi, Daviplata, Cuentas de ahorro)
A47: 46178.632 | B47: Inversión Inicial | E47: Mercancia | F47: 46176 | G47: YENI GARZON | H47: Mercancia | I47: Goldtex Bermudas caballero y shorts dama | J47: 686000 | K47: Efectivo
A48: 46178.634 | B48: Inversión Inicial | E48: Mercancia | F48: 46176 | G48: YENI GARZON | H48: Mercancia | I48: Confecciones perfect chaquetas caballero | J48: 630000 | K48: Transferencia (Tarjeta Debito, Nequi, Daviplata, Cuentas de ahorro)
A49: 46178.638 | B49: Inversión Inicial | E49: Mercancia | F49: 46176 | G49: YENI GARZON | H49: Mercancia | I49: Dannystyless | J49: 379000 | K49: Transferencia (Tarjeta Debito, Nequi, Daviplata, Cuentas de ahorro)
A50: 46178.639 | B50: Inversión Inicial | E50: Mercancia | F50: 46176 | G50: YENI GARZON | H50: Mercancia | I50: Gorras Colombia | J50: 168000 | K50: Transferencia (Tarjeta Debito, Nequi, Daviplata, Cuentas de ahorro)
A51: 46178.64 | B51: Inversión Inicial | E51: Mercancia | F51: 46176 | G51: YENI GARZON | H51: Mercancia | I51: Bolsos, canguros | J51: 900000 | K51: Transferencia (Tarjeta Debito, Nequi, Daviplata, Cuentas de ahorro)
A52: 46178.641 | B52: Inversión Inicial | E52: Mercancia | F52: 46176 | G52: YENI GARZON | H52: Mercancia | I52: Canilleras y medias futbolera | J52: 300000 | K52: Transferencia (Tarjeta Debito, Nequi, Daviplata, Cuentas de ahorro)
A53: 46178.643 | B53: Inversión Inicial | E53: Mercancia | F53: 46176 | G53: YENI GARZON | H53: Mercancia | I53: R Treik jean dama | J53: 1214000 | K53: Transferencia (Tarjeta Debito, Nequi, Daviplata, Cuentas de ahorro)
A54: 46178.721 | B54: Inversión Inicial | E54: Mercancia | F54: 46176 | G54: YENI GARZON | H54: Mercancia | I54: Chaqueta caballero | J54: 270000 | K54: Transferencia (Tarjeta Debito, Nequi, Daviplata, Cuentas de ahorro)
A55: 46178.723 | B55: Inversión Inicial | E55: Mercancia | F55: 46176 | G55: YENI GARZON | H55: Mercancia | I55: Oversize | J55: 949000 | K55: Transferencia (Tarjeta Debito, Nequi, Daviplata, Cuentas de ahorro)
A56: 46178.724 | B56: Inversión Inicial | E56: Mercancia | F56: 46176 | G56: YENI GARZON | H56: Mercancia | I56: Chaquetas dama | J56: 364000 | K56: Transferencia (Tarjeta Debito, Nequi, Daviplata, Cuentas de ahorro)
A57: 46178.725 | B57: Inversión Inicial | E57: Mercancia | F57: 46176 | G57: YENI GARZON | H57: Mercancia | I57: Bicicleteros, leggins algodón y básicas | J57: 366500 | K57: Transferencia (Tarjeta Debito, Nequi, Daviplata, Cuentas de ahorro)
... A82: 46180.625 | B82: Inversión Inicial | E82: Mercancia | F82: 46179 | G82: YENI GARZON | H82: Mercancia | I82: Chaqueta jean caballero y dama | J82: 639000 | K82: Transferencia (Tarjeta Debito, Nequi, Daviplata, Cuentas de ahorro)
A83: 46181.382 | B83: Inversión Inicial | E83: Sistema POS | F83: 46180 | G83: MAURICIO GARZON | H83: Sistema Pos de TiendaNube | I83: Pago primer mes de tiendanube | J83: 39900 | K83: Tarjeta de Credito | L83: https://drive.google.com/open?id=1KVoJUEsH4TipZPrn3uSiA6bMyiFXObFK
A84: 46181.428 | B84: Inversión Inicial | E84: Mercancia | F84: 46176 | G84: MAURICIO GARZON | H84: Mercancia | I84: Splash y brillos | J84: 90000 | K84: Efectivo
A85: 46182.356 | B85: Inversión Inicial | E85: Arreglos locativos | F85: 46182 | G85: ANTONIO RENTERIA | H85: Mostrador | I85: compra madera para el mostrador principal | J85: 1115900 | K85: Transferencia (Tarjeta Debito, Nequi, Daviplata, Cuentas de ahorro) | L85: https://drive.google.com/open?id=1nEzNsAAx89ntwK90vCVMCugxPf68Yuxz
A86: 46182.359 | B86: Inversión Inicial | E86: Movilidad | F86: 46179 | G86: ANTONIO RENTERIA | H86: parqueadero compra | I86: pago parqueadero realizacion de compras en la mañana | J86: 21850 | K86: Efectivo
A87: 46182.36 | B87: Inversión Inicial | E87: Movilidad | F87: 46179 | G87: ANTONIO RENTERIA | H87: parqueadero compras tarde 06-06-2026 | I87: pago parqueadero compras en la tarde del 06-06-2026 | J87: 35000 | K87: Efectivo
A88: 46182.362 | B88: Inversión Inicial | E88: Aviso | F88: 46179 | G88: ANTONIO RENTERIA | H88: Aviso, tarjetas presentacion (abono) | I88: compra para aviso y terjeta presentacion | J88: 300000 | K88: Transferencia (Tarjeta Debito, Nequi, Daviplata, Cuentas de ahorro)
A89: 46182.365 | B89: Inversión Inicial | E89: Arreglos locativos | F89: 46179 | G89: ANTONIO RENTERIA | H89: sensor y multitoma de Corriente | I89: compra de sensores y multitoma de corriente | J89: 49000 | K89: Efectivo
A90: 46182.367 | B90: Inversión Inicial | E90: Comida | F90: 46179 | G90: ANTONIO RENTERIA | H90: Almuerzos del dia para compras realizadas | I90: Pago de almuesrzos en el dia para compras realizadas 06-06-2026 | J90: 97500 | K90: Transferencia (Tarjeta Debito, Nequi, Daviplata, Cuentas de ahorro)
A91: 46182.37 | B91: Inversión Inicial | E91: Arreglos locativos | F91: 46179 | G91: ANTONIO RENTERIA | H91: Rieles Negro | I91: compra de 3 Rieles Negros | J91: 42000 | K91: Efectivo
A92: 46182.373 | B92: Inversión Inicial | E92: Mercancia | F92: 46179 | G92: ANTONIO RENTERIA | H92: correas, billeteras y regalo padre | I92: Compra de las correas, billetaras y regalos de padre para hombre | J92: 365000 | K92: Transferencia (Tarjeta Debito, Nequi, Daviplata, Cuentas de ahorro)
A93: 46182.375 | B93: Inversión Inicial | E93: Arreglos locativos | F93: 46179 | G93: ANTONIO RENTERIA | H93: Pintura, Estuco, rodillo, brocha y Lijas | I93: Compra insumos para arreglos locativos del almacen | J93: 180000 | K93: Transferencia (Tarjeta Debito, Nequi, Daviplata, Cuentas de ahorro)
A94: 46182.428 | B94: Inversión Inicial | E94: Gasolina | F94: 46179 | G94: ANTONIO RENTERIA | H94: Gasolina movilizacion | I94: Pago Gasolina para movilizarse | J94: 40000 | K94: Transferencia (Tarjeta Debito, Nequi, Daviplata, Cuentas de ahorro)
A95: 46182.673 | B95: Inversión Inicial | E95: Arreglos locativos | F95: 46182 | G95: MAURICIO GARZON | H95: Decoracion | I95: Accesorios ferretería y electricidad | J95: 275800 | K95: Transferencia (Tarjeta Debito, Nequi, Daviplata, Cuentas de ahorro) | L95: https://drive.google.com/open?id=1eyAHJovCapDyrYNCxyMsyv-hgWZvWSVn
A96: 46182.675 | B96: Inversión Inicial | E96: Insumos | F96: 46182 | G96: MAURICIO GARZON | H96: Implementos de aseo | I96: Compra ese llanti mantenimiento pisos y limpiador para vidrios | J96: 292999 | K96: Transferencia (Tarjeta Debito, Nequi, Daviplata, Cuentas de ahorro) | L96: https://drive.google.com/open?id=1RCCZmEjKdFZMyBoCAP-oRNoU1WK59LIZ
A97: 46182.679 | B97: Inversión Inicial | E97: Arreglos locativos | F97: 46182 | G97: MAURICIO GARZON | H97: Decoracion | I97: Sonido, percheros y aerosoles | J97: 317900 | K97: Transferencia (Tarjeta Debito, Nequi, Daviplata, Cuentas de ahorro) | L97: https://drive.google.com/open?id=1Dy1Mn5ynd2Hmz1NZzIZq63hJv-dGKDlg
A98: 46182.681 | B98: Inversión Inicial | E98: Insumos | F98: 46182 | G98: MAURICIO GARZON | H98: Papeleria | I98: Papel termico | J98: 17500 | K98: Transferencia (Tarjeta Debito, Nequi, Daviplata, Cuentas de ahorro) | L98: https://drive.google.com/open?id=1-LgHetWEsePIrhYpAmRMZX9E4ItSvwLa
A99: 46182.873 | B99: Inversión Inicial | E99: Arreglos locativos | F99: 46182 | G99: ANTONIO RENTERIA | H99: Antena antiurto | I99: Compra de antena antiurto | J99: 1547000 | K99: Transferencia (Tarjeta Debito, Nequi, Daviplata, Cuentas de ahorro)
A100: 46183.381 | B100: Inversión Inicial | E100: Arreglos locativos | F100: 46183 | G100: DIANA PAOLA GARZON | H100: Vidrios vitrinas entrada | I100: abono de vidrios vitrinas internas y espejos | J100: 400000 | K100: Transferencia (Tarjeta Debito, Nequi, Daviplata, Cuentas de ahorro)
A101: 46183.478 | B101: Inversión Inicial | E101: Insumos | F101: 46183 | G101: MAURICIO GARZON | H101: Papeleria | I101: Compra de bolsas topo sencillo collares y rubana | J101: 52500 | K101: Transferencia (Tarjeta Debito, Nequi, Daviplata, Cuentas de ahorro) | L101: https://drive.google.com/open?id=1_gU_T7RSuX8dUKYuauO34G_KqFvmFTvW
A102: 46183.479 | B102: Inversión Inicial | E102: Mercancia | F102: 46183 | G102: MAURICIO GARZON | H102: Mercancia | I102: Combos Splash caballero | J102: 130500 | K102: Transferencia (Tarjeta Debito, Nequi, Daviplata, Cuentas de ahorro)
A103: 46183.48 | B103: Inversión Inicial | E103: Mercancia | F103: 46183 | G103: MAURICIO GARZON | H103: Mercancia | I103: Compra de buzos | J103: 1074000 | K103: Transferencia (Tarjeta Debito, Nequi, Daviplata, Cuentas de ahorro) | L103: https://drive.google.com/open?id=1IxgbJT2wOaLqZpEGZ2vAb3d95HCk0pQj
A104: 46183.503 | B104: Inversión Inicial | E104: Mercancia | F104: 46183 | G104: MAURICIO GARZON | H104: Mercancia | I104: Compré camiseta oversize | J104: 525000 | K104: Transferencia (Tarjeta Debito, Nequi, Daviplata, Cuentas de ahorro) | L104: https://drive.google.com/open?id=1iS-otFFp43T2jrgjWOPBuyOoZtiK6xva
A105: 46183.604 | B105: Inversión Inicial | E105: Gastos | F105: 46183 | G105: MAURICIO GARZON | H105: Parqueadero | I105: Parqueadero | J105: 50000 | K105: Transferencia (Tarjeta Debito, Nequi, Daviplata, Cuentas de ahorro) | L105: https://drive.google.com/open?id=1MwxsvrWu7SA5rU6MAiWqdvPunsxd8KkB
A106: 46183.637 | B106: Inversión Inicial | E106: Sistema POS | F106: 46183 | G106: MAURICIO GARZON | H106: Equipo Bold | I106: Bold | J106: 149000 | K106: Transferencia (Tarjeta Debito, Nequi, Daviplata, Cuentas de ahorro)
A107: 46183.737 | B107: Inversión Inicial | E107: Mercancia | F107: 46183 | G107: MAURICIO GARZON | H107: Mercancia | I107: Compra camisa Galleta polo (9) | J107: 288000 | K107: Transferencia (Tarjeta Debito, Nequi, Daviplata, Cuentas de ahorro)
A108: 46183.74 | B108: Inversión Inicial | E108: Mercancia | F108: 46183 | G108: MAURICIO GARZON | H108: Mercancia | I108: Compra xl - 2xl. Cant (2), S - M - L cant (6) | J108: 252000 | K108: Transferencia (Tarjeta Debito, Nequi, Daviplata, Cuentas de ahorro)
A109: 46183.751 | B109: Inversión Inicial | E109: Mercancia | F109: 46183 | G109: MAURICIO GARZON | H109: Mercancia | I109: Prendas surtidas $10000 cant(40) | J109: 400000 | K109: Transferencia (Tarjeta Debito, Nequi, Daviplata, Cuentas de ahorro)
A110: 46183.756 | B110: Inversión Inicial | E110: Mercancia | F110: 46183 | G110: YENI GARZON | H110: Mercancia | I110: Compra buzos col cant(6) | J110: 210000 | K110: Efectivo
A111: 46183.76 | B111: Inversión Inicial | E111: Gasolina | F111: 46183 | G111: YENI GARZON | H111: Gasolina | I111: Pago gasolina camioneta para compras 10-06-2026 | J111: 60000 | K111: Efectivo
A112: 46183.769 | B112: Inversión Inicial | E112: Mercancia | F112: 46183 | G112: YENI GARZON | H112: Mercancia | I112: Compra blusas(3), blusa pepa(5), pepa chinilla(3), pepa buso(15) | J112: 780000 | K112: Transferencia (Tarjeta Debito, Nequi, Daviplata, Cuentas de ahorro)
A113: 46183.8 | B113: Inversión Inicial | E113: Mercancia | F113: 46183 | G113: MAURICIO GARZON | H113: Mercancia | I113: Compra camisetas | J113: 2007000 | K113: Transferencia (Tarjeta Debito, Nequi, Daviplata, Cuentas de ahorro)
A114: 46183.803 | B114: Inversión Inicial | E114: Insumos | F114: 46180 | G114: DIANA PAOLA GARZON | H114: Rollos de papel impresora | I114: Compra rollos de de papel impresora | J114: 5800 | K114: Efectivo
A115: 46184.389 | B115: Inversión Inicial | E115: Arreglos locativos | F115: 46184 | G115: ANTONIO RENTERIA | H115: Aviso | I115: Pago final aviso | J115: 180000 | K115: Transferencia (Tarjeta Debito, Nequi, Daviplata, Cuentas de ahorro)
A116: 46184.602 | B116: Inversión Inicial | E116: Mostradores | F116: 46184 | G116: YENI GARZON | H116: Vidrios vitrinas entrada | I116: Acarreo madera | J116: 30000 | K116: Efectivo
A117: 46184.603 | B117: Inversión Inicial | E117: Mostradores | F117: 46184 | G117: DIANA PAOLA GARZON | H117: Vidrios vitrinas entrada | I117: Tapete bienvenido | J117: 25000 | K117: Efectivo
... A123: 46188.616 | B123: Inversión Inicial | E123: Compra talonarios, bombas, pecera, tropo, fomi | F123: 46188 | G123: ANTONIO RENTERIA | H123: Compra utencilios | I123: Compra de accesorios necesarios para el aseo del almacen | J123: 23500 | K123: Efectivo
A124: 46188.827 | B124: Inversión Inicial | E124: Mostradores | F124: 46188 | G124: MAURICIO GARZON | H124: Mostrador | I124: Compra madera mostradores y punto de venta | J124: 1130000 | K124: Transferencia (Tarjeta Debito, Nequi, Daviplata, Cuentas de ahorro) | L124: https://drive.google.com/open?id=15PK0pRY6QHAWofQcFx2lrhMGIXoMyrUi
A125: 46188.829 | B125: Inversión Inicial | E125: Insumos | F125: 46185 | G125: MAURICIO GARZON | H125: Implementos de aseo | I125: Compra de productos de limpieza, perchero para escobas y otros. | J125: 63500 | K125: Efectivo | L125: https://drive.google.com/open?id=1azQiSPONPWu8GKx5x-7Qz1oa05D-olyw
A126: 46188.832 | B126: Inversión Inicial | E126: Mostradores | F126: 46184 | G126: MAURICIO GARZON | H126: Mostrador | I126: Compra de tornillos para madera, soporte para vestier y fresa recta para madera | J126: 64600 | K126: Transferencia (Tarjeta Debito, Nequi, Daviplata, Cuentas de ahorro) | L126: https://drive.google.com/open?id=1pER4L5VUSlqIPL0ZEKMUtnMKDnlAYB0N
A127: 46189.388 | B127: Inversión Inicial | E127: Insumos | F127: 46188 | G127: YENI GARZON | H127: Implementos de aseo | I127: Compra de Vasos | J127: 3000 | K127: Efectivo | L127: https://drive.google.com/open?id=1qCjoemtjGFTUJAgdBvcmSg58EM4GViOL
A128: 46189.57 | B128: Inversión Inicial | E128: Insumos | F128: 46189 | G128: MAURICIO GARZON | H128: Extintor | I128: Extintores y nueve avisos de señalización | J128: 52000 | K128: Transferencia (Tarjeta Debito, Nequi, Daviplata, Cuentas de ahorro) | L128: https://drive.google.com/open?id=1DUFJx-19Aq5ixeIUL1HSqpPrAcPbKzXC
A129: 46189.572 | B129: Inversión Inicial | E129: Insumos | F129: 46189 | G129: MAURICIO GARZON | H129: Botiquin, Extintor | I129: Compra extintor y botiquín puesto por Mauricio Garzón | J129: 45000 | K129: Transferencia (Tarjeta Debito, Nequi, Daviplata, Cuentas de ahorro)
A130: 46189.573 | B130: Inversión Inicial | E130: Insumos | F130: 46189 | G130: MAURICIO GARZON | H130: Canecas | I130: Canica verde y caneca blanca y caneca negra tú estás por Mauricio garzón qué haces señorita | J130: 110000 | K130: Transferencia (Tarjeta Debito, Nequi, Daviplata, Cuentas de ahorro)
A131: 46189.576 | B131: Inversión Inicial | E131: Insumos | F131: 46189 | G131: MAURICIO GARZON | H131: Sillas | I131: Tres sillas de madera | J131: 150000 | K131: Transferencia (Tarjeta Debito, Nequi, Daviplata, Cuentas de ahorro)
A132: 46189.585 | B132: Inversión Inicial | E132: Mercancia | F132: 46189 | G132: MAURICIO GARZON | H132: Mercancia | I132: Mercancía inicial puesta por Mauricio garzón | J132: 2618000 | K132: Efectivo | L132: https://drive.google.com/open?id=134mb89NTwmNRgjOhKO2hJ_cJtYZKJ3lf
...

Sheet RESUMEN
A1: Categoría | B1: Detalle | C1: Valor (COP) | D1: INV INICIAL | E1: INV ADICION | F1: INV OPCION | G1: DINERO
A2: INVERSIÓN INICIAL | B2: Mostradores | C2: =SUMIF('INVERSION INICIAL'!B:B,B2,'INVERSION INICIAL'!G:G) -> 700000 | D2: =SUMIF(TD!B:B,B2,TD!C:C) -> 700000 | E2: =SUMIF(TD!F:F,B2,TD!G:G) -> 0 | F2: =SUMIF(TD!J:J,B2,TD!K:K) -> 0
A3: INVERSIÓN INICIAL | B3: Mercancia | C3: =SUMIF('INVERSION INICIAL'!B:B,B3,'INVERSION INICIAL'!G:G) -> 39400000 | D3: =SUMIF(TD!B:B,B3,TD!C:C) -> 39400000 | E3: =SUMIF(TD!F:F,B3,TD!G:G) -> 0 | F3: =SUMIF(TD!J:J,B3,TD!K:K) -> 0 | G3: =D3 -> 39400000
A4: INVERSIÓN INICIAL | B4: Maniquies | C4: =SUMIF('INVERSION INICIAL'!B:B,B4,'INVERSION INICIAL'!G:G) -> 4680315 | D4: =SUMIF(TD!B:B,B4,TD!C:C) -> 4680315 | E4: =SUMIF(TD!F:F,B4,TD!G:G) -> 0 | F4: =SUMIF(TD!J:J,B4,TD!K:K) -> 0 | G4: =D4 -> 4680315
A5: INVERSIÓN INICIAL | B5: Gancheras | C5: =SUMIF('INVERSION INICIAL'!B:B,B5,'INVERSION INICIAL'!G:G) -> 0 | D5: =SUMIF(TD!B:B,B5,TD!C:C) -> 0 | E5: =SUMIF(TD!F:F,B5,TD!G:G) -> 0 | F5: =SUMIF(TD!J:J,B5,TD!K:K) -> 0 | G5: =D5 -> 0
A6: INVERSIÓN INICIAL | B6: Vestier | C6: =SUMIF('INVERSION INICIAL'!B:B,B6,'INVERSION INICIAL'!G:G) -> 380000 | D6: =SUMIF(TD!B:B,B6,TD!C:C) -> 380000 | E6: =SUMIF(TD!F:F,B6,TD!G:G) -> 0 | F6: =SUMIF(TD!J:J,B6,TD!K:K) -> 0
A7: INVERSIÓN INICIAL | B7: Aviso | C7: =SUMIF('INVERSION INICIAL'!B:B,B7,'INVERSION INICIAL'!G:G) -> 400000 | D7: =SUMIF(TD!B:B,B7,TD!C:C) -> 400000 | E7: =SUMIF(TD!F:F,B7,TD!G:G) -> 0 | F7: =SUMIF(TD!J:J,B7,TD!K:K) -> 0
A8: INVERSIÓN INICIAL | B8: Sistema POS | C8: =SUMIF('INVERSION INICIAL'!B:B,B8,'INVERSION INICIAL'!G:G) -> 315600 | D8: =SUMIF(TD!B:B,B8,TD!C:C) -> 315600 | E8: =SUMIF(TD!F:F,B8,TD!G:G) -> 0 | F8: =SUMIF(TD!J:J,B8,TD!K:K) -> 0 | G8: =D8 -> 315600
A9: INVERSIÓN INICIAL | B9: Iluminacion | C9: =SUMIF('INVERSION INICIAL'!B:B,B9,'INVERSION INICIAL'!G:G) -> 600000 | D9: =SUMIF(TD!B:B,B9,TD!C:C) -> 600000 | E9: =SUMIF(TD!F:F,B9,TD!G:G) -> 0 | F9: =SUMIF(TD!J:J,B9,TD!K:K) -> 0 | G9: =D9 -> 600000
A10: INVERSIÓN INICIAL | B10: Computador | C10: =SUMIF('INVERSION INICIAL'!B:B,B10,'INVERSION INICIAL'!G:G) -> 500000 | D10: =SUMIF(TD!B:B,B10,TD!C:C) -> 500000 | E10: =SUMIF(TD!F:F,B10,TD!G:G) -> 0 | F10: =SUMIF(TD!J:J,B10,TD!K:K) -> 0
A11: INVERSIÓN INICIAL | B11: Legalización | C11: =SUMIF('INVERSION INICIAL'!B:B,B11,'INVERSION INICIAL'!G:G) -> 150000 | D11: =SUMIF(TD!B:B,B11,TD!C:C) -> 150000 | E11: =SUMIF(TD!F:F,B11,TD!G:G) -> 0 | F11: =SUMIF(TD!J:J,B11,TD!K:K) -> 0
A12: INVERSIÓN INICIAL | B12: Insumos | C12: =SUMIF('INVERSION INICIAL'!B:B,B12,'INVERSION INICIAL'!G:G) -> 272000 | D12: =SUMIF(TD!B:B,B12,TD!C:C) -> 272000 | E12: =SUMIF(TD!F:F,B12,TD!G:G) -> 0 | F12: =SUMIF(TD!J:J,B12,TD!K:K) -> 0
A13: INVERSIÓN INICIAL | B13: Seguridad | C13: =SUMIF('INVERSION INICIAL'!B:B,B13,'INVERSION INICIAL'!G:G) -> 145800 | D13: =SUMIF(TD!B:B,B13,TD!C:C) -> 145800 | E13: =SUMIF(TD!F:F,B13,TD!G:G) -> 0 | F13: =SUMIF(TD!J:J,B13,TD!K:K) -> 0 | G13: =D13 -> 145800
A14: INVERSIÓN INICIAL | B14: Arreglos locativos | C14: =SUMIF('INVERSION INICIAL'!B:B,B14,'INVERSION INICIAL'!G:G) -> 8044400 | D14: =SUMIF(TD!B:B,B14,TD!C:C) -> 8044400 | E14: =SUMIF(TD!F:F,B14,TD!G:G) -> 0 | F14: =SUMIF(TD!J:J,B14,TD!K:K) -> 0
A15: INVERSIÓN INICIAL | B15: Arriendo | C15: =SUMIF('INVERSION INICIAL'!B:B,B15,'INVERSION INICIAL'!G:G) -> 4000000 | D15: =SUMIF(TD!B:B,B15,TD!C:C) -> 4000000 | E15: =SUMIF(TD!F:F,B15,TD!G:G) -> 0 | F15: =SUMIF(TD!J:J,B15,TD!K:K) -> 0
A16: TOTAL INVERSIÓN | C16: =SUBTOTAL(9,C2:C15) -> 59588115 | D16: =SUBTOTAL(9,D2:D15) -> 59588115 | E16: =SUBTOTAL(9,E2:E15) -> 0 | F16: =SUBTOTAL(9,F2:F15) -> 0
A17: INVERSIÓN INICIAL | B17: Ventas | C17: =SUMIF('INVERSION INICIAL'!B:B,B17,'INVERSION INICIAL'!G:G) -> 0 | D17: =SUMIF(TD!B:B,B17,TD!C:C) -> 0 | E17: =SUMIF(TD!F:F,B17,TD!G:G) -> 0 | F17: =SUMIF(TD!J:J,B17,TD!K:K) -> 0
A19: INVERSION SOCIOS | C19: =C16/C50 -> 14897029
A21: GASTOS FIJOS | B21: Arriendo Local | C21: =SUMIF('GASTOS FIJOS'!B:B,B21,'GASTOS FIJOS'!G:G) -> 3000000
A22: GASTOS FIJOS | B22: Internet | C22: =SUMIF('GASTOS FIJOS'!B:B,B22,'GASTOS FIJOS'!G:G) -> 76000
A23: GASTOS FIJOS | B23: Administración | C23: =SUMIF('GASTOS FIJOS'!B:B,B23,'GASTOS FIJOS'!G:G) -> 5000
A24: GASTOS FIJOS | B24: Sistema POS | C24: =SUMIF('GASTOS FIJOS'!B:B,B24,'GASTOS FIJOS'!G:G) -> 39900
A25: GASTOS FIJOS | B25: Sueldo administrador | C25: =SUMIF('GASTOS FIJOS'!B:B,B25,'GASTOS FIJOS'!G:G) -> 1800000
A26: GASTOS FIJOS | B26: Sueldo auxiliar | C26: =SUMIF('GASTOS FIJOS'!B:B,B26,'GASTOS FIJOS'!G:G) -> 1800000
A27: TOTAL GASTOS FIJOS | C27: =SUBTOTAL(9,C21:C26) -> 6720900
A29: VARIABLES DE OPERACIÓN | B29: Precio Ticket Promedio | C29: 60000
A30: VARIABLES DE OPERACIÓN | B30: Días Abierto al Mes | C30: 30
A31: VARIABLES DE OPERACIÓN | B31: Horario: Lunes a Domingo 9:00 am-8:00 pm
A32: VARIABLES DE OPERACIÓN | B32: Ventas Diarias Estimadas | C32: =OPERACION!C5 -> 12
A34: NOMINA | B34: Empleados | C34: 2
A35: NOMINA | B35: Valor nomina auxiliar | C35: ='GASTOS FIJOS'!G6 -> 1800000
A36: NOMINA | B36: Valor nomina administrador | C36: ='GASTOS FIJOS'!G6 -> 1800000
A39: GASTOS VARIABLES | B39: Luz | C39: =SUMIF(OPERACION!B:B,B39,OPERACION!G:G) -> 270000
A40: GASTOS VARIABLES | B40: Agua | C40: =SUMIF(OPERACION!B:B,B40,OPERACION!G:G) -> 345600
A41: GASTOS VARIABLES | B41: Consumibles | C41: =SUMIF(OPERACION!B:B,B41,OPERACION!G:G) -> 108000
A42: GASTOS VARIABLES | B42: Mercancia | C42: =SUMIF(OPERACION!B:B,B42,OPERACION!G:G) -> 10800000
A43: TOTAL GASTOS VARIABLES | C43: =SUBTOTAL(9,C39:C42) -> 11523600
A45: PROYECCIÓN MENSUAL | B45: Ventas mensuales | C45: =C32*C30 -> 360
A46: INGRESOS | B46: Ingresos Totales | C46: =C45*C29 -> 21600000 | D46: =C46/30 -> 720000
A47: EGRESOS | B47: Gastos fijos mensuales | C47: =C27 -> 6720900
A48: EGRESOS | B48: Gastos variables mensuales | C48: =C43 -> 11523600
A49: PROYECCIÓN MENSUAL | B49: Utilidad Neta Mensual | C49: =C46-C47-C48 -> 3355500 | D49: =C49/C16 -> 0.056311565
A50: PROYECCIÓN MENSUAL | B50: Accionistas | C50: 4
A51: PROYECCIÓN MENSUAL | B51: Utilidad Neta Mensual/Accionistas | C51: =C49/C50 -> 838875
A53: INDICADORES | B53: Punto de Equilibrio $ Ventas mes | C53: =CEILING(C27/(C29-OPERACION!H9),1) -> 241 | D53: =C53*C29 -> 14460000
A54: INDICADORES | B54: Punto de Equilibrio $ Ventas dia | C54: =C53/30 -> 8.0333333 | D54: =D53/30 -> 482000
A55: INDICADORES | B55: Punto de Equilibrio # Ventas dia | C55: =CEILING(C53/30,1) -> 9 | D55: =C55*C30 -> 270
A56: INDICADORES | B56: ROI (Meses de recuperación) | C56: =CEILING(C16/C49,) -> 18

Sheet TD

Sheet INVERSION INICIAL
G1: =SUBTOTAL(9,G2:G989) -> 60728115 | I1: =SUBTOTAL(9,I2:I989) -> 0
A2: Categoría | B2: Detalle | C2: Nombre | D2: Especificacion | E2: Cantidad | F2: Valor | G2: Valor Total | H2: Fuente | I2: Link | J2: Clase | K2: Valor 1 | L2: Valor Total 2 | M2: Fuente 2
A3: INVERSIÓN INICIAL | B3: Mercancia | C3: Mercancia inicial | D3: Mercancia inicial | E3: 910 | F3: 40000 | G3: =F3*E3 -> 36400000 | H3: INVERSION INICIAL | J3: PANTALON DAMA | K3: =VLOOKUP(B3,RESUMEN!B:B,1,0) -> Mercancia
A4: INVERSIÓN INICIAL | B4: Mercancia | C4: Mercancia Mauricio | D4: Mercancia Mauricio | E4: 1 | F4: 3000000 | G4: =F4*E4 -> 3000000 | H4: INVERSION INICIAL | J4: INVENTARIOS SIN PAGAR | K4: =VLOOKUP(B4,RESUMEN!B:B,1,0) -> Mercancia
A5: INVERSIÓN INICIAL | B5: Mostradores | C5: Mostrador | D5: Mostrador Principal (Punto de Pago) | E5: 1 | F5: 700000 | G5: =F5*E5 -> 700000 | H5: INVERSION INICIAL | K5: =VLOOKUP(B5,RESUMEN!B:B,1,0) -> Mostradores
A6: INVERSIÓN INICIAL | B6: Maniquies | C6: Maniquies cuerpo Completo | D6: Maniquies Blancos cuerpo Completo | E6: 4 | F6: 280000 | G6: =F6*E6 -> 1120000 | H6: INVERSION INICIAL | K6: =VLOOKUP(B6,RESUMEN!B:B,1,0) -> Maniquies
A7: INVERSIÓN INICIAL | B7: Maniquies | C7: Maniquies medio cuerpo | D7: Maniquies plasticos para Exhibicion | E7: 6 | F7: 59900 | G7: =F7*E7 -> 359400 | H7: INVERSION INICIAL | K7: =VLOOKUP(B7,RESUMEN!B:B,1,0) -> Maniquies
A8: INVERSIÓN INICIAL | B8: Vestier | C8: Cortina Negra | D8: Cortina Negra | E8: 2 | F8: 40000 | G8: =F8*E8 -> 80000 | H8: INVERSION INICIAL | K8: =VLOOKUP(B8,RESUMEN!B:B,1,0) -> Vestier
A9: INVERSIÓN INICIAL | B9: Vestier | C9: Vestier en Drywall | D9: Vestier en Drywall | E9: 2 | F9: 150000 | G9: =F9*E9 -> 300000 | H9: INVERSION INICIAL | K9: =VLOOKUP(B9,RESUMEN!B:B,1,0) -> Vestier
A10: INVERSIÓN INICIAL | B10: Maniquies | C10: Flautas para Exhibicion | D10: Flautas para Exhibicion | E10: 40 | F10: 20000 | G10: =F10*E10 -> 800000 | H10: INVERSION INICIAL | K10: =VLOOKUP(B10,RESUMEN!B:B,1,0) -> Maniquies
A11: INVERSIÓN INICIAL | B11: Maniquies | C11: Cremallera para Flauta | D11: Cremallera para Flauta | E11: 20 | F11: 20000 | G11: =F11*E11 -> 400000 | H11: INVERSION INICIAL | K11: =VLOOKUP(B11,RESUMEN!B:B,1,0) -> Maniquies
A12: INVERSIÓN INICIAL | B12: Maniquies | C12: Ganchera tripode | D12: Ganchera tripode | E12: 2 | F12: 50000 | G12: =F12*E12 -> 100000 | H12: INVERSION INICIAL | K12: =VLOOKUP(B12,RESUMEN!B:B,1,0) -> Maniquies
A13: INVERSIÓN INICIAL | B13: Maniquies | C13: Burro | D13: Burro | E13: 2 | F13: 100000 | G13: =F13*E13 -> 200000 | H13: INVERSION INICIAL | K13: =VLOOKUP(B13,RESUMEN!B:B,1,0) -> Maniquies
A14: INVERSIÓN INICIAL | B14: Maniquies | C14: Mesa para Jeans | D14: Mesa para Jeans | E14: 1 | F14: 100000 | G14: =F14*E14 -> 100000 | H14: INVERSION INICIAL | K14: =VLOOKUP(B14,RESUMEN!B:B,1,0) -> Maniquies
A15: INVERSIÓN INICIAL | B15: Maniquies | C15: Ganchera tripode | D15: Ganchera tripode | E15: 2 | F15: 50000 | G15: =F15*E15 -> 100000 | H15: INVERSION INICIAL | K15: =VLOOKUP(B15,RESUMEN!B:B,1,0) -> Maniquies
A16: INVERSIÓN INICIAL | B16: Maniquies | C16: Ganchos de madera | D16: Ganchos de madera | E16: 645 | F16: 2327 | G16: =F16*E16 -> 1500915 | H16: INVERSION INICIAL | I16: https://www.homecenter.com.co/homecenter-co/product/878775/set-de-15-piezas-ganchos-de-ropa-madera-natural/878775/ | K16: =VLOOKUP(B16,RESUMEN!B:B,1,0) -> Maniquies
A17: INVERSIÓN INICIAL | B17: Aviso | C17: Aviso | D17: Arreglo de aviso nuevo y reutilizacion del que se tiene | E17: 1 | F17: 400000 | G17: =F17*E17 -> 400000 | H17: INVERSION INICIAL | K17: =VLOOKUP(B17,RESUMEN!B:B,1,0) -> Aviso
A18: INVERSIÓN INICIAL | B18: Iluminacion | C18: Iluminacion interna y externa | D18: Iluminacion interna y externa | E18: 1 | F18: 600000 | G18: =F18*E18 -> 600000 | H18: INVERSION INICIAL | K18: =VLOOKUP(B18,RESUMEN!B:B,1,0) -> Iluminacion
A19: INVERSIÓN INICIAL | B19: Computador | C19: Computador | D19: Computador | E19: 1 | F19: 500000 | G19: =F19*E19 -> 500000 | H19: INVERSION INICIAL | K19: =VLOOKUP(B19,RESUMEN!B:B,1,0) -> Computador
A20: INVERSIÓN INICIAL | B20: Sistema POS | C20: Sistema Pos de TiendaNube | D20: Sistema Pos de TiendaNube | E20: 1 | F20: 39900 | G20: =F20*E20 -> 39900 | H20: INVERSION INICIAL | K20: =VLOOKUP(B20,RESUMEN!B:B,1,0) -> Sistema POS
A21: INVERSIÓN INICIAL | B21: Caja registradora | C21: Tiqueteadora | D21: Combo Impresora 58mm + Lector Codigo X-718 + Cajon Monede | E21: 1 | F21: 390000 | G21: =F21*E21 -> 390000 | H21: INVERSION INICIAL | K21: =VLOOKUP(B21,RESUMEN!B:B,1,0) -> #N/A
A22: INVERSIÓN INICIAL | B22: Sistema POS | C22: Equipo Bold | D22: Equipo Bold moderno | E22: 1 | F22: 230000 | G22: =F22*E22 -> 230000 | H22: INVERSION INICIAL | K22: =VLOOKUP(B22,RESUMEN!B:B,1,0) -> Sistema POS
A23: INVERSIÓN INICIAL | B23: Sistema POS | C23: Creacion de dominio | D23: Creacion de dominio | E23: 1 | F23: 45700 | G23: =F23*E23 -> 45700 | H23: INVERSION INICIAL | K23: =VLOOKUP(B23,RESUMEN!B:B,1,0) -> Sistema POS
A24: INVERSIÓN INICIAL | B24: Legalización | C24: Registro Único Tributario (RUT) | D24: Registro Único Tributario (RUT) costo 0 | E24: 1 | F24: 0 | G24: =F24*E24 -> 0 | H24: INVERSION INICIAL | K24: =VLOOKUP(B24,RESUMEN!B:B,1,0) -> Legalización
A25: INVERSIÓN INICIAL | B25: Legalización | C25: Matrícula Mercantil (Cámara de Comercio) | D25: Matrícula Mercantil (Cámara de Comercio de Bogota) | E25: 1 | F25: 150000 | G25: =F25*E25 -> 150000 | H25: INVERSION INICIAL | K25: =VLOOKUP(B25,RESUMEN!B:B,1,0) -> Legalización
A26: INVERSIÓN INICIAL | B26: Legalización | C26: Concepto de Uso de Suelo | D26: Secretaría Distrital de Planeación (Se consulta en línea), Es el documento más crítico antes de firmar el contrato de arrendamiento. Certifica que en esa dirección específica de Suba está permitido operar un "Lavadero de Vehículos". Si el suelo es estrictamente residencial, no te dejarán abrir.Costo: $0 (Gratuito, se descarga por internet con el CHIP del predio) | E26: 1 | F26: 0 | G26: =F26*E26 -> 0 | H26: INVERSION INICIAL | K26: =VLOOKUP(B26,RESUMEN!B:B,1,0) -> Legalización
A27: INVERSIÓN INICIAL | B27: Insumos | C27: Implementos de aseo | D27: Jabon piso, limpiavidrios, ambientador | E27: 1 | F27: 50000 | G27: =F27*E27 -> 50000 | H27: INVERSION INICIAL | K27: =VLOOKUP(B27,RESUMEN!B:B,1,0) -> Insumos
A28: INVERSIÓN INICIAL | B28: Insumos | C28: Señalizacion | D28: Salida de emergencia | E28: 1 | F28: 20000 | G28: =F28*E28 -> 20000 | H28: INVERSION INICIAL | K28: =VLOOKUP(B28,RESUMEN!B:B,1,0) -> Insumos
... A36: INVERSIÓN INICIAL | B36: Arreglos locativos | C36: Pin antihurto | D36: Alarma Pin Etiqueta Am Antihurto Tienda Ropa X 1000 Unds | E36: 1 | F36: 1187500 | G36: =F36*E36 -> 1187500 | H36: INVERSION INICIAL | K36: =VLOOKUP(B36,RESUMEN!B:B,1,0) -> Arreglos locativos
A37: INVERSIÓN INICIAL | B37: Seguridad | C37: Candados | D37: Candados | E37: 2 | F37: 42900 | G37: =F37*E37 -> 85800 | H37: INVERSION INICIAL | I37: https://www.homecenter.com.co/homecenter-co/category/cat10662/candados/?kid=dis_adi_1435635&gad_source=1&gad_campaignid=23795319996&gbraid=0AAAAADt6wnoJ5ATpOuCvWSc2VjYD7ZXkR&gclid=CjwKCAjw8uTQBhAdEiwAVvtJyoKJyojXEy2y_DjK7sS4mNBKn8yVvvttGfSm34YsEuaMp2Dz6lf3hBoCyjQQAvD_BwE | K37: =VLOOKUP(B37,RESUMEN!B:B,1,0) -> Seguridad
A38: INVERSIÓN INICIAL | B38: Seguridad | C38: Cambio de guardas | D38: Cambio de guardas | E38: 1 | F38: 60000 | G38: =F38*E38 -> 60000 | H38: INVERSION INICIAL | K38: =VLOOKUP(B38,RESUMEN!B:B,1,0) -> Seguridad
A39: INVERSIÓN INICIAL | B39: Arreglos locativos | C39: Pintura | D39: Pintura Blanca | E39: 1 | F39: 284900 | G39: =F39*E39 -> 284900 | H39: INVERSION INICIAL | K39: =VLOOKUP(B39,RESUMEN!B:B,1,0) -> Arreglos locativos
A40: INVERSIÓN INICIAL | B40: Arreglos locativos | C40: Pintura | D40: Pintura Amarilla | E40: 1 | F40: 72000 | G40: =F40*E40 -> 72000 | H40: INVERSION INICIAL | K40: =VLOOKUP(B40,RESUMEN!B:B,1,0) -> Arreglos locativos
A41: INVERSIÓN INICIAL | B41: Arreglos locativos | C41: Piso | D41: Piso Laminado | E41: 0 | F41: 4000000 | G41: =F41*E41 -> 0 | H41: INVERSION OPCIONAL | K41: =VLOOKUP(B41,RESUMEN!B:B,1,0) -> Arreglos locativos
A42: INVERSIÓN INICIAL | B42: Arreglos locativos | C42: Decoracion | D42: Decoracion | E42: 1 | F42: 600000 | G42: =F42*E42 -> 600000 | H42: INVERSION INICIAL | K42: =VLOOKUP(B42,RESUMEN!B:B,1,0) -> Arreglos locativos
A43: INVERSIÓN INICIAL | B43: Arreglos locativos | C43: Vidrios vitrinas entrada | D43: 2 Vidrios vitrinas entrada de 83 cm en vidrio de seguridad de 8 mm | E43: 2 | F43: 450000 | G43: =F43*E43 -> 900000 | H43: INVERSION INICIAL | K43: =VLOOKUP(B43,RESUMEN!B:B,1,0) -> Arreglos locativos
A44: INVERSIÓN INICIAL | B44: Arriendo | C44: Arriendo inicial | D44: Arriendo inicial | E44: 1 | F44: 4000000 | G44: =F44*E44 -> 4000000 | H44: INVERSION INICIAL | K44: =VLOOKUP(B44,RESUMEN!B:B,1,0) -> Arriendo

Sheet GASTOS FIJOS
G1: =SUBTOTAL(9,G2:G1006) -> 6720900
A2: Categoría | B2: Detalle | C2: Nombre | D2: Especificacion | E2: Cantidad | F2: Valor | G2: Valor Total | H2: Fuente | I2: Telefono | J2: Tarea/observacion | K2: Valor 2 | L2: Valor Total 2 | M2: Fuente 2
A3: GASTOS FIJOS | B3: Arriendo Local | C3: Arriendo Local 25 metros cuadrados | D3: Arriendo Local 25 metros cuadrados | E3: 1 | F3: 3000000 | G3: =F3*E3 -> 3000000 | L3: =K3*E3 -> 0
A4: GASTOS FIJOS | B4: Internet | C4: Internet de 900 megas | D4: Internet de 900 megas movistar | E4: 1 | F4: 76000 | G4: =F4*E4 -> 76000 | H4: https://solucionesmovilyhogar.com/hogar?gad_source=1&gad_campaignid=22638574230&gbraid=0AAAAA-JBuZhpF13EfpX-c8woTOOPZEJRZ&gclid=CjwKCAjwtIfPBhAzEiwAv9RTJoUE7cL_c3ZNPoNtGFPMOVhliD3aVdMV2p4zjMf7SFBtoiGfyQi0dxoCfigQAvD_BwE | L4: =K4*E4 -> 0
A5: GASTOS FIJOS | B5: Administración | C5: Esferos, tablas, impresiones, libro | D5: Esferos, tablas, impresiones, libro | E5: 1 | F5: 5000 | G5: =F5*E5 -> 5000 | L5: =K5*E5 -> 0
A6: GASTOS FIJOS | B6: Sueldo auxiliar | C6: Sueldo 7 horas auxiliar tarde | D6: Sueldo auxiliar | E6: 30 | F6: 60000 | G6: =F6*E6 -> 1800000 | L6: =K6*E6 -> 0
A7: GASTOS FIJOS | B7: Sueldo administrador | C7: Sueldo 3 horas administrador mañana | D7: Mauricio Garzon | E7: 30 | F7: 60000 | G7: =F7*E7 -> 1800000 | L7: =K7*E7 -> 0
A8: GASTOS FIJOS | B8: Sistema POS | C8: Sistema Pos de TiendaNube | D8: Sistema Pos de TiendaNube | E8: 1 | F8: 39900 | G8: =F8*E8 -> 39900 | L8: =K8*E8 -> 0
G9: =F9*E9 -> 0 | L9: =K9*E9 -> 0
G10: =F10*E10 -> 0 | L10: =K10*E10 -> 0
G11: =F11*E11 -> 0 | L11: =K11*E11 -> 0
G12: =F12*E12 -> 0 | L12: =K12*E12 -> 0
G13: =F13*E13 -> 0 | L13: =K13*E13 -> 0
G14: =F14*E14 -> 0 | L14: =K14*E14 -> 0
G15: =F15*E15 -> 0 | L15: =K15*E15 -> 0
G16: =F16*E16 -> 0 | L16: =K16*E16 -> 0
G17: =F17*E17 -> 0 | L17: =K17*E17 -> 0
G18: =F18*E18 -> 0 | L18: =K18*E18 -> 0
G19: =F19*E19 -> 0 | L19: =K19*E19 -> 0
G20: =F20*E20 -> 0 | L20: =K20*E20 -> 0
... G50: =F50*E50 -> 0 | L50: =K50*E50 -> 0

Sheet OPERACION
A1: Categoría | B1: Detalle | C1: Valor (COP)
A2: VARIABLES DE OPERACIÓN | B2: Precio Ticket Promedio | C2: =RESUMEN!C29 -> 60000
A3: VARIABLES DE OPERACIÓN | B3: Días Abierto al Mes | C3: 30
A4: VARIABLES DE OPERACIÓN | B4: Horario: Lunes a Viernes 10:00 am-9:00 pm Sabado-Domingo 9 am-8:30 pm
A5: VARIABLES DE OPERACIÓN | B5: Ventas diarias estimadas | C5: 12
A6: VARIABLES DE OPERACIÓN | B6: Ventas mensuales estimadas | C6: =C5*C3 -> 360
A7: VARIABLES DE OPERACIÓN | B7: Empleados | C7: 2
H8: =1-H9/C2 -> 0.4665
G9: =SUBTOTAL(9,G10:G1002) -> 11523600 | H9: =SUBTOTAL(9,H10:H1002) -> 32010
A10: Categoría | B10: Detalle | C10: Nombre | D10: Volumen | E10: Cantidad | F10: Valor | G10: Valor Total | H10: Valor Unt
A11: GASTOS VARIABLES | B11: Luz | C11: Luz | D11: Gasto: 0.5 kWh de energía por moto. | E11: 0.5 | F11: 1500 | G11: =F11*E11*$C$6 -> 270000 | H11: =E11*F11 -> 750
A12: GASTOS VARIABLES | B12: Agua | C12: Agua | D12: Gasto: 60 Litros por moto. 0,06 m3 | E12: 0.06 | F12: 16000 | G12: =F12*E12*$C$6 -> 345600 | H12: =E12*F12 -> 960
A13: GASTOS VARIABLES | B13: Consumibles | C13: Escobas y traperos | E13: 1 | F13: 100 | G13: =F13*E13*$C$6 -> 36000 | H13: =E13*F13 -> 100
A14: GASTOS VARIABLES | B14: Consumibles | C14: Implementos de aseo | D14: Jabon piso, limpiavidrios, ambientador | E14: 1 | F14: 200 | G14: =F14*E14*$C$6 -> 72000 | H14: =E14*F14 -> 200
A15: GASTOS VARIABLES | B15: Mercancia | C15: Mercancia | E15: 1 | F15: 30000 | G15: =F15*E15*$C$6 -> 10800000 | H15: =E15*F15 -> 30000

Sheet CRONOGRAMA
A1: Arriendo | B1: ok
A2: RUT | B2: ok
A3: nombre | B3: tienda.Be casual | C3: Vístete para ser tú mismo. | D3: Comodidad que se nota. Estilo que se siente.
A4: dirección | B4: Calle 132 # 92-32
A5: celular | B5: 3115929346
A6: correo | B6: ventas@tiendabecasual.com
A7: CCB | B7: ok
A8: monto | B8: 2 millones
A9: CCTV | B9: ok
A10: Facturación
A11: sistema POS
A12: Computador | B12: ok
A14: Medios de pago
A15: Nequi | B15: Mauricio
A16: Daviplata | B16: Diana
A17: Addi | B17: Yeni
A18: Sistecredito | B18: Yeni
A19: cuenta ahorros | B19: Yeni
A20: Bold | B20: Yeni
A22: aviso
A23: nombre
A24: tipo de letra del nombre | B24: Montserrat Black o Futura Bold | C24: monserrat
A25: colores del nombre | B25: Negro, Gris y Amarillo
A26: vidrios
A27: pintura
A28: madera
A29: luces | B29: ok
A30: maniquíes | B30: ok
A31: ganchos | B31: ok
A32: Vestier cortinas | B32: ok | C32: tubos y soporte de tubos
A35: escoba
A36: recogedor
A37: trapero
A38: toallas
A39: desinfectante
A40: jabón rey
A41: Señalizacion
A42: Canecas | B42: ok
A43: Papeleria
A44: Extintor | B44: ok
A45: Botiquin | B45: ok
A46: Internet | B46: Movistar 500 megas ok
A48: PANTALON DAMA
A49: PANTALON CABALLERO
A50: TEJIDO
A51: CHAQUETA DAMA
A52: MODA OVERSIZE
A53: SUDADERAS
A54: CHAQUETA CABALLERO
A55: BOLSOS
A56: CAMISETA POLO CABALLERO
A57: PANTALONETAS
A58: BLUSAS
A59: CHAQUETA MUJER
... A65: BIKER

Sheet COMPRAS
F1: =SUBTOTAL(9,F3:F1014) -> 1821 | H1: =SUBTOTAL(9,H3:H1014) -> 30043296 | I1: 2 | K1: =SUBTOTAL(9,K3:K1014) -> 60266000
A3: FECHA INGRESO | B3: SKU | C3: CODIGO DE BARRAS | D3: NOMBRE COMPLETO | E3: PROVEEDOR-MARCA | F3: CANTIDAD COMPRA | G3: VALOR UNT | H3: VALOR TOTAL COMPRA | I3: PRECIO DE VENTA | J3: % MARGEN | K3: VALOR TOTAL VENTA
A4: 46186 | B4: 1143 | C4: =VLOOKUP(B4,MAESTRA!I:K,2,0) -> *1143* | D4: =VLOOKUP(B4,MAESTRA!I:K,3,0) -> JEANS DAMA 4 BOTONES TALLA 10 | E4: R TREIK | F4: 2 | G4: 32000 | H4: =G4*F4 -> 64000 | I4: =CEILING(G4*$I$1,1000) -> 64000 | J4: =IFERROR((I4-G4)/G4,"") -> 1 | K4: =I4*F4 -> 128000
A5: 46186 | B5: 1142 | C5: =VLOOKUP(B5,MAESTRA!I:K,2,0) -> *1142* | D5: =VLOOKUP(B5,MAESTRA!I:K,3,0) -> JEANS DAMA 4 BOTONES TALLA 8 | E5: R TREIK | F5: 1 | G5: 32000 | H5: =G5*F5 -> 32000 | I5: =CEILING(G5*$I$1,1000) -> 64000 | J5: =IFERROR((I5-G5)/G5,"") -> 1 | K5: =I5*F5 -> 64000
A6: 46186 | B6: 1152 | C6: =VLOOKUP(B6,MAESTRA!I:K,2,0) -> *1152* | D6: =VLOOKUP(B6,MAESTRA!I:K,3,0) -> JEANS DAMA 4 BOTONES SIN BOLSILLO TALLA 8 | E6: R TREIK | F6: 1 | G6: 32000 | H6: =G6*F6 -> 32000 | I6: =CEILING(G6*$I$1,1000) -> 64000 | J6: =IFERROR((I6-G6)/G6,"") -> 1 | K6: =I6*F6 -> 64000
A7: 46186 | B7: 1146 | C7: =VLOOKUP(B7,MAESTRA!I:K,2,0) -> *1146* | D7: =VLOOKUP(B7,MAESTRA!I:K,3,0) -> JEANS DAMA 4 BOTONES TALLA 16 | E7: R TREIK | F7: 2 | G7: 32000 | H7: =G7*F7 -> 64000 | I7: =CEILING(G7*$I$1,1000) -> 64000 | J7: =IFERROR((I7-G7)/G7,"") -> 1 | K7: =I7*F7 -> 128000
A8: 46186 | B8: 1156 | C8: =VLOOKUP(B8,MAESTRA!I:K,2,0) -> *1156* | D8: =VLOOKUP(B8,MAESTRA!I:K,3,0) -> JEANS DAMA 4 BOTONES SIN BOLSILLO TALLA 16 | E8: R TREIK | F8: 1 | G8: 32000 | H8: =G8*F8 -> 32000 | I8: =CEILING(G8*$I$1,1000) -> 64000 | J8: =IFERROR((I8-G8)/G8,"") -> 1 | K8: =I8*F8 -> 64000
A9: 46186 | B9: 1114 | C9: =VLOOKUP(B9,MAESTRA!I:K,2,0) -> *1114* | D9: =VLOOKUP(B9,MAESTRA!I:K,3,0) -> JEANS DAMA 1 BOTON TALLA 12 | E9: R TREIK | F9: 1 | G9: 32000 | H9: =G9*F9 -> 32000 | I9: =CEILING(G9*$I$1,1000) -> 64000 | J9: =IFERROR((I9-G9)/G9,"") -> 1 | K9: =I9*F9 -> 64000
A10: 46186 | B10: 1145 | C10: =VLOOKUP(B10,MAESTRA!I:K,2,0) -> *1145* | D10: =VLOOKUP(B10,MAESTRA!I:K,3,0) -> JEANS DAMA 4 BOTONES TALLA 14 | E10: R TREIK | F10: 1 | G10: 32000 | H10: =G10*F10 -> 32000 | I10: =CEILING(G10*$I$1,1000) -> 64000 | J10: =IFERROR((I10-G10)/G10,"") -> 1 | K10: =I10*F10 -> 64000
A11: 46186 | B11: 1125 | C11: =VLOOKUP(B11,MAESTRA!I:K,2,0) -> *1125* | D11: =VLOOKUP(B11,MAESTRA!I:K,3,0) -> JEANS DAMA 1 BOTON BOTA RECTA TALLA 14 | E11: R TREIK | F11: 2 | G11: 38000 | H11: =G11*F11 -> 76000 | I11: =CEILING(G11*$I$1,1000) -> 76000 | J11: =IFERROR((I11-G11)/G11,"") -> 1 | K11: =I11*F11 -> 152000
A12: 46186 | B12: 1123 | C12: =VLOOKUP(B12,MAESTRA!I:K,2,0) -> *1123* | D12: =VLOOKUP(B12,MAESTRA!I:K,3,0) -> JEANS DAMA 1 BOTON BOTA RECTA TALLA 10 | E12: R TREIK | F12: 1 | G12: 38000 | H12: =G12*F12 -> 38000 | I12: =CEILING(G12*$I$1,1000) -> 76000 | J12: =IFERROR((I12-G12)/G12,"") -> 1 | K12: =I12*F12 -> 76000
A13: 46186 | B13: 1122 | C13: =VLOOKUP(B13,MAESTRA!I:K,2,0) -> *1122* | D13: =VLOOKUP(B13,MAESTRA!I:K,3,0) -> JEANS DAMA 1 BOTON BOTA RECTA TALLA 8 | E13: R TREIK | F13: 1 | G13: 38000 | H13: =G13*F13 -> 38000 | I13: =CEILING(G13*$I$1,1000) -> 76000 | J13: =IFERROR((I13-G13)/G13,"") -> 1 | K13: =I13*F13 -> 76000
A14: 46186 | B14: 1125 | C14: =VLOOKUP(B14,MAESTRA!I:K,2,0) -> *1125* | D14: =VLOOKUP(B14,MAESTRA!I:K,3,0) -> JEANS DAMA 1 BOTON BOTA RECTA TALLA 14 | E14: R TREIK | F14: 2 | G14: 32000 | H14: =G14*F14 -> 64000 | I14: =CEILING(G14*$I$1,1000) -> 64000 | J14: =IFERROR((I14-G14)/G14,"") -> 1 | K14: =I14*F14 -> 128000
A15: 46186 | B15: 1155 | C15: =VLOOKUP(B15,MAESTRA!I:K,2,0) -> *1155* | D15: =VLOOKUP(B15,MAESTRA!I:K,3,0) -> JEANS DAMA 4 BOTONES SIN BOLSILLO TALLA 14 | E15: R TREIK | F15: 1 | G15: 32000 | H15: =G15*F15 -> 32000 | I15: =CEILING(G15*$I$1,1000) -> 64000 | J15: =IFERROR((I15-G15)/G15,"") -> 1 | K15: =I15*F15 -> 64000
... A38: 46186 | B38: 5112131 | C38: =VLOOKUP(B38,MAESTRA!I:K,2,0) -> *5112131* | D38: =VLOOKUP(B38,MAESTRA!I:K,3,0) -> BERMUDAS DAMA DRILL TALLA VA | E38: GOLDTEX | F38: 9 | G38: 26000 | H38: =G38*F38 -> 234000 | I38: =CEILING(G38*$I$1,1000) -> 52000 | J38: =IFERROR((I38-G38)/G38,"") -> 1 | K38: =I38*F38 -> 468000
A39: 46186 | B39: 1212110 | C39: =VLOOKUP(B39,MAESTRA!I:K,2,0) -> *1212110* | D39: =VLOOKUP(B39,MAESTRA!I:K,3,0) -> PERFUMES DAMA PINK MINI | F39: 9 | G39: 5000 | H39: =G39*F39 -> 45000 | I39: =CEILING(G39*$I$1,1000) -> 10000 | J39: =IFERROR((I39-G39)/G39,"") -> 1 | K39: =I39*F39 -> 90000
A40: 46186 | B40: 4711600 | C40: =VLOOKUP(B40,MAESTRA!I:K,2,0) -> *4711600* | D40: =VLOOKUP(B40,MAESTRA!I:K,3,0) -> BRILLO DAMA LABIAL | F40: 6 | G40: 2500 | H40: =G40*F40 -> 15000 | I40: =CEILING(G40*$I$1,1000) -> 5000 | J40: =IFERROR((I40-G40)/G40,"") -> 1 | K40: =I40*F40 -> 30000
A41: 46186 | B41: 46100 | C41: =VLOOKUP(B41,MAESTRA!I:K,2,0) -> *46100* | D41: =VLOOKUP(B41,MAESTRA!I:K,3,0) -> SPLASH DAMA - | F41: 2 | G41: 8500 | H41: =G41*F41 -> 17000 | I41: =CEILING(G41*$I$1,1000) -> 17000 | J41: =IFERROR((I41-G41)/G41,"") -> 1 | K41: =I41*F41 -> 34000
A42: 46186 | B42: 46200 | C42: =VLOOKUP(B42,MAESTRA!I:K,2,0) -> *46200* | D42: =VLOOKUP(B42,MAESTRA!I:K,3,0) -> SPLASH CABALLERO - | F42: 2 | G42: 6500 | H42: =G42*F42 -> 13000 | I42: =CEILING(G42*$I$1,1000) -> 13000 | J42: =IFERROR((I42-G42)/G42,"") -> 1 | K42: =I42*F42 -> 26000
A43: 46186 | B43: 1438630 | C43: =VLOOKUP(B43,MAESTRA!I:K,2,0) -> *1438630* | D43: =VLOOKUP(B43,MAESTRA!I:K,3,0) -> GORRAS UNISEX COLOMBIA TALLA UN | E43: GORRAS LOS ANGELES | F43: 6 | G43: 28000 | H43: =G43*F43 -> 168000 | I43: =CEILING(G43*$I$1,1000) -> 56000 | J43: =IFERROR((I43-G43)/G43,"") -> 1 | K43: =I43*F43 -> 336000
A44: 46186 | B44: 14327530 | C44: =VLOOKUP(B44,MAESTRA!I:K,2,0) -> *14327530* | D44: =VLOOKUP(B44,MAESTRA!I:K,3,0) -> GORRAS UNISEX VARIOS TALLA UN | E44: GORRAS LOS ANGELES | F44: 17 | G44: 16000 | H44: =G44*F44 -> 272000 | I44: =CEILING(G44*$I$1,1000) -> 32000 | J44: =IFERROR((I44-G44)/G44,"") -> 1 | K44: =I44*F44 -> 544000
A45: 46186 | B45: 1532540 | C45: =VLOOKUP(B45,MAESTRA!I:K,2,0) -> *1532540* | D45: =VLOOKUP(B45,MAESTRA!I:K,3,0) -> MALETAS UNISEX SPRAY GROUND | E45: BALU BAGS | F45: 1 | G45: 60000 | H45: =G45*F45 -> 60000 | I45: =CEILING(G45*$I$1,1000) -> 120000 | J45: =IFERROR((I45-G45)/G45,"") -> 1 | K45: =I45*F45 -> 120000
A46: 46186 | B46: 161480 | C46: =VLOOKUP(B46,MAESTRA!I:K,2,0) -> *161480* | D46: =VLOOKUP(B46,MAESTRA!I:K,3,0) -> LLAVEROS DAMA BOMBA | E46: BALU BAGS | F46: 6 | G46: 6000 | H46: =G46*F46 -> 36000 | I46: =CEILING(G46*$I$1,1000) -> 12000 | J46: =IFERROR((I46-G46)/G46,"") -> 1 | K46: =I46*F46 -> 72000
A47: 46186 | B47: 161720 | C47: =VLOOKUP(B47,MAESTRA!I:K,2,0) -> *161720* | D47: =VLOOKUP(B47,MAESTRA!I:K,3,0) -> LLAVEROS DAMA CEREZAS BRILLANTE | E47: BALU BAGS | F47: 2 | G47: 17000 | H47: =G47*F47 -> 34000 | I47: =CEILING(G47*$I$1,1000) -> 34000 | J47: =IFERROR((I47-G47)/G47,"") -> 1 | K47: =I47*F47 -> 68000
A48: 46186 | B48: 171460 | C48: =VLOOKUP(B48,MAESTRA!I:K,2,0) -> *171460* | D48: =VLOOKUP(B48,MAESTRA!I:K,3,0) -> BOLSOS DAMA BAUL | E48: BALU BAGS | F48: 1 | G48: 45000 | H48: =G48*F48 -> 45000 | I48: =CEILING(G48*$I$1,1000) -> 90000 | J48: =IFERROR((I48-G48)/G48,"") -> 1 | K48: =I48*F48 -> 90000
A49: 46186 | B49: 221030 | C49: =VLOOKUP(B49,MAESTRA!I:K,2,0) -> *221030* | D49: =VLOOKUP(B49,MAESTRA!I:K,3,0) -> CORREAS DAMA - TALLA UN | E49: BALU BAGS | F49: 6 | G49: 9000 | H49: =G49*F49 -> 54000 | I49: =CEILING(G49*$I$1,1000) -> 18000 | J49: =IFERROR((I49-G49)/G49,"") -> 1 | K49: =I49*F49 -> 108000
A50: 46186 | B50: 171570 | C50: =VLOOKUP(B50,MAESTRA!I:K,2,0) -> *171570* | D50: =VLOOKUP(B50,MAESTRA!I:K,3,0) -> BOLSOS DAMA CADENA DORADA | E50: BALU BAGS | F50: 1 | G50: 30000 | H50: =G50*F50 -> 30000 | I50: =CEILING(G50*$I$1,1000) -> 60000 | J50: =IFERROR((I50-G50)/G50,"") -> 1 | K50: =I50*F50 -> 60000
A51: 46186 | B51: 183130 | C51: =VLOOKUP(B51,MAESTRA!I:K,2,0) -> *183130* | D51: =VLOOKUP(B51,MAESTRA!I:K,3,0) -> CARRIEL UNISEX ADIDAS | E51: BALU BAGS | F51: 2 | G51: 24000 | H51: =G51*F51 -> 48000 | I51: =CEILING(G51*$I$1,1000) -> 48000 | J51: =IFERROR((I51-G51)/G51,"") -> 1 | K51: =I51*F51 -> 96000
A52: 46186 | B52: 1921180 | C52: =VLOOKUP(B52,MAESTRA!I:K,2,0) -> *1921180* | D52: =VLOOKUP(B52,MAESTRA!I:K,3,0) -> PECHERAS CABALLERO DIFERENTES MARCAS | E52: BALU BAGS | F52: 3 | G52: 24000 | H52: =G52*F52 -> 72000 | I52: =CEILING(G52*$I$1,1000) -> 48000 | J52: =IFERROR((I52-G52)/G52,"") -> 1 | K52: =I52*F52 -> 144000
A53: 46186 | B53: 201540 | C53: =VLOOKUP(B53,MAESTRA!I:K,2,0) -> *201540* | D53: =VLOOKUP(B53,MAESTRA!I:K,3,0) -> CANGUROS DAMA BRILLO | E53: BALU BAGS | F53: 1 | G53: 38000 | H53: =G53*F53 -> 38000 | I53: =CEILING(G53*$I$1,1000) -> 76000 | J53: =IFERROR((I53-G53)/G53,"") -> 1 | K53: =I53*F53 -> 76000
A54: 46186 | B54: 203130 | C54: =VLOOKUP(B54,MAESTRA!I:K,2,0) -> *203130* | D54: =VLOOKUP(B54,MAESTRA!I:K,3,0) -> CANGUROS UNISEX ADIDAS | E54: BALU BAGS | F54: 2 | G54: 20000 | H54: =G54*F54 -> 40000 | I54: =CEILING(G54*$I$1,1000) -> 40000 | J54: =IFERROR((I54-G54)/G54,"") -> 1 | K54: =I54*F54 -> 80000
... A262: 46186 | B262: 1153 | C262: =VLOOKUP(B262,MAESTRA!I:K,2,0) -> *1153* | D262: =VLOOKUP(B262,MAESTRA!I:K,3,0) -> JEANS DAMA 4 BOTONES SIN BOLSILLO TALLA 10 | E262: R TREIK | F262: 1 | G262: 32000 | H262: =G262*F262 -> 32000 | I262: =CEILING(G262*$I$1,1000) -> 64000 | J262: =IFERROR((I262-G262)/G262,"") -> 1 | K262: =I262*F262 -> 64000
A263: 46186 | B263: 35211328 | C263: =VLOOKUP(B263,MAESTRA!I:K,2,0) -> *35211328* | D263: =VLOOKUP(B263,MAESTRA!I:K,3,0) -> PANTALONETAS CABALLERO DEPORTIVA TALLA S-M | F263: 1 | G263: 22000 | H263: =G263*F263 -> 22000 | I263: =CEILING(G263*$I$1,1000) -> 44000 | J263: =IFERROR((I263-G263)/G263,"") -> 1 | K263: =I263*F263 -> 44000
A264: 46186 | B264: 2832531 | C264: =VLOOKUP(B264,MAESTRA!I:K,2,0) -> *2832531* | D264: =VLOOKUP(B264,MAESTRA!I:K,3,0) -> ANILLOS UNISEX ANILLO 1 TALLA VA | E264: DIVAS | F264: 5 | G264: 10500 | H264: =G264*F264 -> 52500 | I264: =CEILING(G264*$I$1,1000) -> 21000 | J264: =IFERROR((I264-G264)/G264,"") -> 1 | K264: =I264*F264 -> 105000
A265: 46186 | B265: 2832631 | C265: =VLOOKUP(B265,MAESTRA!I:K,2,0) -> *2832631* | D265: =VLOOKUP(B265,MAESTRA!I:K,3,0) -> ANILLOS UNISEX ANILLO 2 TALLA VA | E265: DIVAS | F265: 4 | G265: 6500 | H265: =G265*F265 -> 26000 | I265: =CEILING(G265*$I$1,1000) -> 13000 | J265: =IFERROR((I265-G265)/G265,"") -> 1 | K265: =I265*F265 -> 52000
A266: 46186 | B266: 2832731 | C266: =VLOOKUP(B266,MAESTRA!I:K,2,0) -> *2832731* | D266: =VLOOKUP(B266,MAESTRA!I:K,3,0) -> ANILLOS UNISEX ANILLO 3 TALLA VA | E266: DIVAS | F266: 1 | G266: 4500 | H266: =G266*F266 -> 4500 | I266: =CEILING(G266*$I$1,1000) -> 9000 | J266: =IFERROR((I266-G266)/G266,"") -> 1 | K266: =I266*F266 -> 9000
A267: 46186 | B267: 2832831 | C267: =VLOOKUP(B267,MAESTRA!I:K,2,0) -> *2832831* | D267: =VLOOKUP(B267,MAESTRA!I:K,3,0) -> ANILLOS UNISEX ANILLO 4 TALLA VA | E267: DIVAS | F267: 2 | G267: 8000 | H267: =G267*F267 -> 16000 | I267: =CEILING(G267*$I$1,1000) -> 16000 | J267: =IFERROR((I267-G267)/G267,"") -> 1 | K267: =I267*F267 -> 32000
A268: 46186 | B268: 2832931 | C268: =VLOOKUP(B268,MAESTRA!I:K,2,0) -> *2832931* | D268: =VLOOKUP(B268,MAESTRA!I:K,3,0) -> ANILLOS UNISEX ANILLO 5 TALLA VA | E268: DIVAS | F268: 1 | G268: 11000 | H268: =G268*F268 -> 11000 | I268: =CEILING(G268*$I$1,1000) -> 22000 | J268: =IFERROR((I268-G268)/G268,"") -> 1 | K268: =I268*F268 -> 22000
A269: 46186 | B269: 2833031 | C269: =VLOOKUP(B269,MAESTRA!I:K,2,0) -> *2833031* | D269: =VLOOKUP(B269,MAESTRA!I:K,3,0) -> ANILLOS UNISEX ANILLO 6 TALLA VA | E269: DIVAS | F269: 1 | G269: 6000 | H269: =G269*F269 -> 6000 | I269: =CEILING(G269*$I$1,1000) -> 12000 | J269: =IFERROR((I269-G269)/G269,"") -> 1 | K269: =I269*F269 -> 12000
A270: 46186 | B270: 2833131 | C270: =VLOOKUP(B270,MAESTRA!I:K,2,0) -> *2833131* | D270: =VLOOKUP(B270,MAESTRA!I:K,3,0) -> ANILLOS UNISEX ANILLO 7 TALLA VA | E270: DIVAS | F270: 1 | G270: 9000 | H270: =G270*F270 -> 9000 | I270: =CEILING(G270*$I$1,1000) -> 18000 | J270: =IFERROR((I270-G270)/G270,"") -> 1 | K270: =I270*F270 -> 18000
A271: 46186 | B271: 29321331 | C271: =VLOOKUP(B271,MAESTRA!I:K,2,0) -> *29321331* | D271: =VLOOKUP(B271,MAESTRA!I:K,3,0) -> CABELLO-ACCESORIOS UNISEX PINZAS CABELLO TALLA VA | E271: DIVAS | F271: 3 | G271: 2000 | H271: =G271*F271 -> 6000 | I271: =CEILING(G271*$I$1,1000) -> 4000 | J271: =IFERROR((I271-G271)/G271,"") -> 1 | K271: =I271*F271 -> 12000
A272: 46186 | B272: 29319231 | C272: =VLOOKUP(B272,MAESTRA!I:K,2,0) -> *29319231* | D272: =VLOOKUP(B272,MAESTRA!I:K,3,0) -> CABELLO-ACCESORIOS UNISEX MOÑAS COLERA TALLA VA | E272: DIVAS | F272: 4 | G272: 600 | H272: =G272*F272 -> 2400 | I272: =CEILING(G272*$I$1,1000) -> 2000 | J272: =IFERROR((I272-G272)/G272,"") -> 2.3333333 | K272: =I272*F272 -> 8000
A273: 46186 | B273: 29311731 | C273: =VLOOKUP(B273,MAESTRA!I:K,2,0) -> *29311731* | D273: =VLOOKUP(B273,MAESTRA!I:K,3,0) -> CABELLO-ACCESORIOS UNISEX DIADEMA MEDIANA TALLA VA | E273: DIVAS | F273: 3 | G273: 6000 | H273: =G273*F273 -> 18000 | I273: =CEILING(G273*$I$1,1000) -> 12000 | J273: =IFERROR((I273-G273)/G273,"") -> 1 | K273: =I273*F273 -> 36000
A274: 46186 | B274: 29311631 | C274: =VLOOKUP(B274,MAESTRA!I:K,2,0) -> *29311631* | D274: =VLOOKUP(B274,MAESTRA!I:K,3,0) -> CABELLO-ACCESORIOS UNISEX DIADEMA DELGADA TALLA VA | E274: DIVAS | F274: 6 | G274: 3000 | H274: =G274*F274 -> 18000 | I274: =CEILING(G274*$I$1,1000) -> 6000 | J274: =IFERROR((I274-G274)/G274,"") -> 1 | K274: =I274*F274 -> 36000
A275: 46186 | B275: 3037931 | C275: =VLOOKUP(B275,MAESTRA!I:K,2,0) -> *3037931* | D275: =VLOOKUP(B275,MAESTRA!I:K,3,0) -> COLLAR UNISEX COLLAR 1 TALLA VA | E275: DIVAS | F275: 2 | G275: 16000 | H275: =G275*F275 -> 32000 | I275: =CEILING(G275*$I$1,1000) -> 32000 | J275: =IFERROR((I275-G275)/G275,"") -> 1 | K275: =I275*F275 -> 64000
... A310: 46186 | B310: 32326631 | C310: =VLOOKUP(B310,MAESTRA!I:K,2,0) -> *32326631* | D310: =VLOOKUP(B310,MAESTRA!I:K,3,0) -> TOPOS UNISEX TOPO SEGURIDAD TALLA VA | E310: DIVAS | F310: 1 | G310: 4000 | H310: =G310*F310 -> 4000 | I310: =CEILING(G310*$I$1,1000) -> 8000 | J310: =IFERROR((I310-G310)/G310,"") -> 1 | K310: =I310*F310 -> 8000
A311: 46186 | B311: 46223031 | C311: =VLOOKUP(B311,MAESTRA!I:K,2,0) -> *46223031* | D311: =VLOOKUP(B311,MAESTRA!I:K,3,0) -> SPLASH CABALLERO PULSERA COMBO TALLA VA | F311: 5 | G311: 12500 | H311: =G311*F311 -> 62500 | I311: =CEILING(G311*$I$1,1000) -> 25000 | J311: =IFERROR((I311-G311)/G311,"") -> 1 | K311: =I311*F311 -> 125000
A312: 46186 | B312: 46223031 | C312: =VLOOKUP(B312,MAESTRA!I:K,2,0) -> *46223031* | D312: =VLOOKUP(B312,MAESTRA!I:K,3,0) -> SPLASH CABALLERO PULSERA COMBO TALLA VA | F312: 4 | G312: 17000 | H312: =G312*F312 -> 68000 | I312: =CEILING(G312*$I$1,1000) -> 34000 | J312: =IFERROR((I312-G312)/G312,"") -> 1 | K312: =I312*F312 -> 136000
A313: 46186 | B313: 2639327 | C313: =VLOOKUP(B313,MAESTRA!I:K,2,0) -> *2639327* | D313: =VLOOKUP(B313,MAESTRA!I:K,3,0) -> BUSOS UNISEX CON CAPOTA ESTAMPADO CREMALLERA TALLA S | E313: ATHLETIC BODEGA MEDELLÍN | F313: 3 | G313: 24000 | H313: =G313*F313 -> 72000 | I313: =CEILING(G313*$I$1,1000) -> 48000 | J313: =IFERROR((I313-G313)/G313,"") -> 1 | K313: =I313*F313 -> 144000
A314: 46186 | B314: 2631925 | C314: =VLOOKUP(B314,MAESTRA!I:K,2,0) -> *2631925* | D314: =VLOOKUP(B314,MAESTRA!I:K,3,0) -> BUSOS UNISEX ALGODON CON CAPOTA ESTAMPADO CREMALLERA TALLA M | F314: 3 | G314: 24000 | H314: =G314*F314 -> 72000 | I314: =CEILING(G314*$I$1,1000) -> 48000 | J314: =IFERROR((I314-G314)/G314,"") -> 1 | K314: =I314*F314 -> 144000
A315: 46186 | B315: 2631923 | C315: =VLOOKUP(B315,MAESTRA!I:K,2,0) -> *2631923* | D315: =VLOOKUP(B315,MAESTRA!I:K,3,0) -> BUSOS UNISEX ALGODON CON CAPOTA ESTAMPADO CREMALLERA TALLA L | F315: 3 | G315: 24000 | H315: =G315*F315 -> 72000 | I315: =CEILING(G315*$I$1,1000) -> 48000 | J315: =IFERROR((I315-G315)/G315,"") -> 1 | K315: =I315*F315 -> 144000
A316: 46186 | B316: 2631932 | C316: =VLOOKUP(B316,MAESTRA!I:K,2,0) -> *2631932* | D316: =VLOOKUP(B316,MAESTRA!I:K,3,0) -> BUSOS UNISEX ALGODON CON CAPOTA ESTAMPADO CREMALLERA TALLA XL | F316: 2 | G316: 24000 | H316: =G316*F316 -> 48000 | I316: =CEILING(G316*$I$1,1000) -> 48000 | J316: =IFERROR((I316-G316)/G316,"") -> 1 | K316: =I316*F316 -> 96000
A317: 46186 | B317: 2631827 | C317: =VLOOKUP(B317,MAESTRA!I:K,2,0) -> *2631827* | D317: =VLOOKUP(B317,MAESTRA!I:K,3,0) -> BUSOS UNISEX ALGODON CAPOTA ESTAMPADO TALLA S | F317: 3 | G317: 24000 | H317: =G317*F317 -> 72000 | I317: =CEILING(G317*$I$1,1000) -> 48000 | J317: =IFERROR((I317-G317)/G317,"") -> 1 | K317: =I317*F317 -> 144000
A318: 46186 | B318: 2631825 | C318: =VLOOKUP(B318,MAESTRA!I:K,2,0) -> *2631825* | D318: =VLOOKUP(B318,MAESTRA!I:K,3,0) -> BUSOS UNISEX ALGODON CAPOTA ESTAMPADO TALLA M | F318: 2 | G318: 24000 | H318: =G318*F318 -> 48000 | I318: =CEILING(G318*$I$1,1000) -> 48000 | J318: =IFERROR((I318-G318)/G318,"") -> 1 | K318: =I318*F318 -> 96000
A319: 46186 | B319: 2631823 | C319: =VLOOKUP(B319,MAESTRA!I:K,2,0) -> *2631823* | D319: =VLOOKUP(B319,MAESTRA!I:K,3,0) -> BUSOS UNISEX ALGODON CAPOTA ESTAMPADO TALLA L | F319: 3 | G319: 24000 | H319: =G319*F319 -> 72000 | I319: =CEILING(G319*$I$1,1000) -> 48000 | J319: =IFERROR((I319-G319)/G319,"") -> 1 | K319: =I319*F319 -> 144000
A320: 46186 | B320: 2631832 | C320: =VLOOKUP(B320,MAESTRA!I:K,2,0) -> *2631832* | D320: =VLOOKUP(B320,MAESTRA!I:K,3,0) -> BUSOS UNISEX ALGODON CAPOTA ESTAMPADO TALLA XL | F320: 2 | G320: 24000 | H320: =G320*F320 -> 48000 | I320: =CEILING(G320*$I$1,1000) -> 48000 | J320: =IFERROR((I320-G320)/G320,"") -> 1 | K320: =I320*F320 -> 96000
A321: 46186 | B321: 2632127 | C321: =VLOOKUP(B321,MAESTRA!I:K,2,0) -> *2632127* | D321: =VLOOKUP(B321,MAESTRA!I:K,3,0) -> BUSOS UNISEX ALGODON CUELLO REDONDO ESTAMPADO TALLA S | F321: 2 | G321: 22000 | H321: =G321*F321 -> 44000 | I321: =CEILING(G321*$I$1,1000) -> 44000 | J321: =IFERROR((I321-G321)/G321,"") -> 1 | K321: =I321*F321 -> 88000
A322: 46186 | B322: 2632125 | C322: =VLOOKUP(B322,MAESTRA!I:K,2,0) -> *2632125* | D322: =VLOOKUP(B322,MAESTRA!I:K,3,0) -> BUSOS UNISEX ALGODON CUELLO REDONDO ESTAMPADO TALLA M | F322: 3 | G322: 22000 | H322: =G322*F322 -> 66000 | I322: =CEILING(G322*$I$1,1000) -> 44000 | J322: =IFERROR((I322-G322)/G322,"") -> 1 | K322: =I322*F322 -> 132000
A323: 46186 | B323: 2632123 | C323: =VLOOKUP(B323,MAESTRA!I:K,2,0) -> *2632123* | D323: =VLOOKUP(B323,MAESTRA!I:K,3,0) -> BUSOS UNISEX ALGODON CUELLO REDONDO ESTAMPADO TALLA L | F323: 2 | G323: 22000 | H323: =G323*F323 -> 44000 | I323: =CEILING(G323*$I$1,1000) -> 44000 | J323: =IFERROR((I323-G323)/G323,"") -> 1 | K323: =I323*F323 -> 88000
A324: 46186 | B324: 2632132 | C324: =VLOOKUP(B324,MAESTRA!I:K,2,0) -> *2632132* | D324: =VLOOKUP(B324,MAESTRA!I:K,3,0) -> BUSOS UNISEX ALGODON CUELLO REDONDO ESTAMPADO TALLA XL | F324: 2 | G324: 22000 | H324: =G324*F324 -> 44000 | I324: =CEILING(G324*$I$1,1000) -> 44000 | J324: =IFERROR((I324-G324)/G324,"") -> 1 | K324: =I324*F324 -> 88000
A325: 46186 | B325: 2632134 | C325: =VLOOKUP(B325,MAESTRA!I:K,2,0) -> *2632134* | D325: =VLOOKUP(B325,MAESTRA!I:K,3,0) -> BUSOS UNISEX ALGODON CUELLO REDONDO ESTAMPADO TALLA XXL | F325: 4 | G325: 22000 | H325: =G325*F325 -> 88000 | I325: =CEILING(G325*$I$1,1000) -> 44000 | J325: =IFERROR((I325-G325)/G325,"") -> 1 | K325: =I325*F325 -> 176000
... A333: 46186 | B333: 11324932 | C333: =VLOOKUP(B333,MAESTRA!I:K,2,0) -> *11324932* | D333: =VLOOKUP(B333,MAESTRA!I:K,3,0) -> CAMISETAS UNISEX SEDA FRÍA TALLA XL | F333: 2 | G333: 35000 | H333: =G333*F333 -> 70000 | I333: =CEILING(G333*$I$1,1000) -> 70000 | J333: =IFERROR((I333-G333)/G333,"") -> 1 | K333: =I333*F333 -> 140000
A334: 46186 | B334: 1116 | C334: =VLOOKUP(B334,MAESTRA!I:K,2,0) -> *1116* | D334: =VLOOKUP(B334,MAESTRA!I:K,3,0) -> JEANS DAMA 1 BOTON TALLA 16 | E334: R TREIK | F334: 1 | G334: 32000 | H334: =G334*F334 -> 32000 | I334: =CEILING(G334*$I$1,1000) -> 64000 | J334: =IFERROR((I334-G334)/G334,"") -> 1 | K334: =I334*F334 -> 64000
A335: 46186 | B335: 1112 | C335: =VLOOKUP(B335,MAESTRA!I:K,2,0) -> *1112* | D335: =VLOOKUP(B335,MAESTRA!I:K,3,0) -> JEANS DAMA 1 BOTON TALLA 8 | E335: R TREIK | F335: 2 | G335: 32000 | H335: =G335*F335 -> 64000 | I335: =CEILING(G335*$I$1,1000) -> 64000 | J335: =IFERROR((I335-G335)/G335,"") -> 1 | K335: =I335*F335 -> 128000
A336: 46186 | B336: 1143 | C336: =VLOOKUP(B336,MAESTRA!I:K,2,0) -> *1143* | D336: =VLOOKUP(B336,MAESTRA!I:K,3,0) -> JEANS DAMA 4 BOTONES TALLA 10 | E336: R TREIK | F336: 1 | G336: 32000 | H336: =G336*F336 -> 32000 | I336: =CEILING(G336*$I$1,1000) -> 64000 | J336: =IFERROR((I336-G336)/G336,"") -> 1 | K336: =I336*F336 -> 64000
A337: 46186 | B337: 512395 | C337: =VLOOKUP(B337,MAESTRA!I:K,2,0) -> *512395* | D337: =VLOOKUP(B337,MAESTRA!I:K,3,0) -> BERMUDAS DAMA RODILLA TALLA 14 | E337: R TREIK | F337: 1 | G337: 32000 | H337: =G337*F337 -> 32000 | I337: =CEILING(G337*$I$1,1000) -> 64000 | J337: =IFERROR((I337-G337)/G337,"") -> 1 | K337: =I337*F337 -> 64000
A338: 46186 | B338: 512396 | C338: =VLOOKUP(B338,MAESTRA!I:K,2,0) -> *512396* | D338: =VLOOKUP(B338,MAESTRA!I:K,3,0) -> BERMUDAS DAMA RODILLA TALLA 16 | E338: R TREIK | F338: 1 | G338: 32000 | H338: =G338*F338 -> 32000 | I338: =CEILING(G338*$I$1,1000) -> 64000 | J338: =IFERROR((I338-G338)/G338,"") -> 1 | K338: =I338*F338 -> 64000
A339: 46186 | B339: 512394 | C339: =VLOOKUP(B339,MAESTRA!I:K,2,0) -> *512394* | D339: =VLOOKUP(B339,MAESTRA!I:K,3,0) -> BERMUDAS DAMA RODILLA TALLA 12 | E339: R TREIK | F339: 1 | G339: 32000 | H339: =G339*F339 -> 32000 | I339: =CEILING(G339*$I$1,1000) -> 64000 | J339: =IFERROR((I339-G339)/G339,"") -> 1 | K339: =I339*F339 -> 64000
A340: 46186 | B340: 512393 | C340: =VLOOKUP(B340,MAESTRA!I:K,2,0) -> *512393* | D340: =VLOOKUP(B340,MAESTRA!I:K,3,0) -> BERMUDAS DAMA RODILLA TALLA 10 | E340: R TREIK | F340: 1 | G340: 32000 | H340: =G340*F340 -> 32000 | I340: =CEILING(G340*$I$1,1000) -> 64000 | J340: =IFERROR((I340-G340)/G340,"") -> 1 | K340: =I340*F340 -> 64000
A341: 46186 | B341: 1128727 | C341: =VLOOKUP(B341,MAESTRA!I:K,2,0) -> *1128727* | D341: =VLOOKUP(B341,MAESTRA!I:K,3,0) -> CAMISETAS CABALLERO COLOMBIA 1.1 LOCAL TALLA S | E341: ADIDAS | F341: 4 | G341: 27000 | H341: =G341*F341 -> 108000 | I341: =CEILING(G341*$I$1,1000) -> 54000 | J341: =IFERROR((I341-G341)/G341,"") -> 1 | K341: =I341*F341 -> 216000
A342: 46186 | B342: 1128725 | C342: =VLOOKUP(B342,MAESTRA!I:K,2,0) -> *1128725* | D342: =VLOOKUP(B342,MAESTRA!I:K,3,0) -> CAMISETAS CABALLERO COLOMBIA 1.1 LOCAL TALLA M | E342: ADIDAS | F342: 5 | G342: 27000 | H342: =G342*F342 -> 135000 | I342: =CEILING(G342*$I$1,1000) -> 54000 | J342: =IFERROR((I342-G342)/G342,"") -> 1 | K342: =I342*F342 -> 270000
A343: 46186 | B343: 1128723 | C343: =VLOOKUP(B343,MAESTRA!I:K,2,0) -> *1128723* | D343: =VLOOKUP(B343,MAESTRA!I:K,3,0) -> CAMISETAS CABALLERO COLOMBIA 1.1 LOCAL TALLA L | E343: ADIDAS | F343: 6 | G343: 27000 | H343: =G343*F343 -> 162000 | I343: =CEILING(G343*$I$1,1000) -> 54000 | J343: =IFERROR((I343-G343)/G343,"") -> 1 | K343: =I343*F343 -> 324000
A344: 46186 | B344: 1128732 | C344: =VLOOKUP(B344,MAESTRA!I:K,2,0) -> *1128732* | D344: =VLOOKUP(B344,MAESTRA!I:K,3,0) -> CAMISETAS CABALLERO COLOMBIA 1.1 LOCAL TALLA XL | E344: ADIDAS | F344: 4 | G344: 27000 | H344: =G344*F344 -> 108000 | I344: =CEILING(G344*$I$1,1000) -> 54000 | J344: =IFERROR((I344-G344)/G344,"") -> 1 | K344: =I344*F344 -> 216000
A345: 46186 | B345: 1128734 | C345: =VLOOKUP(B345,MAESTRA!I:K,2,0) -> *1128734* | D345: =VLOOKUP(B345,MAESTRA!I:K,3,0) -> CAMISETAS CABALLERO COLOMBIA 1.1 LOCAL TALLA XXL | E345: ADIDAS | F345: 4 | G345: 27000 | H345: =G345*F345 -> 108000 | I345: =CEILING(G345*$I$1,1000) -> 54000 | J345: =IFERROR((I345-G345)/G345,"") -> 1 | K345: =I345*F345 -> 216000
... A411: 46186 | B411: 11222032 | C411: =VLOOKUP(B411,MAESTRA!I:K,2,0) -> *11222032* | D411: =VLOOKUP(B411,MAESTRA!I:K,3,0) -> CAMISETAS CABALLERO POLO TIPO GALLETA TALLA XL | E411: PETRO AZUL | F411: 2 | G411: 32000 | H411: =G411*F411 -> 64000 | I411: =CEILING(G411*$I$1,1000) -> 64000 | J411: =IFERROR((I411-G411)/G411,"") -> 1 | K411: =I411*F411 -> 128000
A412: 46186 | B412: 11117030 | C412: =VLOOKUP(B412,MAESTRA!I:K,2,0) -> *11117030* | D412: =VLOOKUP(B412,MAESTRA!I:K,3,0) -> CAMISETAS DAMA LICRADA MANGA CORTA TALLA UN | F412: 5 | G412: 10000 | H412: =G412*F412 -> 50000 | I412: =CEILING(G412*$I$1,1000) -> 20000 | J412: =IFERROR((I412-G412)/G412,"") -> 1 | K412: =I412*F412 -> 100000
A413: 46186 | B413: 26117130 | C413: =VLOOKUP(B413,MAESTRA!I:K,2,0) -> *26117130* | D413: =VLOOKUP(B413,MAESTRA!I:K,3,0) -> BUSOS DAMA LICRADA MANGA LARGA TALLA UN | F413: 8 | G413: 10000 | H413: =G413*F413 -> 80000 | I413: =CEILING(G413*$I$1,1000) -> 20000 | J413: =IFERROR((I413-G413)/G413,"") -> 1 | K413: =I413*F413 -> 160000
A414: 46186 | B414: 11126230 | C414: =VLOOKUP(B414,MAESTRA!I:K,2,0) -> *11126230* | D414: =VLOOKUP(B414,MAESTRA!I:K,3,0) -> CAMISETAS DAMA TIPO GALLETA TALLA UN | F414: 3 | G414: 10000 | H414: =G414*F414 -> 30000 | I414: =CEILING(G414*$I$1,1000) -> 20000 | J414: =IFERROR((I414-G414)/G414,"") -> 1 | K414: =I414*F414 -> 60000
A415: 46186 | B415: 1116430 | C415: =VLOOKUP(B415,MAESTRA!I:K,2,0) -> *1116430* | D415: =VLOOKUP(B415,MAESTRA!I:K,3,0) -> CAMISETAS DAMA CAMISETA ESTAMPADO ALGODON LARGA TALLA UN | F415: 3 | G415: 10000 | H415: =G415*F415 -> 30000 | I415: =CEILING(G415*$I$1,1000) -> 20000 | J415: =IFERROR((I415-G415)/G415,"") -> 1 | K415: =I415*F415 -> 60000
A416: 46186 | B416: 1112030 | C416: =VLOOKUP(B416,MAESTRA!I:K,2,0) -> *1112030* | D416: =VLOOKUP(B416,MAESTRA!I:K,3,0) -> CAMISETAS DAMA ALGODON CORTA E U TALLA UN | F416: 4 | G416: 10000 | H416: =G416*F416 -> 40000 | I416: =CEILING(G416*$I$1,1000) -> 20000 | J416: =IFERROR((I416-G416)/G416,"") -> 1 | K416: =I416*F416 -> 80000
A417: 46186 | B417: 38117230 | C417: =VLOOKUP(B417,MAESTRA!I:K,2,0) -> *38117230* | D417: =VLOOKUP(B417,MAESTRA!I:K,3,0) -> BODY DAMA LICRADO TALLA UN | F417: 1 | G417: 10000 | H417: =G417*F417 -> 10000 | I417: =CEILING(G417*$I$1,1000) -> 20000 | J417: =IFERROR((I417-G417)/G417,"") -> 1 | K417: =I417*F417 -> 20000
A418: 46186 | B418: 37117430 | C418: =VLOOKUP(B418,MAESTRA!I:K,2,0) -> *37117430* | D418: =VLOOKUP(B418,MAESTRA!I:K,3,0) -> ESQUELETO DAMA LICRADO LARGO TALLA UN | F418: 8 | G418: 10000 | H418: =G418*F418 -> 80000 | I418: =CEILING(G418*$I$1,1000) -> 20000 | J418: =IFERROR((I418-G418)/G418,"") -> 1 | K418: =I418*F418 -> 160000
A419: 46186 | B419: 37117330 | C419: =VLOOKUP(B419,MAESTRA!I:K,2,0) -> *37117330* | D419: =VLOOKUP(B419,MAESTRA!I:K,3,0) -> ESQUELETO DAMA LICRADO CORTOS TALLA UN | F419: 10 | G419: 10000 | H419: =G419*F419 -> 100000 | I419: =CEILING(G419*$I$1,1000) -> 20000 | J419: =IFERROR((I419-G419)/G419,"") -> 1 | K419: =I419*F419 -> 200000
A420: 46186 | B420: 37127330 | C420: =VLOOKUP(B420,MAESTRA!I:K,2,0) -> *37127330* | D420: =VLOOKUP(B420,MAESTRA!I:K,3,0) -> ESQUELETO DAMA UN SOLO HOMBRO TALLA UN | F420: 3 | G420: 10000 | H420: =G420*F420 -> 30000 | I420: =CEILING(G420*$I$1,1000) -> 20000 | J420: =IFERROR((I420-G420)/G420,"") -> 1 | K420: =I420*F420 -> 60000
A421: 46186 | B421: 26319427 | C421: =VLOOKUP(B421,MAESTRA!I:K,2,0) -> *26319427* | D421: =VLOOKUP(B421,MAESTRA!I:K,3,0) -> BUSOS UNISEX MUNDIAL 2026 TALLA S | E421: CREACIONES DANNY - - CLEOTILDE | F421: 1 | G421: 35000 | H421: =G421*F421 -> 35000 | I421: =CEILING(G421*$I$1,1000) -> 70000 | J421: =IFERROR((I421-G421)/G421,"") -> 1 | K421: =I421*F421 -> 70000
A422: 46186 | B422: 26319425 | C422: =VLOOKUP(B422,MAESTRA!I:K,2,0) -> *26319425* | D422: =VLOOKUP(B422,MAESTRA!I:K,3,0) -> BUSOS UNISEX MUNDIAL 2026 TALLA M | E422: CREACIONES DANNY - - CLEOTILDE | F422: 2 | G422: 35000 | H422: =G422*F422 -> 70000 | I422: =CEILING(G422*$I$1,1000) -> 70000 | J422: =IFERROR((I422-G422)/G422,"") -> 1 | K422: =I422*F422 -> 140000
A423: 46186 | B423: 26319423 | C423: =VLOOKUP(B423,MAESTRA!I:K,2,0) -> *26319423* | D423: =VLOOKUP(B423,MAESTRA!I:K,3,0) -> BUSOS UNISEX MUNDIAL 2026 TALLA L | E423: CREACIONES DANNY - - CLEOTILDE | F423: 2 | G423: 35000 | H423: =G423*F423 -> 70000 | I423: =CEILING(G423*$I$1,1000) -> 70000 | J423: =IFERROR((I423-G423)/G423,"") -> 1 | K423: =I423*F423 -> 140000
A424: 46186 | B424: 26319432 | C424: =VLOOKUP(B424,MAESTRA!I:K,2,0) -> *26319432* | D424: =VLOOKUP(B424,MAESTRA!I:K,3,0) -> BUSOS UNISEX MUNDIAL 2026 TALLA XL | E424: CREACIONES DANNY - - CLEOTILDE | F424: 1 | G424: 35000 | H424: =G424*F424 -> 35000 | I424: =CEILING(G424*$I$1,1000) -> 70000 | J424: =IFERROR((I424-G424)/G424,"") -> 1 | K424: =I424*F424 -> 70000
A425: 46186 | B425: 39124730 | C425: =VLOOKUP(B425,MAESTRA!I:K,2,0) -> *39124730* | D425: =VLOOKUP(B425,MAESTRA!I:K,3,0) -> SACO DAMA SACO ABIERTO TALLA UN | E425: ECUATORIANOS | F425: 2 | G425: 33000 | H425: =G425*F425 -> 66000 | I425: =CEILING(G425*$I$1,1000) -> 66000 | J425: =IFERROR((I425-G425)/G425,"") -> 1 | K425: =I425*F425 -> 132000
A426: 46186 | B426: 26120730 | C426: =VLOOKUP(B426,MAESTRA!I:K,2,0) -> *26120730* | D426: =VLOOKUP(B426,MAESTRA!I:K,3,0) -> BUSOS DAMA PEPAS CHINILLO TALLA UN | E426: ECUATORIANOS | F426: 3 | G426: 25000 | H426: =G426*F426 -> 75000 | I426: =CEILING(G426*$I$1,1000) -> 50000 | J426: =IFERROR((I426-G426)/G426,"") -> 1 | K426: =I426*F426 -> 150000
A427: 46186 | B427: 6112530 | C427: =VLOOKUP(B427,MAESTRA!I:K,2,0) -> *6112530* | D427: =VLOOKUP(B427,MAESTRA!I:K,3,0) -> BLUSAS DAMA ELEGANTE TALLA UN | E427: ECUATORIANOS | F427: 5 | G427: 27000 | H427: =G427*F427 -> 135000 | I427: =CEILING(G427*$I$1,1000) -> 54000 | J427: =IFERROR((I427-G427)/G427,"") -> 1 | K427: =I427*F427 -> 270000
A428: 46186 | B428: 619430 | C428: =VLOOKUP(B428,MAESTRA!I:K,2,0) -> *619430* | D428: =VLOOKUP(B428,MAESTRA!I:K,3,0) -> BLUSAS DAMA CON PEPAS TALLA UN | E428: ECUATORIANOS | F428: 3 | G428: 25000 | H428: =G428*F428 -> 75000 | I428: =CEILING(G428*$I$1,1000) -> 50000 | J428: =IFERROR((I428-G428)/G428,"") -> 1 | K428: =I428*F428 -> 150000
A429: 46186 | B429: 2619030 | C429: =VLOOKUP(B429,MAESTRA!I:K,2,0) -> *2619030* | D429: =VLOOKUP(B429,MAESTRA!I:K,3,0) -> BUSOS DAMA CON BORDADOS TALLA UN | E429: ECUATORIANOS | F429: 9 | G429: 33000 | H429: =G429*F429 -> 297000 | I429: =CEILING(G429*$I$1,1000) -> 66000 | J429: =IFERROR((I429-G429)/G429,"") -> 1 | K429: =I429*F429 -> 594000
A430: 46186 | B430: 2617030 | C430: =VLOOKUP(B430,MAESTRA!I:K,2,0) -> *2617030* | D430: =VLOOKUP(B430,MAESTRA!I:K,3,0) -> BUSOS DAMA CAPOTA LANA TALLA UN | E430: ECUATORIANOS | F430: 4 | G430: 33000 | H430: =G430*F430 -> 132000 | I430: =CEILING(G430*$I$1,1000) -> 66000 | J430: =IFERROR((I430-G430)/G430,"") -> 1 | K430: =I430*F430 -> 264000
A431: 46186 | B431: 1112227 | C431: =VLOOKUP(B431,MAESTRA!I:K,2,0) -> *1112227* | D431: =VLOOKUP(B431,MAESTRA!I:K,3,0) -> CAMISETAS DAMA ALGODON OLGADA TALLA S | E431: RED-PLAY 21 | F431: 8 | G431: 17000 | H431: =G431*F431 -> 136000 | I431: =CEILING(G431*$I$1,1000) -> 34000 | J431: =IFERROR((I431-G431)/G431,"") -> 1 | K431: =I431*F431 -> 272000
A432: 46186 | B432: 1112225 | C432: =VLOOKUP(B432,MAESTRA!I:K,2,0) -> *1112225* | D432: =VLOOKUP(B432,MAESTRA!I:K,3,0) -> CAMISETAS DAMA ALGODON OLGADA TALLA M | E432: RED-PLAY 21 | F432: 7 | G432: 17000 | H432: =G432*F432 -> 119000 | I432: =CEILING(G432*$I$1,1000) -> 34000 | J432: =IFERROR((I432-G432)/G432,"") -> 1 | K432: =I432*F432 -> 238000
... A448: 46186 | B448: 55127223 | C448: =VLOOKUP(B448,MAESTRA!I:K,2,0) -> *55127223* | D448: =VLOOKUP(B448,MAESTRA!I:K,3,0) -> CROPTOP DAMA UN ESTAMPADO TALLA L | E448: RED-PLAY 21 | F448: 12 | G448: 18000 | H448: =G448*F448 -> 216000 | I448: =CEILING(G448*$I$1,1000) -> 36000 | J448: =IFERROR((I448-G448)/G448,"") -> 1 | K448: =I448*F448 -> 432000
A449: 46186 | B449: 1128823 | C449: =VLOOKUP(B449,MAESTRA!I:K,2,0) -> *1128823* | D449: =VLOOKUP(B449,MAESTRA!I:K,3,0) -> CAMISETAS CABALLERO COLOMBIA AAA TALLA L | E449: ADIDAS | F449: 3 | H449: =G449*F449 -> 0 | I449: =CEILING(G449*$I$1,1000) -> 0 | J449: =IFERROR((I449-G449)/G449,"") | K449: =I449*F449 -> 0
A450: 46186 | B450: 1128827 | C450: =VLOOKUP(B450,MAESTRA!I:K,2,0) -> *1128827* | D450: =VLOOKUP(B450,MAESTRA!I:K,3,0) -> CAMISETAS CABALLERO COLOMBIA AAA TALLA S | E450: ADIDAS | F450: 2 | H450: =G450*F450 -> 0 | I450: =CEILING(G450*$I$1,1000) -> 0 | J450: =IFERROR((I450-G450)/G450,"") | K450: =I450*F450 -> 0
A451: 46186 | B451: 1128825 | C451: =VLOOKUP(B451,MAESTRA!I:K,2,0) -> *1128825* | D451: =VLOOKUP(B451,MAESTRA!I:K,3,0) -> CAMISETAS CABALLERO COLOMBIA AAA TALLA M | E451: ADIDAS | F451: 3 | H451: =G451*F451 -> 0 | I451: =CEILING(G451*$I$1,1000) -> 0 | J451: =IFERROR((I451-G451)/G451,"") | K451: =I451*F451 -> 0
...

Sheet IMPRESION
A1: CODIGO | B1: 1143
A2: DESCRIPCION | B2: =VLOOKUP(B1,COMPRAS!B:I,3,0) -> JEANS DAMA 4 BOTONES TALLA 10
A3: VALOR | B3: =VLOOKUP(B1,COMPRAS!B:I,7,0) -> 64000
A4: CODIGOBARRA | B4: =VLOOKUP(B1,COMPRAS!B:I,2,0) -> *1143*
A5: CANTIDAD ETIQUETAS | B5: 2

Sheet MAESTRA
A3: FECHA CREACION | B3: LINEA | C3: CATEGORIA | D3: GENERO | E3: ESTILO-DETALLE | F3: COLOR | G3: TALLA | H3: PROVEEDOR-MARCA | I3: SKU | J3: CODIGO DE BARRAS | K3: NOMBRE COMPLETO
A4: 46186 | B4: ROPA DAMA | C4: JEANS | D4: DAMA | E4: 4 BOTONES | F4: GRIS | G4: 10 | H4: R TREIK | I4: =IFERROR(CONCATENATE(VLOOKUP(C4,PARAM!D:E,2,0),VLOOKUP(D4,PARAM!J:K,2,0),VLOOKUP(E4,PARAM!G:H,2,0),VLOOKUP(G4,PARAM!P:Q,2,0)),"") -> 1143 | J4: =IFERROR(CONCATENATE("*",VLOOKUP(C4,PARAM!D:E,2,0),VLOOKUP(D4,PARAM!J:K,2,0),VLOOKUP(E4,PARAM!G:H,2,0),VLOOKUP(G4,PARAM!P:Q,2,0),"*"),"") -> *1143* | K4: =CONCATENATE(C4," ",D4," ",E4,IF(G4="-","",CONCATENATE(" TALLA ",G4))) -> JEANS DAMA 4 BOTONES TALLA 10
A5: 46186 | B5: ROPA DAMA | C5: JEANS | D5: DAMA | E5: 4 BOTONES | F5: GRIS | G5: 8 | H5: R TREIK | I5: =IFERROR(CONCATENATE(VLOOKUP(C5,PARAM!D:E,2,0),VLOOKUP(D5,PARAM!J:K,2,0),VLOOKUP(E5,PARAM!G:H,2,0),VLOOKUP(G5,PARAM!P:Q,2,0)),"") -> 1142 | J5: =IFERROR(CONCATENATE("*",VLOOKUP(C5,PARAM!D:E,2,0),VLOOKUP(D5,PARAM!J:K,2,0),VLOOKUP(E5,PARAM!G:H,2,0),VLOOKUP(G5,PARAM!P:Q,2,0),"*"),"") -> *1142* | K5: =CONCATENATE(C5," ",D5," ",E5,IF(G5="-","",CONCATENATE(" TALLA ",G5))) -> JEANS DAMA 4 BOTONES TALLA 8
A6: 46186 | B6: ROPA DAMA | C6: JEANS | D6: DAMA | E6: 4 BOTONES SIN BOLSILLO | F6: GRIS | G6: 8 | H6: R TREIK | I6: =IFERROR(CONCATENATE(VLOOKUP(C6,PARAM!D:E,2,0),VLOOKUP(D6,PARAM!J:K,2,0),VLOOKUP(E6,PARAM!G:H,2,0),VLOOKUP(G6,PARAM!P:Q,2,0)),"") -> 1152 | J6: =IFERROR(CONCATENATE("*",VLOOKUP(C6,PARAM!D:E,2,0),VLOOKUP(D6,PARAM!J:K,2,0),VLOOKUP(E6,PARAM!G:H,2,0),VLOOKUP(G6,PARAM!P:Q,2,0),"*"),"") -> *1152* | K6: =CONCATENATE(C6," ",D6," ",E6,IF(G6="-","",CONCATENATE(" TALLA ",G6))) -> JEANS DAMA 4 BOTONES SIN BOLSILLO TALLA 8
A7: 46186 | B7: ROPA DAMA | C7: JEANS | D7: DAMA | E7: 4 BOTONES | F7: GRIS | G7: 16 | H7: R TREIK | I7: =IFERROR(CONCATENATE(VLOOKUP(C7,PARAM!D:E,2,0),VLOOKUP(D7,PARAM!J:K,2,0),VLOOKUP(E7,PARAM!G:H,2,0),VLOOKUP(G7,PARAM!P:Q,2,0)),"") -> 1146 | J7: =IFERROR(CONCATENATE("*",VLOOKUP(C7,PARAM!D:E,2,0),VLOOKUP(D7,PARAM!J:K,2,0),VLOOKUP(E7,PARAM!G:H,2,0),VLOOKUP(G7,PARAM!P:Q,2,0),"*"),"") -> *1146* | K7: =CONCATENATE(C7," ",D7," ",E7,IF(G7="-","",CONCATENATE(" TALLA ",G7))) -> JEANS DAMA 4 BOTONES TALLA 16
A8: 46186 | B8: ROPA DAMA | C8: JEANS | D8: DAMA | E8: 4 BOTONES SIN BOLSILLO | F8: GRIS | G8: 16 | H8: R TREIK | I8: =IFERROR(CONCATENATE(VLOOKUP(C8,PARAM!D:E,2,0),VLOOKUP(D8,PARAM!J:K,2,0),VLOOKUP(E8,PARAM!G:H,2,0),VLOOKUP(G8,PARAM!P:Q,2,0)),"") -> 1156 | J8: =IFERROR(CONCATENATE("*",VLOOKUP(C8,PARAM!D:E,2,0),VLOOKUP(D8,PARAM!J:K,2,0),VLOOKUP(E8,PARAM!G:H,2,0),VLOOKUP(G8,PARAM!P:Q,2,0),"*"),"") -> *1156* | K8: =CONCATENATE(C8," ",D8," ",E8,IF(G8="-","",CONCATENATE(" TALLA ",G8))) -> JEANS DAMA 4 BOTONES SIN BOLSILLO TALLA 16
A9: 46186 | B9: ROPA DAMA | C9: JEANS | D9: DAMA | E9: 1 BOTON | F9: GRIS | G9: 12 | H9: R TREIK | I9: =IFERROR(CONCATENATE(VLOOKUP(C9,PARAM!D:E,2,0),VLOOKUP(D9,PARAM!J:K,2,0),VLOOKUP(E9,PARAM!G:H,2,0),VLOOKUP(G9,PARAM!P:Q,2,0)),"") -> 1114 | J9: =IFERROR(CONCATENATE("*",VLOOKUP(C9,PARAM!D:E,2,0),VLOOKUP(D9,PARAM!J:K,2,0),VLOOKUP(E9,PARAM!G:H,2,0),VLOOKUP(G9,PARAM!P:Q,2,0),"*"),"") -> *1114* | K9: =CONCATENATE(C9," ",D9," ",E9,IF(G9="-","",CONCATENATE(" TALLA ",G9))) -> JEANS DAMA 1 BOTON TALLA 12
A10: 46186 | B10: ROPA DAMA | C10: JEANS | D10: DAMA | E10: 4 BOTONES | F10: GRIS | G10: 14 | H10: R TREIK | I10: =IFERROR(CONCATENATE(VLOOKUP(C10,PARAM!D:E,2,0),VLOOKUP(D10,PARAM!J:K,2,0),VLOOKUP(E10,PARAM!G:H,2,0),VLOOKUP(G10,PARAM!P:Q,2,0)),"") -> 1145 | J10: =IFERROR(CONCATENATE("*",VLOOKUP(C10,PARAM!D:E,2,0),VLOOKUP(D10,PARAM!J:K,2,0),VLOOKUP(E10,PARAM!G:H,2,0),VLOOKUP(G10,PARAM!P:Q,2,0),"*"),"") -> *1145* | K10: =CONCATENATE(C10," ",D10," ",E10,IF(G10="-","",CONCATENATE(" TALLA ",G10))) -> JEANS DAMA 4 BOTONES TALLA 14
A11: 46186 | B11: ROPA DAMA | C11: JEANS | D11: DAMA | E11: 1 BOTON BOTA RECTA | F11: NEGRO | G11: 14 | H11: R TREIK | I11: =IFERROR(CONCATENATE(VLOOKUP(C11,PARAM!D:E,2,0),VLOOKUP(D11,PARAM!J:K,2,0),VLOOKUP(E11,PARAM!G:H,2,0),VLOOKUP(G11,PARAM!P:Q,2,0)),"") -> 1125 | J11: =IFERROR(CONCATENATE("*",VLOOKUP(C11,PARAM!D:E,2,0),VLOOKUP(D11,PARAM!J:K,2,0),VLOOKUP(E11,PARAM!G:H,2,0),VLOOKUP(G11,PARAM!P:Q,2,0),"*"),"") -> *1125* | K11: =CONCATENATE(C11," ",D11," ",E11,IF(G11="-","",CONCATENATE(" TALLA ",G11))) -> JEANS DAMA 1 BOTON BOTA RECTA TALLA 14
A12: 46186 | B12: ROPA DAMA | C12: JEANS | D12: DAMA | E12: 1 BOTON BOTA RECTA | F12: NEGRO | G12: 10 | H12: R TREIK | I12: =IFERROR(CONCATENATE(VLOOKUP(C12,PARAM!D:E,2,0),VLOOKUP(D12,PARAM!J:K,2,0),VLOOKUP(E12,PARAM!G:H,2,0),VLOOKUP(G12,PARAM!P:Q,2,0)),"") -> 1123 | J12: =IFERROR(CONCATENATE("*",VLOOKUP(C12,PARAM!D:E,2,0),VLOOKUP(D12,PARAM!J:K,2,0),VLOOKUP(E12,PARAM!G:H,2,0),VLOOKUP(G12,PARAM!P:Q,2,0),"*"),"") -> *1123* | K12: =CONCATENATE(C12," ",D12," ",E12,IF(G12="-","",CONCATENATE(" TALLA ",G12))) -> JEANS DAMA 1 BOTON BOTA RECTA TALLA 10
A13: 46186 | B13: ROPA DAMA | C13: JEANS | D13: DAMA | E13: 1 BOTON BOTA RECTA | F13: NEGRO | G13: 8 | H13: R TREIK | I13: =IFERROR(CONCATENATE(VLOOKUP(C13,PARAM!D:E,2,0),VLOOKUP(D13,PARAM!J:K,2,0),VLOOKUP(E13,PARAM!G:H,2,0),VLOOKUP(G13,PARAM!P:Q,2,0)),"") -> 1122 | J13: =IFERROR(CONCATENATE("*",VLOOKUP(C13,PARAM!D:E,2,0),VLOOKUP(D13,PARAM!J:K,2,0),VLOOKUP(E13,PARAM!G:H,2,0),VLOOKUP(G13,PARAM!P:Q,2,0),"*"),"") -> *1122* | K13: =CONCATENATE(C13," ",D13," ",E13,IF(G13="-","",CONCATENATE(" TALLA ",G13))) -> JEANS DAMA 1 BOTON BOTA RECTA TALLA 8
A14: 46186 | B14: ROPA DAMA | C14: JEANS | D14: DAMA | E14: 1 BOTON BOTA RECTA | F14: NEGRO | G14: 14 | H14: R TREIK | I14: =IFERROR(CONCATENATE(VLOOKUP(C14,PARAM!D:E,2,0),VLOOKUP(D14,PARAM!J:K,2,0),VLOOKUP(E14,PARAM!G:H,2,0),VLOOKUP(G14,PARAM!P:Q,2,0)),"") -> 1125 | J14: =IFERROR(CONCATENATE("*",VLOOKUP(C14,PARAM!D:E,2,0),VLOOKUP(D14,PARAM!J:K,2,0),VLOOKUP(E14,PARAM!G:H,2,0),VLOOKUP(G14,PARAM!P:Q,2,0),"*"),"") -> *1125* | K14: =CONCATENATE(C14," ",D14," ",E14,IF(G14="-","",CONCATENATE(" TALLA ",G14))) -> JEANS DAMA 1 BOTON BOTA RECTA TALLA 14
A15: 46186 | B15: ROPA DAMA | C15: JEANS | D15: DAMA | E15: 4 BOTONES SIN BOLSILLO | F15: NEGRO | G15: 14 | H15: R TREIK | I15: =IFERROR(CONCATENATE(VLOOKUP(C15,PARAM!D:E,2,0),VLOOKUP(D15,PARAM!J:K,2,0),VLOOKUP(E15,PARAM!G:H,2,0),VLOOKUP(G15,PARAM!P:Q,2,0)),"") -> 1155 | J15: =IFERROR(CONCATENATE("*",VLOOKUP(C15,PARAM!D:E,2,0),VLOOKUP(D15,PARAM!J:K,2,0),VLOOKUP(E15,PARAM!G:H,2,0),VLOOKUP(G15,PARAM!P:Q,2,0),"*"),"") -> *1155* | K15: =CONCATENATE(C15," ",D15," ",E15,IF(G15="-","",CONCATENATE(" TALLA ",G15))) -> JEANS DAMA 4 BOTONES SIN BOLSILLO TALLA 14
... A21: 46186 | B21: ROPA DAMA | C21: JEANS | D21: DAMA | E21: 4 BOTONES SIN BOLSILLO | F21: AZUL | G21: 8 | H21: R TREIK | I21: =IFERROR(CONCATENATE(VLOOKUP(C21,PARAM!D:E,2,0),VLOOKUP(D21,PARAM!J:K,2,0),VLOOKUP(E21,PARAM!G:H,2,0),VLOOKUP(G21,PARAM!P:Q,2,0)),"") -> 1152 | J21: =IFERROR(CONCATENATE("*",VLOOKUP(C21,PARAM!D:E,2,0),VLOOKUP(D21,PARAM!J:K,2,0),VLOOKUP(E21,PARAM!G:H,2,0),VLOOKUP(G21,PARAM!P:Q,2,0),"*"),"") -> *1152* | K21: =CONCATENATE(C21," ",D21," ",E21,IF(G21="-","",CONCATENATE(" TALLA ",G21))) -> JEANS DAMA 4 BOTONES SIN BOLSILLO TALLA 8
A22: 46186 | B22: ROPA DAMA | C22: BLUSAS | D22: DAMA | E22: BASICA ALGODON | F22: VARIOS | G22: VA | H22: LUZMAR | I22: =IFERROR(CONCATENATE(VLOOKUP(C22,PARAM!D:E,2,0),VLOOKUP(D22,PARAM!J:K,2,0),VLOOKUP(E22,PARAM!G:H,2,0),VLOOKUP(G22,PARAM!P:Q,2,0)),"") -> 614531 | J22: =IFERROR(CONCATENATE("*",VLOOKUP(C22,PARAM!D:E,2,0),VLOOKUP(D22,PARAM!J:K,2,0),VLOOKUP(E22,PARAM!G:H,2,0),VLOOKUP(G22,PARAM!P:Q,2,0),"*"),"") -> *614531* | K22: =CONCATENATE(C22," ",D22," ",E22,IF(G22="-","",CONCATENATE(" TALLA ",G22))) -> BLUSAS DAMA BASICA ALGODON TALLA VA
A23: 46186 | B23: LICRA DEPORTIVA | C23: BICICLETERO | D23: DAMA | E23: ALGODON | F23: VARIOS | G23: M-L | H23: LUZMAR | I23: =IFERROR(CONCATENATE(VLOOKUP(C23,PARAM!D:E,2,0),VLOOKUP(D23,PARAM!J:K,2,0),VLOOKUP(E23,PARAM!G:H,2,0),VLOOKUP(G23,PARAM!P:Q,2,0)),"") -> 4311626 | J23: =IFERROR(CONCATENATE("*",VLOOKUP(C23,PARAM!D:E,2,0),VLOOKUP(D23,PARAM!J:K,2,0),VLOOKUP(E23,PARAM!G:H,2,0),VLOOKUP(G23,PARAM!P:Q,2,0),"*"),"") -> *4311626* | K23: =CONCATENATE(C23," ",D23," ",E23,IF(G23="-","",CONCATENATE(" TALLA ",G23))) -> BICICLETERO DAMA ALGODON TALLA M-L
A24: 46186 | B24: LICRA DEPORTIVA | C24: BICICLETERO | D24: DAMA | E24: ALGODON | F24: VARIOS | G24: 16-S | H24: LUZMAR | I24: =IFERROR(CONCATENATE(VLOOKUP(C24,PARAM!D:E,2,0),VLOOKUP(D24,PARAM!J:K,2,0),VLOOKUP(E24,PARAM!G:H,2,0),VLOOKUP(G24,PARAM!P:Q,2,0)),"") -> 4311618 | J24: =IFERROR(CONCATENATE("*",VLOOKUP(C24,PARAM!D:E,2,0),VLOOKUP(D24,PARAM!J:K,2,0),VLOOKUP(E24,PARAM!G:H,2,0),VLOOKUP(G24,PARAM!P:Q,2,0),"*"),"") -> *4311618* | K24: =CONCATENATE(C24," ",D24," ",E24,IF(G24="-","",CONCATENATE(" TALLA ",G24))) -> BICICLETERO DAMA ALGODON TALLA 16-S
A25: 46186 | B25: LICRA DEPORTIVA | C25: BICICLETERO | D25: DAMA | E25: ALGODON | F25: VARIOS | G25: 14 | H25: LUZMAR | I25: =IFERROR(CONCATENATE(VLOOKUP(C25,PARAM!D:E,2,0),VLOOKUP(D25,PARAM!J:K,2,0),VLOOKUP(E25,PARAM!G:H,2,0),VLOOKUP(G25,PARAM!P:Q,2,0)),"") -> 431165 | J25: =IFERROR(CONCATENATE("*",VLOOKUP(C25,PARAM!D:E,2,0),VLOOKUP(D25,PARAM!J:K,2,0),VLOOKUP(E25,PARAM!G:H,2,0),VLOOKUP(G25,PARAM!P:Q,2,0),"*"),"") -> *431165* | K25: =CONCATENATE(C25," ",D25," ",E25,IF(G25="-","",CONCATENATE(" TALLA ",G25))) -> BICICLETERO DAMA ALGODON TALLA 14
A26: 46186 | B26: LICRA DEPORTIVA | C26: LEGGINS | D26: DAMA | E26: ALGODON | F26: VARIOS | G26: XL | H26: LUZMAR | I26: =IFERROR(CONCATENATE(VLOOKUP(C26,PARAM!D:E,2,0),VLOOKUP(D26,PARAM!J:K,2,0),VLOOKUP(E26,PARAM!G:H,2,0),VLOOKUP(G26,PARAM!P:Q,2,0)),"") -> 4411632 | J26: =IFERROR(CONCATENATE("*",VLOOKUP(C26,PARAM!D:E,2,0),VLOOKUP(D26,PARAM!J:K,2,0),VLOOKUP(E26,PARAM!G:H,2,0),VLOOKUP(G26,PARAM!P:Q,2,0),"*"),"") -> *4411632* | K26: =CONCATENATE(C26," ",D26," ",E26,IF(G26="-","",CONCATENATE(" TALLA ",G26))) -> LEGGINS DAMA ALGODON TALLA XL
A27: 46186 | B27: ROPA CABALLERO | C27: BERMUDAS | D27: CABALLERO | E27: CAMUFLADO | F27: BEIGE | G27: 36 | H27: GOLDTEX | I27: =IFERROR(CONCATENATE(VLOOKUP(C27,PARAM!D:E,2,0),VLOOKUP(D27,PARAM!J:K,2,0),VLOOKUP(E27,PARAM!G:H,2,0),VLOOKUP(G27,PARAM!P:Q,2,0)),"") -> 526616 | J27: =IFERROR(CONCATENATE("*",VLOOKUP(C27,PARAM!D:E,2,0),VLOOKUP(D27,PARAM!J:K,2,0),VLOOKUP(E27,PARAM!G:H,2,0),VLOOKUP(G27,PARAM!P:Q,2,0),"*"),"") -> *526616* | K27: =CONCATENATE(C27," ",D27," ",E27,IF(G27="-","",CONCATENATE(" TALLA ",G27))) -> BERMUDAS CABALLERO CAMUFLADO TALLA 36
A28: 46186 | B28: ROPA CABALLERO | C28: BERMUDAS | D28: CABALLERO | E28: CAMUFLADO | F28: CAQUI OSCURO | G28: 28 | H28: GOLDTEX | I28: =IFERROR(CONCATENATE(VLOOKUP(C28,PARAM!D:E,2,0),VLOOKUP(D28,PARAM!J:K,2,0),VLOOKUP(E28,PARAM!G:H,2,0),VLOOKUP(G28,PARAM!P:Q,2,0)),"") -> 526612 | J28: =IFERROR(CONCATENATE("*",VLOOKUP(C28,PARAM!D:E,2,0),VLOOKUP(D28,PARAM!J:K,2,0),VLOOKUP(E28,PARAM!G:H,2,0),VLOOKUP(G28,PARAM!P:Q,2,0),"*"),"") -> *526612* | K28: =CONCATENATE(C28," ",D28," ",E28,IF(G28="-","",CONCATENATE(" TALLA ",G28))) -> BERMUDAS CABALLERO CAMUFLADO TALLA 28
A29: 46186 | B29: ROPA CABALLERO | C29: BERMUDAS | D29: CABALLERO | E29: CAMUFLADO | F29: AZUL NOCHE | G29: 30 | H29: GOLDTEX | I29: =IFERROR(CONCATENATE(VLOOKUP(C29,PARAM!D:E,2,0),VLOOKUP(D29,PARAM!J:K,2,0),VLOOKUP(E29,PARAM!G:H,2,0),VLOOKUP(G29,PARAM!P:Q,2,0)),"") -> 526613 | J29: =IFERROR(CONCATENATE("*",VLOOKUP(C29,PARAM!D:E,2,0),VLOOKUP(D29,PARAM!J:K,2,0),VLOOKUP(E29,PARAM!G:H,2,0),VLOOKUP(G29,PARAM!P:Q,2,0),"*"),"") -> *526613* | K29: =CONCATENATE(C29," ",D29," ",E29,IF(G29="-","",CONCATENATE(" TALLA ",G29))) -> BERMUDAS CABALLERO CAMUFLADO TALLA 30
A30: 46186 | B30: ROPA CABALLERO | C30: BERMUDAS | D30: CABALLERO | E30: CAMUFLADO | F30: VERDE | G30: 32 | H30: GOLDTEX | I30: =IFERROR(CONCATENATE(VLOOKUP(C30,PARAM!D:E,2,0),VLOOKUP(D30,PARAM!J:K,2,0),VLOOKUP(E30,PARAM!G:H,2,0),VLOOKUP(G30,PARAM!P:Q,2,0)),"") -> 526614 | J30: =IFERROR(CONCATENATE("*",VLOOKUP(C30,PARAM!D:E,2,0),VLOOKUP(D30,PARAM!J:K,2,0),VLOOKUP(E30,PARAM!G:H,2,0),VLOOKUP(G30,PARAM!P:Q,2,0),"*"),"") -> *526614* | K30: =CONCATENATE(C30," ",D30," ",E30,IF(G30="-","",CONCATENATE(" TALLA ",G30))) -> BERMUDAS CABALLERO CAMUFLADO TALLA 32
A31: 46186 | B31: ROPA CABALLERO | C31: BERMUDAS | D31: CABALLERO | E31: CAMUFLADO | F31: NEGRO | G31: 34 | H31: GOLDTEX | I31: =IFERROR(CONCATENATE(VLOOKUP(C31,PARAM!D:E,2,0),VLOOKUP(D31,PARAM!J:K,2,0),VLOOKUP(E31,PARAM!G:H,2,0),VLOOKUP(G31,PARAM!P:Q,2,0)),"") -> 526615 | J31: =IFERROR(CONCATENATE("*",VLOOKUP(C31,PARAM!D:E,2,0),VLOOKUP(D31,PARAM!J:K,2,0),VLOOKUP(E31,PARAM!G:H,2,0),VLOOKUP(G31,PARAM!P:Q,2,0),"*"),"") -> *526615* | K31: =CONCATENATE(C31," ",D31," ",E31,IF(G31="-","",CONCATENATE(" TALLA ",G31))) -> BERMUDAS CABALLERO CAMUFLADO TALLA 34
A32: 46186 | B32: ROPA CABALLERO | C32: BERMUDAS | D32: CABALLERO | E32: CLASICA DRILL | F32: NEGRO | G32: 34 | H32: GOLDTEX | I32: =IFERROR(CONCATENATE(VLOOKUP(C32,PARAM!D:E,2,0),VLOOKUP(D32,PARAM!J:K,2,0),VLOOKUP(E32,PARAM!G:H,2,0),VLOOKUP(G32,PARAM!P:Q,2,0)),"") -> 527515 | J32: =IFERROR(CONCATENATE("*",VLOOKUP(C32,PARAM!D:E,2,0),VLOOKUP(D32,PARAM!J:K,2,0),VLOOKUP(E32,PARAM!G:H,2,0),VLOOKUP(G32,PARAM!P:Q,2,0),"*"),"") -> *527515* | K32: =CONCATENATE(C32," ",D32," ",E32,IF(G32="-","",CONCATENATE(" TALLA ",G32))) -> BERMUDAS CABALLERO CLASICA DRILL TALLA 34
A33: 46186 | B33: ROPA CABALLERO | C33: BERMUDAS | D33: CABALLERO | E33: CLASICA DRILL | F33: CAQUI OSCURO | G33: 28 | H33: GOLDTEX | I33: =IFERROR(CONCATENATE(VLOOKUP(C33,PARAM!D:E,2,0),VLOOKUP(D33,PARAM!J:K,2,0),VLOOKUP(E33,PARAM!G:H,2,0),VLOOKUP(G33,PARAM!P:Q,2,0)),"") -> 527512 | J33: =IFERROR(CONCATENATE("*",VLOOKUP(C33,PARAM!D:E,2,0),VLOOKUP(D33,PARAM!J:K,2,0),VLOOKUP(E33,PARAM!G:H,2,0),VLOOKUP(G33,PARAM!P:Q,2,0),"*"),"") -> *527512* | K33: =CONCATENATE(C33," ",D33," ",E33,IF(G33="-","",CONCATENATE(" TALLA ",G33))) -> BERMUDAS CABALLERO CLASICA DRILL TALLA 28
A34: 46186 | B34: ROPA CABALLERO | C34: BERMUDAS | D34: CABALLERO | E34: CLASICA DRILL | F34: AZUL CLARO | G34: 32 | H34: GOLDTEX | I34: =IFERROR(CONCATENATE(VLOOKUP(C34,PARAM!D:E,2,0),VLOOKUP(D34,PARAM!J:K,2,0),VLOOKUP(E34,PARAM!G:H,2,0),VLOOKUP(G34,PARAM!P:Q,2,0)),"") -> 527514 | J34: =IFERROR(CONCATENATE("*",VLOOKUP(C34,PARAM!D:E,2,0),VLOOKUP(D34,PARAM!J:K,2,0),VLOOKUP(E34,PARAM!G:H,2,0),VLOOKUP(G34,PARAM!P:Q,2,0),"*"),"") -> *527514* | K34: =CONCATENATE(C34," ",D34," ",E34,IF(G34="-","",CONCATENATE(" TALLA ",G34))) -> BERMUDAS CABALLERO CLASICA DRILL TALLA 32
A35: 46186 | B35: ROPA CABALLERO | C35: BERMUDAS | D35: CABALLERO | E35: CLASICA DRILL | F35: VERDE OSCURO | G35: 30 | H35: GOLDTEX | I35: =IFERROR(CONCATENATE(VLOOKUP(C35,PARAM!D:E,2,0),VLOOKUP(D35,PARAM!J:K,2,0),VLOOKUP(E35,PARAM!G:H,2,0),VLOOKUP(G35,PARAM!P:Q,2,0)),"") -> 527513 | J35: =IFERROR(CONCATENATE("*",VLOOKUP(C35,PARAM!D:E,2,0),VLOOKUP(D35,PARAM!J:K,2,0),VLOOKUP(E35,PARAM!G:H,2,0),VLOOKUP(G35,PARAM!P:Q,2,0),"*"),"") -> *527513* | K35: =CONCATENATE(C35," ",D35," ",E35,IF(G35="-","",CONCATENATE(" TALLA ",G35))) -> BERMUDAS CABALLERO CLASICA DRILL TALLA 30
A36: 46186 | B36: ROPA DAMA | C36: SHORTS | D36: DAMA | E36: SHORT ARO | F36: VARIOS | G36: VA | H36: GOLDTEX | I36: =IFERROR(CONCATENATE(VLOOKUP(C36,PARAM!D:E,2,0),VLOOKUP(D36,PARAM!J:K,2,0),VLOOKUP(E36,PARAM!G:H,2,0),VLOOKUP(G36,PARAM!P:Q,2,0)),"") -> 4125131 | J36: =IFERROR(CONCATENATE("*",VLOOKUP(C36,PARAM!D:E,2,0),VLOOKUP(D36,PARAM!J:K,2,0),VLOOKUP(E36,PARAM!G:H,2,0),VLOOKUP(G36,PARAM!P:Q,2,0),"*"),"") -> *4125131* | K36: =CONCATENATE(C36," ",D36," ",E36,IF(G36="-","",CONCATENATE(" TALLA ",G36))) -> SHORTS DAMA SHORT ARO TALLA VA
A37: 46186 | B37: ROPA DAMA | C37: SHORTS | D37: DAMA | E37: CINTURON ANCHO | F37: VARIOS | G37: VA | H37: GOLDTEX | I37: =IFERROR(CONCATENATE(VLOOKUP(C37,PARAM!D:E,2,0),VLOOKUP(D37,PARAM!J:K,2,0),VLOOKUP(E37,PARAM!G:H,2,0),VLOOKUP(G37,PARAM!P:Q,2,0)),"") -> 417431 | J37: =IFERROR(CONCATENATE("*",VLOOKUP(C37,PARAM!D:E,2,0),VLOOKUP(D37,PARAM!J:K,2,0),VLOOKUP(E37,PARAM!G:H,2,0),VLOOKUP(G37,PARAM!P:Q,2,0),"*"),"") -> *417431* | K37: =CONCATENATE(C37," ",D37," ",E37,IF(G37="-","",CONCATENATE(" TALLA ",G37))) -> SHORTS DAMA CINTURON ANCHO TALLA VA
A38: 46186 | B38: ROPA DAMA | C38: BERMUDAS | D38: DAMA | E38: DRILL | F38: VARIOS | G38: VA | H38: GOLDTEX | I38: =IFERROR(CONCATENATE(VLOOKUP(C38,PARAM!D:E,2,0),VLOOKUP(D38,PARAM!J:K,2,0),VLOOKUP(E38,PARAM!G:H,2,0),VLOOKUP(G38,PARAM!P:Q,2,0)),"") -> 5112131 | J38: =IFERROR(CONCATENATE("*",VLOOKUP(C38,PARAM!D:E,2,0),VLOOKUP(D38,PARAM!J:K,2,0),VLOOKUP(E38,PARAM!G:H,2,0),VLOOKUP(G38,PARAM!P:Q,2,0),"*"),"") -> *5112131* | K38: =CONCATENATE(C38," ",D38," ",E38,IF(G38="-","",CONCATENATE(" TALLA ",G38))) -> BERMUDAS DAMA DRILL TALLA VA
A39: 46186 | B39: PERFUMERIA | C39: PERFUMES | D39: DAMA | E39: PINK MINI | F39: VARIOS | G39: - | I39: =IFERROR(CONCATENATE(VLOOKUP(C39,PARAM!D:E,2,0),VLOOKUP(D39,PARAM!J:K,2,0),VLOOKUP(E39,PARAM!G:H,2,0),VLOOKUP(G39,PARAM!P:Q,2,0)),"") -> 1212110 | J39: =IFERROR(CONCATENATE("*",VLOOKUP(C39,PARAM!D:E,2,0),VLOOKUP(D39,PARAM!J:K,2,0),VLOOKUP(E39,PARAM!G:H,2,0),VLOOKUP(G39,PARAM!P:Q,2,0),"*"),"") -> *1212110* | K39: =CONCATENATE(C39," ",D39," ",E39,IF(G39="-","",CONCATENATE(" TALLA ",G39))) -> PERFUMES DAMA PINK MINI
A40: 46186 | B40: MAQUILLAJE | C40: BRILLO | D40: DAMA | E40: LABIAL | F40: VARIOS | G40: - | I40: =IFERROR(CONCATENATE(VLOOKUP(C40,PARAM!D:E,2,0),VLOOKUP(D40,PARAM!J:K,2,0),VLOOKUP(E40,PARAM!G:H,2,0),VLOOKUP(G40,PARAM!P:Q,2,0)),"") -> 4711600 | J40: =IFERROR(CONCATENATE("*",VLOOKUP(C40,PARAM!D:E,2,0),VLOOKUP(D40,PARAM!J:K,2,0),VLOOKUP(E40,PARAM!G:H,2,0),VLOOKUP(G40,PARAM!P:Q,2,0),"*"),"") -> *4711600* | K40: =CONCATENATE(C40," ",D40," ",E40,IF(G40="-","",CONCATENATE(" TALLA ",G40))) -> BRILLO DAMA LABIAL
A41: 46186 | B41: PERFUMERIA | C41: SPLASH | D41: DAMA | E41: - | F41: VARIOS | G41: - | I41: =IFERROR(CONCATENATE(VLOOKUP(C41,PARAM!D:E,2,0),VLOOKUP(D41,PARAM!J:K,2,0),VLOOKUP(E41,PARAM!G:H,2,0),VLOOKUP(G41,PARAM!P:Q,2,0)),"") -> 46100 | J41: =IFERROR(CONCATENATE("*",VLOOKUP(C41,PARAM!D:E,2,0),VLOOKUP(D41,PARAM!J:K,2,0),VLOOKUP(E41,PARAM!G:H,2,0),VLOOKUP(G41,PARAM!P:Q,2,0),"*"),"") -> *46100* | K41: =CONCATENATE(C41," ",D41," ",E41,IF(G41="-","",CONCATENATE(" TALLA ",G41))) -> SPLASH DAMA -
A42: 46186 | B42: PERFUMERIA | C42: SPLASH | D42: CABALLERO | E42: - | F42: VARIOS | G42: - | I42: =IFERROR(CONCATENATE(VLOOKUP(C42,PARAM!D:E,2,0),VLOOKUP(D42,PARAM!J:K,2,0),VLOOKUP(E42,PARAM!G:H,2,0),VLOOKUP(G42,PARAM!P:Q,2,0)),"") -> 46200 | J42: =IFERROR(CONCATENATE("*",VLOOKUP(C42,PARAM!D:E,2,0),VLOOKUP(D42,PARAM!J:K,2,0),VLOOKUP(E42,PARAM!G:H,2,0),VLOOKUP(G42,PARAM!P:Q,2,0),"*"),"") -> *46200* | K42: =CONCATENATE(C42," ",D42," ",E42,IF(G42="-","",CONCATENATE(" TALLA ",G42))) -> SPLASH CABALLERO -
A43: 46186 | B43: ACCESORIOS | C43: GORRAS | D43: UNISEX | E43: COLOMBIA | F43: VARIOS | G43: UN | H43: GORRAS LOS ANGELES | I43: =IFERROR(CONCATENATE(VLOOKUP(C43,PARAM!D:E,2,0),VLOOKUP(D43,PARAM!J:K,2,0),VLOOKUP(E43,PARAM!G:H,2,0),VLOOKUP(G43,PARAM!P:Q,2,0)),"") -> 1438630 | J43: =IFERROR(CONCATENATE("*",VLOOKUP(C43,PARAM!D:E,2,0),VLOOKUP(D43,PARAM!J:K,2,0),VLOOKUP(E43,PARAM!G:H,2,0),VLOOKUP(G43,PARAM!P:Q,2,0),"*"),"") -> *1438630* | K43: =CONCATENATE(C43," ",D43," ",E43,IF(G43="-","",CONCATENATE(" TALLA ",G43))) -> GORRAS UNISEX COLOMBIA TALLA UN
A44: 46186 | B44: ACCESORIOS | C44: GORRAS | D44: UNISEX | E44: VARIOS | F44: VARIOS | G44: UN | H44: GORRAS LOS ANGELES | I44: =IFERROR(CONCATENATE(VLOOKUP(C44,PARAM!D:E,2,0),VLOOKUP(D44,PARAM!J:K,2,0),VLOOKUP(E44,PARAM!G:H,2,0),VLOOKUP(G44,PARAM!P:Q,2,0)),"") -> 14327530 | J44: =IFERROR(CONCATENATE("*",VLOOKUP(C44,PARAM!D:E,2,0),VLOOKUP(D44,PARAM!J:K,2,0),VLOOKUP(E44,PARAM!G:H,2,0),VLOOKUP(G44,PARAM!P:Q,2,0),"*"),"") -> *14327530* | K44: =CONCATENATE(C44," ",D44," ",E44,IF(G44="-","",CONCATENATE(" TALLA ",G44))) -> GORRAS UNISEX VARIOS TALLA UN
A45: 46186 | B45: ACCESORIOS | C45: MALETAS | D45: UNISEX | E45: SPRAY GROUND | F45: VARIOS | G45: - | H45: BALU BAGS | I45: =IFERROR(CONCATENATE(VLOOKUP(C45,PARAM!D:E,2,0),VLOOKUP(D45,PARAM!J:K,2,0),VLOOKUP(E45,PARAM!G:H,2,0),VLOOKUP(G45,PARAM!P:Q,2,0)),"") -> 1532540 | J45: =IFERROR(CONCATENATE("*",VLOOKUP(C45,PARAM!D:E,2,0),VLOOKUP(D45,PARAM!J:K,2,0),VLOOKUP(E45,PARAM!G:H,2,0),VLOOKUP(G45,PARAM!P:Q,2,0),"*"),"") -> *1532540* | K45: =CONCATENATE(C45," ",D45," ",E45,IF(G45="-","",CONCATENATE(" TALLA ",G45))) -> MALETAS UNISEX SPRAY GROUND
A46: 46186 | B46: ACCESORIOS | C46: LLAVEROS | D46: DAMA | E46: BOMBA | F46: VARIOS | G46: - | H46: BALU BAGS | I46: =IFERROR(CONCATENATE(VLOOKUP(C46,PARAM!D:E,2,0),VLOOKUP(D46,PARAM!J:K,2,0),VLOOKUP(E46,PARAM!G:H,2,0),VLOOKUP(G46,PARAM!P:Q,2,0)),"") -> 161480 | J46: =IFERROR(CONCATENATE("*",VLOOKUP(C46,PARAM!D:E,2,0),VLOOKUP(D46,PARAM!J:K,2,0),VLOOKUP(E46,PARAM!G:H,2,0),VLOOKUP(G46,PARAM!P:Q,2,0),"*"),"") -> *161480* | K46: =CONCATENATE(C46," ",D46," ",E46,IF(G46="-","",CONCATENATE(" TALLA ",G46))) -> LLAVEROS DAMA BOMBA
A47: 46186 | B47: ACCESORIOS | C47: LLAVEROS | D47: DAMA | E47: CEREZAS BRILLANTE | F47: VARIOS | G47: - | H47: BALU BAGS | I47: =IFERROR(CONCATENATE(VLOOKUP(C47,PARAM!D:E,2,0),VLOOKUP(D47,PARAM!J:K,2,0),VLOOKUP(E47,PARAM!G:H,2,0),VLOOKUP(G47,PARAM!P:Q,2,0)),"") -> 161720 | J47: =IFERROR(CONCATENATE("*",VLOOKUP(C47,PARAM!D:E,2,0),VLOOKUP(D47,PARAM!J:K,2,0),VLOOKUP(E47,PARAM!G:H,2,0),VLOOKUP(G47,PARAM!P:Q,2,0),"*"),"") -> *161720* | K47: =CONCATENATE(C47," ",D47," ",E47,IF(G47="-","",CONCATENATE(" TALLA ",G47))) -> LLAVEROS DAMA CEREZAS BRILLANTE
A48: 46186 | B48: ACCESORIOS | C48: BOLSOS | D48: DAMA | E48: BAUL | F48: NEGRO | G48: - | H48: BALU BAGS | I48: =IFERROR(CONCATENATE(VLOOKUP(C48,PARAM!D:E,2,0),VLOOKUP(D48,PARAM!J:K,2,0),VLOOKUP(E48,PARAM!G:H,2,0),VLOOKUP(G48,PARAM!P:Q,2,0)),"") -> 171460 | J48: =IFERROR(CONCATENATE("*",VLOOKUP(C48,PARAM!D:E,2,0),VLOOKUP(D48,PARAM!J:K,2,0),VLOOKUP(E48,PARAM!G:H,2,0),VLOOKUP(G48,PARAM!P:Q,2,0),"*"),"") -> *171460* | K48: =CONCATENATE(C48," ",D48," ",E48,IF(G48="-","",CONCATENATE(" TALLA ",G48))) -> BOLSOS DAMA BAUL
A49: 46186 | B49: ACCESORIOS | C49: CORREAS | D49: DAMA | E49: - | F49: VARIOS | G49: UN | H49: BALU BAGS | I49: =IFERROR(CONCATENATE(VLOOKUP(C49,PARAM!D:E,2,0),VLOOKUP(D49,PARAM!J:K,2,0),VLOOKUP(E49,PARAM!G:H,2,0),VLOOKUP(G49,PARAM!P:Q,2,0)),"") -> 221030 | J49: =IFERROR(CONCATENATE("*",VLOOKUP(C49,PARAM!D:E,2,0),VLOOKUP(D49,PARAM!J:K,2,0),VLOOKUP(E49,PARAM!G:H,2,0),VLOOKUP(G49,PARAM!P:Q,2,0),"*"),"") -> *221030* | K49: =CONCATENATE(C49," ",D49," ",E49,IF(G49="-","",CONCATENATE(" TALLA ",G49))) -> CORREAS DAMA - TALLA UN
A50: 46186 | B50: ACCESORIOS | C50: BOLSOS | D50: DAMA | E50: CADENA DORADA | F50: VARIOS | G50: - | H50: BALU BAGS | I50: =IFERROR(CONCATENATE(VLOOKUP(C50,PARAM!D:E,2,0),VLOOKUP(D50,PARAM!J:K,2,0),VLOOKUP(E50,PARAM!G:H,2,0),VLOOKUP(G50,PARAM!P:Q,2,0)),"") -> 171570 | J50: =IFERROR(CONCATENATE("*",VLOOKUP(C50,PARAM!D:E,2,0),VLOOKUP(D50,PARAM!J:K,2,0),VLOOKUP(E50,PARAM!G:H,2,0),VLOOKUP(G50,PARAM!P:Q,2,0),"*"),"") -> *171570* | K50: =CONCATENATE(C50," ",D50," ",E50,IF(G50="-","",CONCATENATE(" TALLA ",G50))) -> BOLSOS DAMA CADENA DORADA
A51: 46186 | B51: ACCESORIOS | C51: CARRIEL | D51: UNISEX | E51: ADIDAS | F51: VARIOS | G51: - | H51: BALU BAGS | I51: =IFERROR(CONCATENATE(VLOOKUP(C51,PARAM!D:E,2,0),VLOOKUP(D51,PARAM!J:K,2,0),VLOOKUP(E51,PARAM!G:H,2,0),VLOOKUP(G51,PARAM!P:Q,2,0)),"") -> 183130 | J51: =IFERROR(CONCATENATE("*",VLOOKUP(C51,PARAM!D:E,2,0),VLOOKUP(D51,PARAM!J:K,2,0),VLOOKUP(E51,PARAM!G:H,2,0),VLOOKUP(G51,PARAM!P:Q,2,0),"*"),"") -> *183130* | K51: =CONCATENATE(C51," ",D51," ",E51,IF(G51="-","",CONCATENATE(" TALLA ",G51))) -> CARRIEL UNISEX ADIDAS
A52: 46186 | B52: ACCESORIOS | C52: PECHERAS | D52: CABALLERO | E52: DIFERENTES MARCAS | F52: VARIOS | G52: - | H52: BALU BAGS | I52: =IFERROR(CONCATENATE(VLOOKUP(C52,PARAM!D:E,2,0),VLOOKUP(D52,PARAM!J:K,2,0),VLOOKUP(E52,PARAM!G:H,2,0),VLOOKUP(G52,PARAM!P:Q,2,0)),"") -> 1921180 | J52: =IFERROR(CONCATENATE("*",VLOOKUP(C52,PARAM!D:E,2,0),VLOOKUP(D52,PARAM!J:K,2,0),VLOOKUP(E52,PARAM!G:H,2,0),VLOOKUP(G52,PARAM!P:Q,2,0),"*"),"") -> *1921180* | K52: =CONCATENATE(C52," ",D52," ",E52,IF(G52="-","",CONCATENATE(" TALLA ",G52))) -> PECHERAS CABALLERO DIFERENTES MARCAS
A53: 46186 | B53: ACCESORIOS | C53: CANGUROS | D53: DAMA | E53: BRILLO | F53: VARIOS | G53: - | H53: BALU BAGS | I53: =IFERROR(CONCATENATE(VLOOKUP(C53,PARAM!D:E,2,0),VLOOKUP(D53,PARAM!J:K,2,0),VLOOKUP(E53,PARAM!G:H,2,0),VLOOKUP(G53,PARAM!P:Q,2,0)),"") -> 201540 | J53: =IFERROR(CONCATENATE("*",VLOOKUP(C53,PARAM!D:E,2,0),VLOOKUP(D53,PARAM!J:K,2,0),VLOOKUP(E53,PARAM!G:H,2,0),VLOOKUP(G53,PARAM!P:Q,2,0),"*"),"") -> *201540* | K53: =CONCATENATE(C53," ",D53," ",E53,IF(G53="-","",CONCATENATE(" TALLA ",G53))) -> CANGUROS DAMA BRILLO
A54: 46186 | B54: ACCESORIOS | C54: CANGUROS | D54: UNISEX | E54: ADIDAS | F54: VARIOS | G54: - | H54: BALU BAGS | I54: =IFERROR(CONCATENATE(VLOOKUP(C54,PARAM!D:E,2,0),VLOOKUP(D54,PARAM!J:K,2,0),VLOOKUP(E54,PARAM!G:H,2,0),VLOOKUP(G54,PARAM!P:Q,2,0)),"") -> 203130 | J54: =IFERROR(CONCATENATE("*",VLOOKUP(C54,PARAM!D:E,2,0),VLOOKUP(D54,PARAM!J:K,2,0),VLOOKUP(E54,PARAM!G:H,2,0),VLOOKUP(G54,PARAM!P:Q,2,0),"*"),"") -> *203130* | K54: =CONCATENATE(C54," ",D54," ",E54,IF(G54="-","",CONCATENATE(" TALLA ",G54))) -> CANGUROS UNISEX ADIDAS
... A116: 46186 | B116: ROPA DAMA | C116: CHAQUETAS | D116: DAMA | E116: JEAN TORERA OVEJERA | F116: VARIOS | G116: M | H116: KBU DENIM JACKETS | I116: =IFERROR(CONCATENATE(VLOOKUP(C116,PARAM!D:E,2,0),VLOOKUP(D116,PARAM!J:K,2,0),VLOOKUP(E116,PARAM!G:H,2,0),VLOOKUP(G116,PARAM!P:Q,2,0)),"") -> 25115525 | J116: =IFERROR(CONCATENATE("*",VLOOKUP(C116,PARAM!D:E,2,0),VLOOKUP(D116,PARAM!J:K,2,0),VLOOKUP(E116,PARAM!G:H,2,0),VLOOKUP(G116,PARAM!P:Q,2,0),"*"),"") -> *25115525* | K116: =CONCATENATE(C116," ",D116," ",E116,IF(G116="-","",CONCATENATE(" TALLA ",G116))) -> CHAQUETAS DAMA JEAN TORERA OVEJERA TALLA M
A117: 46186 | B117: ROPA DAMA | C117: JEANS | D117: DAMA | E117: BAGGI | F117: VARIOS | G117: 14 | H117: CONFECCIONES GROWTH | I117: =IFERROR(CONCATENATE(VLOOKUP(C117,PARAM!D:E,2,0),VLOOKUP(D117,PARAM!J:K,2,0),VLOOKUP(E117,PARAM!G:H,2,0),VLOOKUP(G117,PARAM!P:Q,2,0)),"") -> 11395 | J117: =IFERROR(CONCATENATE("*",VLOOKUP(C117,PARAM!D:E,2,0),VLOOKUP(D117,PARAM!J:K,2,0),VLOOKUP(E117,PARAM!G:H,2,0),VLOOKUP(G117,PARAM!P:Q,2,0),"*"),"") -> *11395* | K117: =CONCATENATE(C117," ",D117," ",E117,IF(G117="-","",CONCATENATE(" TALLA ",G117))) -> JEANS DAMA BAGGI TALLA 14
A118: 46186 | B118: ROPA DAMA | C118: JEANS | D118: DAMA | E118: BAGGI | F118: VARIOS | G118: 12 | H118: CONFECCIONES GROWTH | I118: =IFERROR(CONCATENATE(VLOOKUP(C118,PARAM!D:E,2,0),VLOOKUP(D118,PARAM!J:K,2,0),VLOOKUP(E118,PARAM!G:H,2,0),VLOOKUP(G118,PARAM!P:Q,2,0)),"") -> 11394 | J118: =IFERROR(CONCATENATE("*",VLOOKUP(C118,PARAM!D:E,2,0),VLOOKUP(D118,PARAM!J:K,2,0),VLOOKUP(E118,PARAM!G:H,2,0),VLOOKUP(G118,PARAM!P:Q,2,0),"*"),"") -> *11394* | K118: =CONCATENATE(C118," ",D118," ",E118,IF(G118="-","",CONCATENATE(" TALLA ",G118))) -> JEANS DAMA BAGGI TALLA 12
A119: 46186 | B119: ROPA DAMA | C119: JEANS | D119: DAMA | E119: BAGGI | F119: VARIOS | G119: 8 | H119: CONFECCIONES GROWTH | I119: =IFERROR(CONCATENATE(VLOOKUP(C119,PARAM!D:E,2,0),VLOOKUP(D119,PARAM!J:K,2,0),VLOOKUP(E119,PARAM!G:H,2,0),VLOOKUP(G119,PARAM!P:Q,2,0)),"") -> 11392 | J119: =IFERROR(CONCATENATE("*",VLOOKUP(C119,PARAM!D:E,2,0),VLOOKUP(D119,PARAM!J:K,2,0),VLOOKUP(E119,PARAM!G:H,2,0),VLOOKUP(G119,PARAM!P:Q,2,0),"*"),"") -> *11392* | K119: =CONCATENATE(C119," ",D119," ",E119,IF(G119="-","",CONCATENATE(" TALLA ",G119))) -> JEANS DAMA BAGGI TALLA 8
A120: 46186 | B120: ROPA DAMA | C120: JEANS | D120: DAMA | E120: BAGGI | F120: VARIOS | G120: 10 | H120: CONFECCIONES GROWTH | I120: =IFERROR(CONCATENATE(VLOOKUP(C120,PARAM!D:E,2,0),VLOOKUP(D120,PARAM!J:K,2,0),VLOOKUP(E120,PARAM!G:H,2,0),VLOOKUP(G120,PARAM!P:Q,2,0)),"") -> 11393 | J120: =IFERROR(CONCATENATE("*",VLOOKUP(C120,PARAM!D:E,2,0),VLOOKUP(D120,PARAM!J:K,2,0),VLOOKUP(E120,PARAM!G:H,2,0),VLOOKUP(G120,PARAM!P:Q,2,0),"*"),"") -> *11393* | K120: =CONCATENATE(C120," ",D120," ",E120,IF(G120="-","",CONCATENATE(" TALLA ",G120))) -> JEANS DAMA BAGGI TALLA 10
A121: 46186 | B121: ROPA DAMA | C121: JEANS | D121: DAMA | E121: BAGGI CON BRILLANTES | F121: VARIOS | G121: 16 | H121: CONFECCIONES GROWTH | I121: =IFERROR(CONCATENATE(VLOOKUP(C121,PARAM!D:E,2,0),VLOOKUP(D121,PARAM!J:K,2,0),VLOOKUP(E121,PARAM!G:H,2,0),VLOOKUP(G121,PARAM!P:Q,2,0)),"") -> 11406 | J121: =IFERROR(CONCATENATE("*",VLOOKUP(C121,PARAM!D:E,2,0),VLOOKUP(D121,PARAM!J:K,2,0),VLOOKUP(E121,PARAM!G:H,2,0),VLOOKUP(G121,PARAM!P:Q,2,0),"*"),"") -> *11406* | K121: =CONCATENATE(C121," ",D121," ",E121,IF(G121="-","",CONCATENATE(" TALLA ",G121))) -> JEANS DAMA BAGGI CON BRILLANTES TALLA 16
A122: 46186 | B122: ROPA DAMA | C122: CAMISETAS | D122: DAMA | E122: CON BRILLANTES | F122: VARIOS | G122: S | H122: - | I122: =IFERROR(CONCATENATE(VLOOKUP(C122,PARAM!D:E,2,0),VLOOKUP(D122,PARAM!J:K,2,0),VLOOKUP(E122,PARAM!G:H,2,0),VLOOKUP(G122,PARAM!P:Q,2,0)),"") -> 1119127 | J122: =IFERROR(CONCATENATE("*",VLOOKUP(C122,PARAM!D:E,2,0),VLOOKUP(D122,PARAM!J:K,2,0),VLOOKUP(E122,PARAM!G:H,2,0),VLOOKUP(G122,PARAM!P:Q,2,0),"*"),"") -> *1119127* | K122: =CONCATENATE(C122," ",D122," ",E122,IF(G122="-","",CONCATENATE(" TALLA ",G122))) -> CAMISETAS DAMA CON BRILLANTES TALLA S
A123: 46186 | B123: ROPA DAMA | C123: CAMISETAS | D123: DAMA | E123: CON BRILLANTES | F123: VARIOS | G123: M | H123: - | I123: =IFERROR(CONCATENATE(VLOOKUP(C123,PARAM!D:E,2,0),VLOOKUP(D123,PARAM!J:K,2,0),VLOOKUP(E123,PARAM!G:H,2,0),VLOOKUP(G123,PARAM!P:Q,2,0)),"") -> 1119125 | J123: =IFERROR(CONCATENATE("*",VLOOKUP(C123,PARAM!D:E,2,0),VLOOKUP(D123,PARAM!J:K,2,0),VLOOKUP(E123,PARAM!G:H,2,0),VLOOKUP(G123,PARAM!P:Q,2,0),"*"),"") -> *1119125* | K123: =CONCATENATE(C123," ",D123," ",E123,IF(G123="-","",CONCATENATE(" TALLA ",G123))) -> CAMISETAS DAMA CON BRILLANTES TALLA M
A124: 46186 | B124: ROPA DAMA | C124: CAMISETAS | D124: DAMA | E124: CON BRILLANTES | F124: VARIOS | G124: L | H124: - | I124: =IFERROR(CONCATENATE(VLOOKUP(C124,PARAM!D:E,2,0),VLOOKUP(D124,PARAM!J:K,2,0),VLOOKUP(E124,PARAM!G:H,2,0),VLOOKUP(G124,PARAM!P:Q,2,0)),"") -> 1119123 | J124: =IFERROR(CONCATENATE("*",VLOOKUP(C124,PARAM!D:E,2,0),VLOOKUP(D124,PARAM!J:K,2,0),VLOOKUP(E124,PARAM!G:H,2,0),VLOOKUP(G124,PARAM!P:Q,2,0),"*"),"") -> *1119123* | K124: =CONCATENATE(C124," ",D124," ",E124,IF(G124="-","",CONCATENATE(" TALLA ",G124))) -> CAMISETAS DAMA CON BRILLANTES TALLA L
A125: 46186 | B125: ROPA DAMA | C125: CAMISETAS | D125: DAMA | E125: CON BRILLANTES | F125: VARIOS | G125: XL | H125: - | I125: =IFERROR(CONCATENATE(VLOOKUP(C125,PARAM!D:E,2,0),VLOOKUP(D125,PARAM!J:K,2,0),VLOOKUP(E125,PARAM!G:H,2,0),VLOOKUP(G125,PARAM!P:Q,2,0)),"") -> 1119132 | J125: =IFERROR(CONCATENATE("*",VLOOKUP(C125,PARAM!D:E,2,0),VLOOKUP(D125,PARAM!J:K,2,0),VLOOKUP(E125,PARAM!G:H,2,0),VLOOKUP(G125,PARAM!P:Q,2,0),"*"),"") -> *1119132* | K125: =CONCATENATE(C125," ",D125," ",E125,IF(G125="-","",CONCATENATE(" TALLA ",G125))) -> CAMISETAS DAMA CON BRILLANTES TALLA XL
A126: 46186 | B126: ROPA CABALLERO | C126: JEANS | D126: CABALLERO | E126: BAGGI | F126: VARIOS | G126: 30 | H126: CONFECCIONES GROWTH | I126: =IFERROR(CONCATENATE(VLOOKUP(C126,PARAM!D:E,2,0),VLOOKUP(D126,PARAM!J:K,2,0),VLOOKUP(E126,PARAM!G:H,2,0),VLOOKUP(G126,PARAM!P:Q,2,0)),"") -> 123913 | J126: =IFERROR(CONCATENATE("*",VLOOKUP(C126,PARAM!D:E,2,0),VLOOKUP(D126,PARAM!J:K,2,0),VLOOKUP(E126,PARAM!G:H,2,0),VLOOKUP(G126,PARAM!P:Q,2,0),"*"),"") -> *123913* | K126: =CONCATENATE(C126," ",D126," ",E126,IF(G126="-","",CONCATENATE(" TALLA ",G126))) -> JEANS CABALLERO BAGGI TALLA 30
A127: 46186 | B127: ROPA CABALLERO | C127: JEANS | D127: CABALLERO | E127: BAGGI | F127: VARIOS | G127: 32 | H127: CONFECCIONES GROWTH | I127: =IFERROR(CONCATENATE(VLOOKUP(C127,PARAM!D:E,2,0),VLOOKUP(D127,PARAM!J:K,2,0),VLOOKUP(E127,PARAM!G:H,2,0),VLOOKUP(G127,PARAM!P:Q,2,0)),"") -> 123914 | J127: =IFERROR(CONCATENATE("*",VLOOKUP(C127,PARAM!D:E,2,0),VLOOKUP(D127,PARAM!J:K,2,0),VLOOKUP(E127,PARAM!G:H,2,0),VLOOKUP(G127,PARAM!P:Q,2,0),"*"),"") -> *123914* | K127: =CONCATENATE(C127," ",D127," ",E127,IF(G127="-","",CONCATENATE(" TALLA ",G127))) -> JEANS CABALLERO BAGGI TALLA 32
A128: 46186 | B128: ROPA CABALLERO | C128: JEANS | D128: CABALLERO | E128: BAGGI | F128: VARIOS | G128: 34 | H128: CONFECCIONES GROWTH | I128: =IFERROR(CONCATENATE(VLOOKUP(C128,PARAM!D:E,2,0),VLOOKUP(D128,PARAM!J:K,2,0),VLOOKUP(E128,PARAM!G:H,2,0),VLOOKUP(G128,PARAM!P:Q,2,0)),"") -> 123915 | J128: =IFERROR(CONCATENATE("*",VLOOKUP(C128,PARAM!D:E,2,0),VLOOKUP(D128,PARAM!J:K,2,0),VLOOKUP(E128,PARAM!G:H,2,0),VLOOKUP(G128,PARAM!P:Q,2,0),"*"),"") -> *123915* | K128: =CONCATENATE(C128," ",D128," ",E128,IF(G128="-","",CONCATENATE(" TALLA ",G128))) -> JEANS CABALLERO BAGGI TALLA 34
A129: 46186 | B129: ROPA CABALLERO | C129: CAMISAS | D129: CABALLERO | E129: - | F129: VARIOS | G129: L | H129: HHR ELIECER HERNANDEZ | I129: =IFERROR(CONCATENATE(VLOOKUP(C129,PARAM!D:E,2,0),VLOOKUP(D129,PARAM!J:K,2,0),VLOOKUP(E129,PARAM!G:H,2,0),VLOOKUP(G129,PARAM!P:Q,2,0)),"") -> 102023 | J129: =IFERROR(CONCATENATE("*",VLOOKUP(C129,PARAM!D:E,2,0),VLOOKUP(D129,PARAM!J:K,2,0),VLOOKUP(E129,PARAM!G:H,2,0),VLOOKUP(G129,PARAM!P:Q,2,0),"*"),"") -> *102023* | K129: =CONCATENATE(C129," ",D129," ",E129,IF(G129="-","",CONCATENATE(" TALLA ",G129))) -> CAMISAS CABALLERO - TALLA L
A130: 46186 | B130: ROPA CABALLERO | C130: CAMISAS | D130: CABALLERO | E130: JEAN | F130: VARIOS | G130: L | H130: HHR ELIECER HERNANDEZ | I130: =IFERROR(CONCATENATE(VLOOKUP(C130,PARAM!D:E,2,0),VLOOKUP(D130,PARAM!J:K,2,0),VLOOKUP(E130,PARAM!G:H,2,0),VLOOKUP(G130,PARAM!P:Q,2,0)),"") -> 10215223 | J130: =IFERROR(CONCATENATE("*",VLOOKUP(C130,PARAM!D:E,2,0),VLOOKUP(D130,PARAM!J:K,2,0),VLOOKUP(E130,PARAM!G:H,2,0),VLOOKUP(G130,PARAM!P:Q,2,0),"*"),"") -> *10215223* | K130: =CONCATENATE(C130," ",D130," ",E130,IF(G130="-","",CONCATENATE(" TALLA ",G130))) -> CAMISAS CABALLERO JEAN TALLA L
A131: 46186 | B131: ROPA CABALLERO | C131: CAMISAS | D131: CABALLERO | E131: - | F131: VARIOS | G131: M | H131: HHR ELIECER HERNANDEZ | I131: =IFERROR(CONCATENATE(VLOOKUP(C131,PARAM!D:E,2,0),VLOOKUP(D131,PARAM!J:K,2,0),VLOOKUP(E131,PARAM!G:H,2,0),VLOOKUP(G131,PARAM!P:Q,2,0)),"") -> 102025 | J131: =IFERROR(CONCATENATE("*",VLOOKUP(C131,PARAM!D:E,2,0),VLOOKUP(D131,PARAM!J:K,2,0),VLOOKUP(E131,PARAM!G:H,2,0),VLOOKUP(G131,PARAM!P:Q,2,0),"*"),"") -> *102025* | K131: =CONCATENATE(C131," ",D131," ",E131,IF(G131="-","",CONCATENATE(" TALLA ",G131))) -> CAMISAS CABALLERO - TALLA M
A132: 46186 | B132: ROPA CABALLERO | C132: CAMISAS | D132: CABALLERO | E132: JEAN | F132: VARIOS | G132: M | H132: HHR ELIECER HERNANDEZ | I132: =IFERROR(CONCATENATE(VLOOKUP(C132,PARAM!D:E,2,0),VLOOKUP(D132,PARAM!J:K,2,0),VLOOKUP(E132,PARAM!G:H,2,0),VLOOKUP(G132,PARAM!P:Q,2,0)),"") -> 10215225 | J132: =IFERROR(CONCATENATE("*",VLOOKUP(C132,PARAM!D:E,2,0),VLOOKUP(D132,PARAM!J:K,2,0),VLOOKUP(E132,PARAM!G:H,2,0),VLOOKUP(G132,PARAM!P:Q,2,0),"*"),"") -> *10215225* | K132: =CONCATENATE(C132," ",D132," ",E132,IF(G132="-","",CONCATENATE(" TALLA ",G132))) -> CAMISAS CABALLERO JEAN TALLA M
A133: 46186 | B133: ROPA CABALLERO | C133: CAMISAS | D133: CABALLERO | E133: - | F133: VARIOS | G133: S | H133: HHR ELIECER HERNANDEZ | I133: =IFERROR(CONCATENATE(VLOOKUP(C133,PARAM!D:E,2,0),VLOOKUP(D133,PARAM!J:K,2,0),VLOOKUP(E133,PARAM!G:H,2,0),VLOOKUP(G133,PARAM!P:Q,2,0)),"") -> 102027 | J133: =IFERROR(CONCATENATE("*",VLOOKUP(C133,PARAM!D:E,2,0),VLOOKUP(D133,PARAM!J:K,2,0),VLOOKUP(E133,PARAM!G:H,2,0),VLOOKUP(G133,PARAM!P:Q,2,0),"*"),"") -> *102027* | K133: =CONCATENATE(C133," ",D133," ",E133,IF(G133="-","",CONCATENATE(" TALLA ",G133))) -> CAMISAS CABALLERO - TALLA S
A134: 46186 | B134: ROPA CABALLERO | C134: CAMISAS | D134: CABALLERO | E134: - | F134: VARIOS | G134: XL | H134: HHR ELIECER HERNANDEZ | I134: =IFERROR(CONCATENATE(VLOOKUP(C134,PARAM!D:E,2,0),VLOOKUP(D134,PARAM!J:K,2,0),VLOOKUP(E134,PARAM!G:H,2,0),VLOOKUP(G134,PARAM!P:Q,2,0)),"") -> 102032 | J134: =IFERROR(CONCATENATE("*",VLOOKUP(C134,PARAM!D:E,2,0),VLOOKUP(D134,PARAM!J:K,2,0),VLOOKUP(E134,PARAM!G:H,2,0),VLOOKUP(G134,PARAM!P:Q,2,0),"*"),"") -> *102032* | K134: =CONCATENATE(C134," ",D134," ",E134,IF(G134="-","",CONCATENATE(" TALLA ",G134))) -> CAMISAS CABALLERO - TALLA XL
A135: 46186 | B135: ROPA DAMA | C135: BODY | D135: DAMA | E135: AFELPADO | F135: VARIOS | G135: UN | H135: SAMA | I135: =IFERROR(CONCATENATE(VLOOKUP(C135,PARAM!D:E,2,0),VLOOKUP(D135,PARAM!J:K,2,0),VLOOKUP(E135,PARAM!G:H,2,0),VLOOKUP(G135,PARAM!P:Q,2,0)),"") -> 3811430 | J135: =IFERROR(CONCATENATE("*",VLOOKUP(C135,PARAM!D:E,2,0),VLOOKUP(D135,PARAM!J:K,2,0),VLOOKUP(E135,PARAM!G:H,2,0),VLOOKUP(G135,PARAM!P:Q,2,0),"*"),"") -> *3811430* | K135: =CONCATENATE(C135," ",D135," ",E135,IF(G135="-","",CONCATENATE(" TALLA ",G135))) -> BODY DAMA AFELPADO TALLA UN
A136: 46186 | B136: ROPA DAMA | C136: BLUSAS | D136: DAMA | E136: BRILLANTE | F136: VARIOS | G136: UN | H136: SAMA | I136: =IFERROR(CONCATENATE(VLOOKUP(C136,PARAM!D:E,2,0),VLOOKUP(D136,PARAM!J:K,2,0),VLOOKUP(E136,PARAM!G:H,2,0),VLOOKUP(G136,PARAM!P:Q,2,0)),"") -> 615230 | J136: =IFERROR(CONCATENATE("*",VLOOKUP(C136,PARAM!D:E,2,0),VLOOKUP(D136,PARAM!J:K,2,0),VLOOKUP(E136,PARAM!G:H,2,0),VLOOKUP(G136,PARAM!P:Q,2,0),"*"),"") -> *615230* | K136: =CONCATENATE(C136," ",D136," ",E136,IF(G136="-","",CONCATENATE(" TALLA ",G136))) -> BLUSAS DAMA BRILLANTE TALLA UN
A137: 46186 | B137: ROPA DAMA | C137: BLUSAS | D137: DAMA | E137: MARIPOSA | F137: VARIOS | G137: UN | H137: SAMA | I137: =IFERROR(CONCATENATE(VLOOKUP(C137,PARAM!D:E,2,0),VLOOKUP(D137,PARAM!J:K,2,0),VLOOKUP(E137,PARAM!G:H,2,0),VLOOKUP(G137,PARAM!P:Q,2,0)),"") -> 6118430 | J137: =IFERROR(CONCATENATE("*",VLOOKUP(C137,PARAM!D:E,2,0),VLOOKUP(D137,PARAM!J:K,2,0),VLOOKUP(E137,PARAM!G:H,2,0),VLOOKUP(G137,PARAM!P:Q,2,0),"*"),"") -> *6118430* | K137: =CONCATENATE(C137," ",D137," ",E137,IF(G137="-","",CONCATENATE(" TALLA ",G137))) -> BLUSAS DAMA MARIPOSA TALLA UN
A138: 46186 | B138: ROPA DAMA | C138: BLUSAS | D138: DAMA | E138: AMBAR | F138: VARIOS | G138: UN | H138: SAMA | I138: =IFERROR(CONCATENATE(VLOOKUP(C138,PARAM!D:E,2,0),VLOOKUP(D138,PARAM!J:K,2,0),VLOOKUP(E138,PARAM!G:H,2,0),VLOOKUP(G138,PARAM!P:Q,2,0)),"") -> 612430 | J138: =IFERROR(CONCATENATE("*",VLOOKUP(C138,PARAM!D:E,2,0),VLOOKUP(D138,PARAM!J:K,2,0),VLOOKUP(E138,PARAM!G:H,2,0),VLOOKUP(G138,PARAM!P:Q,2,0),"*"),"") -> *612430* | K138: =CONCATENATE(C138," ",D138," ",E138,IF(G138="-","",CONCATENATE(" TALLA ",G138))) -> BLUSAS DAMA AMBAR TALLA UN
A139: 46186 | B139: ROPA DAMA | C139: BODY | D139: DAMA | E139: BODY COSMO | F139: VARIOS | G139: UN | H139: SAMA | I139: =IFERROR(CONCATENATE(VLOOKUP(C139,PARAM!D:E,2,0),VLOOKUP(D139,PARAM!J:K,2,0),VLOOKUP(E139,PARAM!G:H,2,0),VLOOKUP(G139,PARAM!P:Q,2,0)),"") -> 3814730 | J139: =IFERROR(CONCATENATE("*",VLOOKUP(C139,PARAM!D:E,2,0),VLOOKUP(D139,PARAM!J:K,2,0),VLOOKUP(E139,PARAM!G:H,2,0),VLOOKUP(G139,PARAM!P:Q,2,0),"*"),"") -> *3814730* | K139: =CONCATENATE(C139," ",D139," ",E139,IF(G139="-","",CONCATENATE(" TALLA ",G139))) -> BODY DAMA BODY COSMO TALLA UN
A140: 46186 | B140: ROPA DAMA | C140: BODY | D140: DAMA | E140: OTRA CLASE | F140: VARIOS | G140: UN | H140: SAMA | I140: =IFERROR(CONCATENATE(VLOOKUP(C140,PARAM!D:E,2,0),VLOOKUP(D140,PARAM!J:K,2,0),VLOOKUP(E140,PARAM!G:H,2,0),VLOOKUP(G140,PARAM!P:Q,2,0)),"") -> 38119930 | J140: =IFERROR(CONCATENATE("*",VLOOKUP(C140,PARAM!D:E,2,0),VLOOKUP(D140,PARAM!J:K,2,0),VLOOKUP(E140,PARAM!G:H,2,0),VLOOKUP(G140,PARAM!P:Q,2,0),"*"),"") -> *38119930* | K140: =CONCATENATE(C140," ",D140," ",E140,IF(G140="-","",CONCATENATE(" TALLA ",G140))) -> BODY DAMA OTRA CLASE TALLA UN
... A154: 46186 | B154: ROPA CABALLERO | C154: CAMISETAS | D154: CABALLERO | E154: POLO SEDA FRIA | F154: VARIOS | G154: XL | H154: DRAGMA | I154: =IFERROR(CONCATENATE(VLOOKUP(C154,PARAM!D:E,2,0),VLOOKUP(D154,PARAM!J:K,2,0),VLOOKUP(E154,PARAM!G:H,2,0),VLOOKUP(G154,PARAM!P:Q,2,0)),"") -> 11221832 | J154: =IFERROR(CONCATENATE("*",VLOOKUP(C154,PARAM!D:E,2,0),VLOOKUP(D154,PARAM!J:K,2,0),VLOOKUP(E154,PARAM!G:H,2,0),VLOOKUP(G154,PARAM!P:Q,2,0),"*"),"") -> *11221832* | K154: =CONCATENATE(C154," ",D154," ",E154,IF(G154="-","",CONCATENATE(" TALLA ",G154))) -> CAMISETAS CABALLERO POLO SEDA FRIA TALLA XL
A155: 46186 | B155: ROPA DAMA | C155: PANTALONES | D155: DAMA | E155: NOCHE | F155: VARIOS | G155: 12 | H155: R&D | I155: =IFERROR(CONCATENATE(VLOOKUP(C155,PARAM!D:E,2,0),VLOOKUP(D155,PARAM!J:K,2,0),VLOOKUP(E155,PARAM!G:H,2,0),VLOOKUP(G155,PARAM!P:Q,2,0)),"") -> 211974 | J155: =IFERROR(CONCATENATE("*",VLOOKUP(C155,PARAM!D:E,2,0),VLOOKUP(D155,PARAM!J:K,2,0),VLOOKUP(E155,PARAM!G:H,2,0),VLOOKUP(G155,PARAM!P:Q,2,0),"*"),"") -> *211974* | K155: =CONCATENATE(C155," ",D155," ",E155,IF(G155="-","",CONCATENATE(" TALLA ",G155))) -> PANTALONES DAMA NOCHE TALLA 12
A156: 46186 | B156: ROPA DAMA | C156: PANTALONES | D156: DAMA | E156: NOCHE | F156: VARIOS | G156: 14 | H156: R&D | I156: =IFERROR(CONCATENATE(VLOOKUP(C156,PARAM!D:E,2,0),VLOOKUP(D156,PARAM!J:K,2,0),VLOOKUP(E156,PARAM!G:H,2,0),VLOOKUP(G156,PARAM!P:Q,2,0)),"") -> 211975 | J156: =IFERROR(CONCATENATE("*",VLOOKUP(C156,PARAM!D:E,2,0),VLOOKUP(D156,PARAM!J:K,2,0),VLOOKUP(E156,PARAM!G:H,2,0),VLOOKUP(G156,PARAM!P:Q,2,0),"*"),"") -> *211975* | K156: =CONCATENATE(C156," ",D156," ",E156,IF(G156="-","",CONCATENATE(" TALLA ",G156))) -> PANTALONES DAMA NOCHE TALLA 14
A157: 46186 | B157: ROPA DAMA | C157: PANTALONES | D157: DAMA | E157: NOCHE | F157: VARIOS | G157: 10 | H157: R&D | I157: =IFERROR(CONCATENATE(VLOOKUP(C157,PARAM!D:E,2,0),VLOOKUP(D157,PARAM!J:K,2,0),VLOOKUP(E157,PARAM!G:H,2,0),VLOOKUP(G157,PARAM!P:Q,2,0)),"") -> 211973 | J157: =IFERROR(CONCATENATE("*",VLOOKUP(C157,PARAM!D:E,2,0),VLOOKUP(D157,PARAM!J:K,2,0),VLOOKUP(E157,PARAM!G:H,2,0),VLOOKUP(G157,PARAM!P:Q,2,0),"*"),"") -> *211973* | K157: =CONCATENATE(C157," ",D157," ",E157,IF(G157="-","",CONCATENATE(" TALLA ",G157))) -> PANTALONES DAMA NOCHE TALLA 10
A158: 46186 | B158: ROPA DAMA | C158: FALDAS | D158: DAMA | E158: GAMUSA | F158: VARIOS | G158: 6 | H158: R&D | I158: =IFERROR(CONCATENATE(VLOOKUP(C158,PARAM!D:E,2,0),VLOOKUP(D158,PARAM!J:K,2,0),VLOOKUP(E158,PARAM!G:H,2,0),VLOOKUP(G158,PARAM!P:Q,2,0)),"") -> 911371 | J158: =IFERROR(CONCATENATE("*",VLOOKUP(C158,PARAM!D:E,2,0),VLOOKUP(D158,PARAM!J:K,2,0),VLOOKUP(E158,PARAM!G:H,2,0),VLOOKUP(G158,PARAM!P:Q,2,0),"*"),"") -> *911371* | K158: =CONCATENATE(C158," ",D158," ",E158,IF(G158="-","",CONCATENATE(" TALLA ",G158))) -> FALDAS DAMA GAMUSA TALLA 6
A159: 46186 | B159: ROPA DAMA | C159: FALDAS | D159: DAMA | E159: GAMUSA | F159: VARIOS | G159: 8 | H159: R&D | I159: =IFERROR(CONCATENATE(VLOOKUP(C159,PARAM!D:E,2,0),VLOOKUP(D159,PARAM!J:K,2,0),VLOOKUP(E159,PARAM!G:H,2,0),VLOOKUP(G159,PARAM!P:Q,2,0)),"") -> 911372 | J159: =IFERROR(CONCATENATE("*",VLOOKUP(C159,PARAM!D:E,2,0),VLOOKUP(D159,PARAM!J:K,2,0),VLOOKUP(E159,PARAM!G:H,2,0),VLOOKUP(G159,PARAM!P:Q,2,0),"*"),"") -> *911372* | K159: =CONCATENATE(C159," ",D159," ",E159,IF(G159="-","",CONCATENATE(" TALLA ",G159))) -> FALDAS DAMA GAMUSA TALLA 8
A160: 46186 | B160: ROPA DAMA | C160: FALDAS | D160: DAMA | E160: GAMUSA | F160: VARIOS | G160: 12 | H160: R&D | I160: =IFERROR(CONCATENATE(VLOOKUP(C160,PARAM!D:E,2,0),VLOOKUP(D160,PARAM!J:K,2,0),VLOOKUP(E160,PARAM!G:H,2,0),VLOOKUP(G160,PARAM!P:Q,2,0)),"") -> 911374 | J160: =IFERROR(CONCATENATE("*",VLOOKUP(C160,PARAM!D:E,2,0),VLOOKUP(D160,PARAM!J:K,2,0),VLOOKUP(E160,PARAM!G:H,2,0),VLOOKUP(G160,PARAM!P:Q,2,0),"*"),"") -> *911374* | K160: =CONCATENATE(C160," ",D160," ",E160,IF(G160="-","",CONCATENATE(" TALLA ",G160))) -> FALDAS DAMA GAMUSA TALLA 12
A161: 46186 | B161: ROPA DAMA | C161: FALDAS | D161: DAMA | E161: GAMUSA | F161: VARIOS | G161: 10 | H161: R&D | I161: =IFERROR(CONCATENATE(VLOOKUP(C161,PARAM!D:E,2,0),VLOOKUP(D161,PARAM!J:K,2,0),VLOOKUP(E161,PARAM!G:H,2,0),VLOOKUP(G161,PARAM!P:Q,2,0)),"") -> 911373 | J161: =IFERROR(CONCATENATE("*",VLOOKUP(C161,PARAM!D:E,2,0),VLOOKUP(D161,PARAM!J:K,2,0),VLOOKUP(E161,PARAM!G:H,2,0),VLOOKUP(G161,PARAM!P:Q,2,0),"*"),"") -> *911373* | K161: =CONCATENATE(C161," ",D161," ",E161,IF(G161="-","",CONCATENATE(" TALLA ",G161))) -> FALDAS DAMA GAMUSA TALLA 10
A162: 46186 | B162: ROPA DAMA | C162: CHAQUETAS | D162: DAMA | E162: GAMUSA | F162: VARIOS | G162: M | H162: MODA FEMENINA | I162: =IFERROR(CONCATENATE(VLOOKUP(C162,PARAM!D:E,2,0),VLOOKUP(D162,PARAM!J:K,2,0),VLOOKUP(E162,PARAM!G:H,2,0),VLOOKUP(G162,PARAM!P:Q,2,0)),"") -> 25113725 | J162: =IFERROR(CONCATENATE("*",VLOOKUP(C162,PARAM!D:E,2,0),VLOOKUP(D162,PARAM!J:K,2,0),VLOOKUP(E162,PARAM!G:H,2,0),VLOOKUP(G162,PARAM!P:Q,2,0),"*"),"") -> *25113725* | K162: =CONCATENATE(C162," ",D162," ",E162,IF(G162="-","",CONCATENATE(" TALLA ",G162))) -> CHAQUETAS DAMA GAMUSA TALLA M
A163: 46186 | B163: ROPA DAMA | C163: CHAQUETAS | D163: DAMA | E163: GAMUSA | F163: VARIOS | G163: L | H163: MODA FEMENINA | I163: =IFERROR(CONCATENATE(VLOOKUP(C163,PARAM!D:E,2,0),VLOOKUP(D163,PARAM!J:K,2,0),VLOOKUP(E163,PARAM!G:H,2,0),VLOOKUP(G163,PARAM!P:Q,2,0)),"") -> 25113723 | J163: =IFERROR(CONCATENATE("*",VLOOKUP(C163,PARAM!D:E,2,0),VLOOKUP(D163,PARAM!J:K,2,0),VLOOKUP(E163,PARAM!G:H,2,0),VLOOKUP(G163,PARAM!P:Q,2,0),"*"),"") -> *25113723* | K163: =CONCATENATE(C163," ",D163," ",E163,IF(G163="-","",CONCATENATE(" TALLA ",G163))) -> CHAQUETAS DAMA GAMUSA TALLA L
A164: 46186 | B164: ROPA DAMA | C164: CHAQUETAS | D164: DAMA | E164: PAÑO | F164: VARIOS | G164: M | H164: MARTINA BENDITA | I164: =IFERROR(CONCATENATE(VLOOKUP(C164,PARAM!D:E,2,0),VLOOKUP(D164,PARAM!J:K,2,0),VLOOKUP(E164,PARAM!G:H,2,0),VLOOKUP(G164,PARAM!P:Q,2,0)),"") -> 25120525 | J164: =IFERROR(CONCATENATE("*",VLOOKUP(C164,PARAM!D:E,2,0),VLOOKUP(D164,PARAM!J:K,2,0),VLOOKUP(E164,PARAM!G:H,2,0),VLOOKUP(G164,PARAM!P:Q,2,0),"*"),"") -> *25120525* | K164: =CONCATENATE(C164," ",D164," ",E164,IF(G164="-","",CONCATENATE(" TALLA ",G164))) -> CHAQUETAS DAMA PAÑO TALLA M
A165: 46186 | B165: ROPA DAMA | C165: CHAQUETAS | D165: DAMA | E165: PAÑO | F165: VARIOS | G165: L | H165: MARTINA BENDITA | I165: =IFERROR(CONCATENATE(VLOOKUP(C165,PARAM!D:E,2,0),VLOOKUP(D165,PARAM!J:K,2,0),VLOOKUP(E165,PARAM!G:H,2,0),VLOOKUP(G165,PARAM!P:Q,2,0)),"") -> 25120523 | J165: =IFERROR(CONCATENATE("*",VLOOKUP(C165,PARAM!D:E,2,0),VLOOKUP(D165,PARAM!J:K,2,0),VLOOKUP(E165,PARAM!G:H,2,0),VLOOKUP(G165,PARAM!P:Q,2,0),"*"),"") -> *25120523* | K165: =CONCATENATE(C165," ",D165," ",E165,IF(G165="-","",CONCATENATE(" TALLA ",G165))) -> CHAQUETAS DAMA PAÑO TALLA L
A166: 46186 | B166: DEPORTIVO | C166: PANTALONES | D166: UNISEX | E166: IMPERMEABLE | F166: VARIOS | G166: XXL | H166: MADRUGON | I166: =IFERROR(CONCATENATE(VLOOKUP(C166,PARAM!D:E,2,0),VLOOKUP(D166,PARAM!J:K,2,0),VLOOKUP(E166,PARAM!G:H,2,0),VLOOKUP(G166,PARAM!P:Q,2,0)),"") -> 2314534 | J166: =IFERROR(CONCATENATE("*",VLOOKUP(C166,PARAM!D:E,2,0),VLOOKUP(D166,PARAM!J:K,2,0),VLOOKUP(E166,PARAM!G:H,2,0),VLOOKUP(G166,PARAM!P:Q,2,0),"*"),"") -> *2314534* | K166: =CONCATENATE(C166," ",D166," ",E166,IF(G166="-","",CONCATENATE(" TALLA ",G166))) -> PANTALONES UNISEX IMPERMEABLE TALLA XXL
A167: 46186 | B167: DEPORTIVO | C167: PANTALONES | D167: UNISEX | E167: IMPERMEABLE | F167: VARIOS | G167: XL | H167: MADRUGON | I167: =IFERROR(CONCATENATE(VLOOKUP(C167,PARAM!D:E,2,0),VLOOKUP(D167,PARAM!J:K,2,0),VLOOKUP(E167,PARAM!G:H,2,0),VLOOKUP(G167,PARAM!P:Q,2,0)),"") -> 2314532 | J167: =IFERROR(CONCATENATE("*",VLOOKUP(C167,PARAM!D:E,2,0),VLOOKUP(D167,PARAM!J:K,2,0),VLOOKUP(E167,PARAM!G:H,2,0),VLOOKUP(G167,PARAM!P:Q,2,0),"*"),"") -> *2314532* | K167: =CONCATENATE(C167," ",D167," ",E167,IF(G167="-","",CONCATENATE(" TALLA ",G167))) -> PANTALONES UNISEX IMPERMEABLE TALLA XL
A168: 46186 | B168: DEPORTIVO | C168: PANTALONES | D168: UNISEX | E168: IMPERMEABLE | F168: VARIOS | G168: L | H168: MADRUGON | I168: =IFERROR(CONCATENATE(VLOOKUP(C168,PARAM!D:E,2,0),VLOOKUP(D168,PARAM!J:K,2,0),VLOOKUP(E168,PARAM!G:H,2,0),VLOOKUP(G168,PARAM!P:Q,2,0)),"") -> 2314523 | J168: =IFERROR(CONCATENATE("*",VLOOKUP(C168,PARAM!D:E,2,0),VLOOKUP(D168,PARAM!J:K,2,0),VLOOKUP(E168,PARAM!G:H,2,0),VLOOKUP(G168,PARAM!P:Q,2,0),"*"),"") -> *2314523* | K168: =CONCATENATE(C168," ",D168," ",E168,IF(G168="-","",CONCATENATE(" TALLA ",G168))) -> PANTALONES UNISEX IMPERMEABLE TALLA L
A169: 46186 | B169: DEPORTIVO | C169: PANTALONES | D169: UNISEX | E169: IMPERMEABLE | F169: VARIOS | G169: XL | H169: MADRUGON | I169: =IFERROR(CONCATENATE(VLOOKUP(C169,PARAM!D:E,2,0),VLOOKUP(D169,PARAM!J:K,2,0),VLOOKUP(E169,PARAM!G:H,2,0),VLOOKUP(G169,PARAM!P:Q,2,0)),"") -> 2314532 | J169: =IFERROR(CONCATENATE("*",VLOOKUP(C169,PARAM!D:E,2,0),VLOOKUP(D169,PARAM!J:K,2,0),VLOOKUP(E169,PARAM!G:H,2,0),VLOOKUP(G169,PARAM!P:Q,2,0),"*"),"") -> *2314532* | K169: =CONCATENATE(C169," ",D169," ",E169,IF(G169="-","",CONCATENATE(" TALLA ",G169))) -> PANTALONES UNISEX IMPERMEABLE TALLA XL
A170: 46186 | B170: DEPORTIVO | C170: PANTALONES | D170: UNISEX | E170: IMPERMEABLE | F170: VARIOS | G170: UN | H170: MADRUGON | I170: =IFERROR(CONCATENATE(VLOOKUP(C170,PARAM!D:E,2,0),VLOOKUP(D170,PARAM!J:K,2,0),VLOOKUP(E170,PARAM!G:H,2,0),VLOOKUP(G170,PARAM!P:Q,2,0)),"") -> 2314530 | J170: =IFERROR(CONCATENATE("*",VLOOKUP(C170,PARAM!D:E,2,0),VLOOKUP(D170,PARAM!J:K,2,0),VLOOKUP(E170,PARAM!G:H,2,0),VLOOKUP(G170,PARAM!P:Q,2,0),"*"),"") -> *2314530* | K170: =CONCATENATE(C170," ",D170," ",E170,IF(G170="-","",CONCATENATE(" TALLA ",G170))) -> PANTALONES UNISEX IMPERMEABLE TALLA UN
A171: 46186 | B171: DEPORTIVO | C171: PANTALONES | D171: UNISEX | E171: VIOTO | F171: VARIOS | G171: M | H171: MADRUGON | I171: =IFERROR(CONCATENATE(VLOOKUP(C171,PARAM!D:E,2,0),VLOOKUP(D171,PARAM!J:K,2,0),VLOOKUP(E171,PARAM!G:H,2,0),VLOOKUP(G171,PARAM!P:Q,2,0)),"") -> 2327625 | J171: =IFERROR(CONCATENATE("*",VLOOKUP(C171,PARAM!D:E,2,0),VLOOKUP(D171,PARAM!J:K,2,0),VLOOKUP(E171,PARAM!G:H,2,0),VLOOKUP(G171,PARAM!P:Q,2,0),"*"),"") -> *2327625* | K171: =CONCATENATE(C171," ",D171," ",E171,IF(G171="-","",CONCATENATE(" TALLA ",G171))) -> PANTALONES UNISEX VIOTO TALLA M
A172: 46186 | B172: DEPORTIVO | C172: PANTALONES | D172: UNISEX | E172: IMPERMEABLE | F172: VARIOS | G172: M | H172: MADRUGON | I172: =IFERROR(CONCATENATE(VLOOKUP(C172,PARAM!D:E,2,0),VLOOKUP(D172,PARAM!J:K,2,0),VLOOKUP(E172,PARAM!G:H,2,0),VLOOKUP(G172,PARAM!P:Q,2,0)),"") -> 2314525 | J172: =IFERROR(CONCATENATE("*",VLOOKUP(C172,PARAM!D:E,2,0),VLOOKUP(D172,PARAM!J:K,2,0),VLOOKUP(E172,PARAM!G:H,2,0),VLOOKUP(G172,PARAM!P:Q,2,0),"*"),"") -> *2314525* | K172: =CONCATENATE(C172," ",D172," ",E172,IF(G172="-","",CONCATENATE(" TALLA ",G172))) -> PANTALONES UNISEX IMPERMEABLE TALLA M
A173: 46186 | B173: DEPORTIVO | C173: PANTALONES | D173: UNISEX | E173: IMPERMEABLE | F173: VARIOS | G173: L | H173: MADRUGON | I173: =IFERROR(CONCATENATE(VLOOKUP(C173,PARAM!D:E,2,0),VLOOKUP(D173,PARAM!J:K,2,0),VLOOKUP(E173,PARAM!G:H,2,0),VLOOKUP(G173,PARAM!P:Q,2,0)),"") -> 2314523 | J173: =IFERROR(CONCATENATE("*",VLOOKUP(C173,PARAM!D:E,2,0),VLOOKUP(D173,PARAM!J:K,2,0),VLOOKUP(E173,PARAM!G:H,2,0),VLOOKUP(G173,PARAM!P:Q,2,0),"*"),"") -> *2314523* | K173: =CONCATENATE(C173," ",D173," ",E173,IF(G173="-","",CONCATENATE(" TALLA ",G173))) -> PANTALONES UNISEX IMPERMEABLE TALLA L
... A256: 46186 | B256: ROPA DAMA | C256: CHAQUETAS | D256: DAMA | E256: OVEJERA CUERINA | F256: VARIOS | G256: M | H256: KING 7 ECUATORIANOS | I256: =IFERROR(CONCATENATE(VLOOKUP(C256,PARAM!D:E,2,0),VLOOKUP(D256,PARAM!J:K,2,0),VLOOKUP(E256,PARAM!G:H,2,0),VLOOKUP(G256,PARAM!P:Q,2,0)),"") -> 25120025 | J256: =IFERROR(CONCATENATE("*",VLOOKUP(C256,PARAM!D:E,2,0),VLOOKUP(D256,PARAM!J:K,2,0),VLOOKUP(E256,PARAM!G:H,2,0),VLOOKUP(G256,PARAM!P:Q,2,0),"*"),"") -> *25120025* | K256: =CONCATENATE(C256," ",D256," ",E256,IF(G256="-","",CONCATENATE(" TALLA ",G256))) -> CHAQUETAS DAMA OVEJERA CUERINA TALLA M
A257: 46186 | B257: ROPA DAMA | C257: JEANS | D257: DAMA | E257: CAMUFLADO | F257: AZUL | G257: 16 | H257: R TREIK | I257: =IFERROR(CONCATENATE(VLOOKUP(C257,PARAM!D:E,2,0),VLOOKUP(D257,PARAM!J:K,2,0),VLOOKUP(E257,PARAM!G:H,2,0),VLOOKUP(G257,PARAM!P:Q,2,0)),"") -> 11666 | J257: =IFERROR(CONCATENATE("*",VLOOKUP(C257,PARAM!D:E,2,0),VLOOKUP(D257,PARAM!J:K,2,0),VLOOKUP(E257,PARAM!G:H,2,0),VLOOKUP(G257,PARAM!P:Q,2,0),"*"),"") -> *11666* | K257: =CONCATENATE(C257," ",D257," ",E257,IF(G257="-","",CONCATENATE(" TALLA ",G257))) -> JEANS DAMA CAMUFLADO TALLA 16
A258: 46186 | B258: ROPA DAMA | C258: JEANS | D258: DAMA | E258: CAMUFLADO | F258: AZUL | G258: 14 | H258: R TREIK | I258: =IFERROR(CONCATENATE(VLOOKUP(C258,PARAM!D:E,2,0),VLOOKUP(D258,PARAM!J:K,2,0),VLOOKUP(E258,PARAM!G:H,2,0),VLOOKUP(G258,PARAM!P:Q,2,0)),"") -> 11665 | J258: =IFERROR(CONCATENATE("*",VLOOKUP(C258,PARAM!D:E,2,0),VLOOKUP(D258,PARAM!J:K,2,0),VLOOKUP(E258,PARAM!G:H,2,0),VLOOKUP(G258,PARAM!P:Q,2,0),"*"),"") -> *11665* | K258: =CONCATENATE(C258," ",D258," ",E258,IF(G258="-","",CONCATENATE(" TALLA ",G258))) -> JEANS DAMA CAMUFLADO TALLA 14
A259: 46186 | B259: ROPA DAMA | C259: JEANS | D259: DAMA | E259: CAMUFLADO | F259: AZUL | G259: 10 | H259: R TREIK | I259: =IFERROR(CONCATENATE(VLOOKUP(C259,PARAM!D:E,2,0),VLOOKUP(D259,PARAM!J:K,2,0),VLOOKUP(E259,PARAM!G:H,2,0),VLOOKUP(G259,PARAM!P:Q,2,0)),"") -> 11663 | J259: =IFERROR(CONCATENATE("*",VLOOKUP(C259,PARAM!D:E,2,0),VLOOKUP(D259,PARAM!J:K,2,0),VLOOKUP(E259,PARAM!G:H,2,0),VLOOKUP(G259,PARAM!P:Q,2,0),"*"),"") -> *11663* | K259: =CONCATENATE(C259," ",D259," ",E259,IF(G259="-","",CONCATENATE(" TALLA ",G259))) -> JEANS DAMA CAMUFLADO TALLA 10
A260: 46186 | B260: ROPA DAMA | C260: JEANS | D260: DAMA | E260: CAMUFLADO | F260: AZUL | G260: 8 | H260: R TREIK | I260: =IFERROR(CONCATENATE(VLOOKUP(C260,PARAM!D:E,2,0),VLOOKUP(D260,PARAM!J:K,2,0),VLOOKUP(E260,PARAM!G:H,2,0),VLOOKUP(G260,PARAM!P:Q,2,0)),"") -> 11662 | J260: =IFERROR(CONCATENATE("*",VLOOKUP(C260,PARAM!D:E,2,0),VLOOKUP(D260,PARAM!J:K,2,0),VLOOKUP(E260,PARAM!G:H,2,0),VLOOKUP(G260,PARAM!P:Q,2,0),"*"),"") -> *11662* | K260: =CONCATENATE(C260," ",D260," ",E260,IF(G260="-","",CONCATENATE(" TALLA ",G260))) -> JEANS DAMA CAMUFLADO TALLA 8
A261: 46186 | B261: ROPA DAMA | C261: JEANS | D261: DAMA | E261: CAMUFLADO | F261: AZUL | G261: 12 | H261: R TREIK | I261: =IFERROR(CONCATENATE(VLOOKUP(C261,PARAM!D:E,2,0),VLOOKUP(D261,PARAM!J:K,2,0),VLOOKUP(E261,PARAM!G:H,2,0),VLOOKUP(G261,PARAM!P:Q,2,0)),"") -> 11664 | J261: =IFERROR(CONCATENATE("*",VLOOKUP(C261,PARAM!D:E,2,0),VLOOKUP(D261,PARAM!J:K,2,0),VLOOKUP(E261,PARAM!G:H,2,0),VLOOKUP(G261,PARAM!P:Q,2,0),"*"),"") -> *11664* | K261: =CONCATENATE(C261," ",D261," ",E261,IF(G261="-","",CONCATENATE(" TALLA ",G261))) -> JEANS DAMA CAMUFLADO TALLA 12
A262: 46186 | B262: ROPA DAMA | C262: JEANS | D262: DAMA | E262: 4 BOTONES SIN BOLSILLO | F262: AZUL | G262: 10 | H262: R TREIK | I262: =IFERROR(CONCATENATE(VLOOKUP(C262,PARAM!D:E,2,0),VLOOKUP(D262,PARAM!J:K,2,0),VLOOKUP(E262,PARAM!G:H,2,0),VLOOKUP(G262,PARAM!P:Q,2,0)),"") -> 1153 | J262: =IFERROR(CONCATENATE("*",VLOOKUP(C262,PARAM!D:E,2,0),VLOOKUP(D262,PARAM!J:K,2,0),VLOOKUP(E262,PARAM!G:H,2,0),VLOOKUP(G262,PARAM!P:Q,2,0),"*"),"") -> *1153* | K262: =CONCATENATE(C262," ",D262," ",E262,IF(G262="-","",CONCATENATE(" TALLA ",G262))) -> JEANS DAMA 4 BOTONES SIN BOLSILLO TALLA 10
A263: 46186 | B263: DEPORTIVO | C263: PANTALONETAS | D263: CABALLERO | E263: DEPORTIVA | F263: VARIOS | G263: S-M | I263: =IFERROR(CONCATENATE(VLOOKUP(C263,PARAM!D:E,2,0),VLOOKUP(D263,PARAM!J:K,2,0),VLOOKUP(E263,PARAM!G:H,2,0),VLOOKUP(G263,PARAM!P:Q,2,0)),"") -> 35211328 | J263: =IFERROR(CONCATENATE("*",VLOOKUP(C263,PARAM!D:E,2,0),VLOOKUP(D263,PARAM!J:K,2,0),VLOOKUP(E263,PARAM!G:H,2,0),VLOOKUP(G263,PARAM!P:Q,2,0),"*"),"") -> *35211328* | K263: =CONCATENATE(C263," ",D263," ",E263,IF(G263="-","",CONCATENATE(" TALLA ",G263))) -> PANTALONETAS CABALLERO DEPORTIVA TALLA S-M
...

Sheet PARAM
A1: LINEAS | B1: ID LINEA | D1: CATEGORIAS | E1: ID CATEGORIA | G1: ESTILO-DETALLE | H1: ID ESTILO-DETALLE | J1: GENERO | K1: ID GENERO | M1: COLOR | N1: ID COLOR | P1: TALLA | Q1: ID TALLA | S1: PROVEEDOR-MARCA | T1: ID PROVEEDOR
A2: ROPA DAMA | B2: 1 | D2: JEANS | E2: 1 | G2: - | H2: 0 | J2: DAMA | K2: 1 | M2: - | N2: 0 | P2: - | Q2: 0 | S2: - | T2: 0
A3: ROPA CABALLERO | B3: 2 | D3: PANTALONES | E3: 2 | G3: 1 BOTON | H3: =H2+1 -> 1 | J3: CABALLERO | K3: 2 | M3: AMARILLO | N3: 1 | P3: 6 | Q3: 1 | S3: ADIDAS | T3: =T2+1 -> 1
A4: ROPA OVERSIZE | B4: 3 | D4: LICRAS | E4: 3 | G4: 1 BOTON BOTA RECTA | H4: =H3+1 -> 2 | J4: UNISEX | K4: 3 | M4: AZUL | N4: 2 | P4: 8 | Q4: 2 | S4: AKKA SPORT | T4: =T3+1 -> 2
A5: ACCESORIOS | B5: 4 | D5: SHORTS | E5: 4 | G5: 3/4 VALANT | H5: =H4+1 -> 3 | J5: NIÑO | K5: 4 | M5: AZUL CLARO | N5: 3 | P5: 10 | Q5: 3 | S5: ATHLETIC BODEGA MEDELLÍN | T5: =T4+1 -> 3
A6: DEPORTIVO | B6: 5 | D6: BERMUDAS | E6: 5 | G6: 4 BOTONES | H6: =H5+1 -> 4 | J6: - | K6: 0 | M6: AZUL NOCHE | N6: 4 | P6: 12 | Q6: 4 | S6: BALU BAGS | T6: =T5+1 -> 4
A7: LICRA DEPORTIVA | B7: 6 | D7: BLUSAS | E7: 6 | G7: 4 BOTONES SIN BOLSILLO | H7: =H6+1 -> 5 | M7: BEIGE | N7: 5 | P7: 14 | Q7: 5 | S7: CONFECCIONES GROWTH | T7: =T6+1 -> 5
A8: PERFUMERIA | B8: 7 | D8: TEJIDOS | E8: 7 | G8: A RODILLA | H8: =H7+1 -> 6 | M8: BLANCO | N8: 6 | P8: 16 | Q8: 6 | S8: CONFECCIONES PERFECT | T8: =T7+1 -> 6
A9: MAQUILLAJE | B9: 8 | D9: VESTIDOS | E9: 8 | G9: ABIERTA AIR | H9: =H8+1 -> 7 | M9: CAFE | N9: 7 | P9: 18 | Q9: 7 | S9: CONFECCIONES PERFECT | T9: =T8+1 -> 7
D10: FALDAS | E10: 9 | G10: ACANALADA | H10: =H9+1 -> 8 | M10: CAQUI OSCURO | N10: 8 | P10: 20 | Q10: 8 | S10: CREACION DINS CENTROLANDIA | T10: =T9+1 -> 8
D11: CAMISAS | E11: 10 | G11: ACANALADO CORTO | H11: =H10+1 -> 9 | M11: DORADO | N11: 9 | P11: 22 | Q11: 9 | S11: CREACIONES DANNY - - CLEOTILDE | T11: =T10+1 -> 9
D12: CAMISETAS | E12: 11 | G12: ACANALADO LARGO | H12: =H11+1 -> 10 | M12: GRIS | N12: 10 | P12: 24 | Q12: 10 | S12: DANNSTYLES | T12: =T11+1 -> 10
D13: PERFUMES | E13: 12 | G13: ACOLCHADA | H13: =H12+1 -> 11 | M13: NARANJA | N13: 11 | P13: 26 | Q13: 11 | S13: DEPORTES | T13: =T12+1 -> 11
D14: MAQUILLAJE | E14: 13 | G14: ACOLCHADA LARGA | H14: =H13+1 -> 12 | M14: NEGRO | N14: 12 | P14: 28 | Q14: 12 | S14: DIVAS | T14: =T13+1 -> 12
D15: GORRAS | E15: 14 | G15: ADIDAS | H15: =H14+1 -> 13 | M15: PLATEADO | N15: 13 | P15: 30 | Q15: 13 | S15: DRAGMA | T15: =T14+1 -> 13
D16: MALETAS | E16: 15 | G16: AFELPADO | H16: =H15+1 -> 14 | M16: ROJO | N16: 14 | P16: 32 | Q16: 14 | S16: DRI-FIT | T16: =T15+1 -> 14
D17: LLAVEROS | E17: 16 | G17: ALEMANIA AAA LOCAL | H17: =H16+1 -> 15 | M17: ROSADO | N17: 15 | P17: 34 | Q17: 15 | S17: ECUATORIANOS | T17: =T16+1 -> 15
D18: BOLSOS | E18: 17 | G18: ALGODON | H18: =H17+1 -> 16 | M18: VARIOS | N18: 16 | P18: 36 | Q18: 16 | S18: FIT STYLE | T18: =T17+1 -> 16
D19: CARRIEL | E19: 18 | G19: ALGODON AJUSTADA | H19: =H18+1 -> 17 | M19: VARIOS | N19: 17 | P19: 16-S | Q19: 18 | S19: GOLDTEX | T19: =T18+1 -> 17
D20: PECHERAS | E20: 19 | G20: ALGODON CAPOTA ESTAMPADO | H20: =H19+1 -> 18 | M20: VERDE | N20: 18 | P20: 2XL | Q20: 19 | S20: GORRAS LOS ANGELES | T20: =T19+1 -> 18
D21: CANGUROS | E21: 20 | G21: ALGODON CON CAPOTA ESTAMPADO CREMALLERA | H21: =H20+1 -> 19 | M21: VERDE OSCURO | N21: 19 | P21: 3XL | Q21: 20 | S21: HHR ELIECER HERNANDEZ | T21: =T20+1 -> 19
D22: CAJAS REGALO | E22: 21 | G22: ALGODON CORTA E U | H22: =H21+1 -> 20 | M22: MIEL | N22: =N21+1 -> 20 | P22: 4XL | Q22: 21 | S22: IMPERIO DE LA MODA | T22: =T21+1 -> 20
D23: CORREAS | E23: 22 | G23: ALGODON CUELLO REDONDO ESTAMPADO | H23: =H22+1 -> 21 | P23: 6XL | Q23: 22 | S23: IMPORTADO | T23: =T22+1 -> 21
D24: BILLETERAS | E24: 23 | G24: ALGODON OLGADA | H24: =H23+1 -> 22 | P24: L | Q24: 23 | S24: KBU DENIM JACKETS | T24: =T23+1 -> 22
D25: MEDIAS | E25: 24 | G25: ALGODON SIN ESTAMPADO | H25: =H24+1 -> 23 | P25: L-XL | Q25: 24 | S25: KING 7 ECUATORIANOS | T25: =T24+1 -> 23
D26: CHAQUETAS | E26: 25 | G26: AMBAR | H26: =H25+1 -> 24 | P26: M | Q26: 25 | S26: LOS POLACOS (DEISY) | T26: =T25+1 -> 24
D27: BUSOS | E27: 26 | G27: ANILLO 1 | H27: =H26+1 -> 25 | P27: M-L | Q27: 26 | S27: LUZMAR | T27: =T26+1 -> 25
D28: CANILLERAS | E28: 27 | G28: ANILLO 2 | H28: =H27+1 -> 26 | P28: S | Q28: 27 | S28: MADRUGON | T28: =T27+1 -> 26
D29: ANILLOS | E29: 28 | G29: ANILLO 3 | H29: =H28+1 -> 27 | P29: S-M | Q29: 28 | S29: MARTINA BENDITA | T29: =T28+1 -> 27
D30: CABELLO-ACCESORIOS | E30: 29 | G30: ANILLO 4 | H30: =H29+1 -> 28 | P30: SM | Q30: 29 | S30: MAURICIO | T30: =T29+1 -> 28
D31: COLLAR | E31: 30 | G31: ANILLO 5 | H31: =H30+1 -> 29 | P31: UN | Q31: 30 | S31: MAURICIO-ADIDAS | T31: =T30+1 -> 29
D32: PULSERAS | E32: 31 | G32: ANILLO 6 | H32: =H31+1 -> 30 | P32: VA | Q32: 31 | S32: MAURICIO-ADIDAS | T32: =T31+1 -> 30
D33: TOPOS | E33: 32 | G33: ANILLO 7 | H33: =H32+1 -> 31 | P33: XL | Q33: 32 | S33: MAURICIO-COLUMBIA | T33: =T32+1 -> 31
D34: ARETES | E34: 33 | G34: APLICADOR SOMBRA | H34: =H33+1 -> 32 | P34: XL | Q34: 33 | S34: MAURICIO-NBA | T34: =T33+1 -> 32
D35: CANDONGAS | E35: 34 | G35: ARGENTINA AAA LOCAL | H35: =H34+1 -> 33 | P35: XXL | Q35: 34 | S35: MAURICIO-NIKE | T35: =T34+1 -> 33
D36: PANTALONETAS | E36: 35 | G36: ASIMETRICA 1 HOMBRO | H36: =H35+1 -> 34 | S36: MAURICIO-PUMA | T36: =T35+1 -> 34
D37: EAR CUFF | E37: 36 | G37: ATLETICO MADRID AAA LOCAL 2025 | H37: =H36+1 -> 35 | S37: MAURICIO-THE NORTH FACE | T37: =T36+1 -> 35
D38: ESQUELETO | E38: 37 | G38: ATLETICO NACIONAL 1.1 LOCAL 2025 | H38: =H37+1 -> 36 | S38: MODA FEMENINA | T38: =T37+1 -> 36
D39: BODY | E39: 38 | G39: ATLETICO NACIONAL AAA 2025 | H39: =H38+1 -> 37 | S39: NIKE | T39: =T38+1 -> 37
D40: SACO | E40: 39 | G40: ATLETICO NACIONAL AAA 2026 | H40: =H39+1 -> 38 | S40: NOVA W 78 | T40: =T39+1 -> 38
D41: CONJUNTO | E41: 40 | G41: BAGGI | H41: =H40+1 -> 39 | S41: PETRO AZUL | T41: =T40+1 -> 39
D42: SUDADERA | E42: 41 | G42: BAGGI CON BRILLANTES | H42: =H41+1 -> 40 | S42: PUMA | T42: =T41+1 -> 40
D43: DRILL | E43: 42 | G43: BALACA TELA | H43: =H42+1 -> 41 | S43: R TREIK | T43: =T42+1 -> 41
D44: - | E44: 0 | G44: BAMBA SATIN | H44: =H43+1 -> 42 | S44: R&D | T44: =T43+1 -> 42
D45: BICICLETERO | E45: 43 | G45: BARCELONA | H45: =H44+1 -> 43 | S45: RED-PLAY 21 | T45: =T44+1 -> 43
D46: LEGGINS | E46: 44 | G46: BARCELONA AAA VISITANTE 2025 | H46: =H45+1 -> 44 | S46: ROSE GARCIA | T46: =T45+1 -> 44
D47: CAMUFLADO | E47: =E46+1 -> 45 | G47: BASICA ALGODON | H47: =H46+1 -> 45 | S47: SAMBA | T47: =T46+1 -> 45
D48: SPLASH | E48: =E47+1 -> 46 | G48: BAUL | H48: =H47+1 -> 46 | S48: TEJIDOS GERAS | T48: =T47+1 -> 46
D49: BRILLO | E49: =E48+1 -> 47 | G49: BODY COSMO | H49: =H48+1 -> 47 | S49: TEJIDOS HERAS | T49: =T48+1 -> 47
D50: BOLSAS JOYERIA | E50: =E49+1 -> 48 | G50: BOMBA | H50: =H49+1 -> 48
D51: CAJAS JOYERIA | E51: =E50+1 -> 49 | G51: BORDADA VALANT | H51: =H50+1 -> 49
D52: CINTURON+BILLETERA | E52: =E51+1 -> 50 | G52: BOTONES | H52: =H51+1 -> 50
D53: STRAPLE | E53: =E52+1 -> 51 | G53: BRASIL AAA | H53: =H52+1 -> 51
D54: BATAS TEJIDO | E54: =E53+1 -> 52 | G54: BRILLANTE | H54: =H53+1 -> 52
D55: ENTERIZO DEPORTIVO | E55: =E54+1 -> 53 | G55: BRILLANTES FIGURAS | H55: =H54+1 -> 53
D56: CONJUNTO DEPORTIVO | E56: =E55+1 -> 54 | G56: BRILLO | H56: =H55+1 -> 54
D57: CROPTOP | E57: =E56+1 -> 55 | G57: BRONCE CAIMAN | H57: =H56+1 -> 55
D58: MOÑOS | E58: =E57+1 -> 56 | G58: BULLS | H58: =H57+1 -> 56
D59: ENCRESPADOR | E59: =E58+1 -> 57 | G59: CADENA DORADA | H59: =H58+1 -> 57
D60: PAQUETE CAUCHOS | E60: =E59+1 -> 58 | G60: CAIMAN BRILLO | H60: =H59+1 -> 58
D61: CAIMAN | E61: =E60+1 -> 59 | G61: CAJA GRIS | H61: =H60+1 -> 59
... D76: PINTUCARA | E76: =E75+1 -> 74 | G76: CINTURON ANCHO | H76: =H75+1 -> 74
G77: CLASICA DRILL | H77: =H76+1 -> 75
G78: CLASICA FINA | H78: =H77+1 -> 76
G79: CLASICAS | H79: =H78+1 -> 77
G80: CLASICO | H80: =H79+1 -> 78
G81: COLLAR 1 | H81: =H80+1 -> 79
G82: COLLAR 2 | H82: =H81+1 -> 80
G83: COLLAR 3 | H83: =H82+1 -> 81
G84: COLLAR 4 | H84: =H83+1 -> 82
G85: COLLAR 5 | H85: =H84+1 -> 83
G86: COLLAR 6 | H86: =H85+1 -> 84
G87: COLLAR 7 | H87: =H86+1 -> 85
G88: COLOMBIA | H88: =H87+1 -> 86
... G284: ZARCILLO 5 | H284: =H283+1 -> 282

Sheet Copia de COMPRAS
A1: =SUBTOTAL(9,A3:A1013) -> 1821 | E1: =SUBTOTAL(9,E3:E1013) -> 14061867 | F1: =SUBTOTAL(9,F3:F1013) -> 28042296 | G1: =SUBTOTAL(9,G3:G1013) -> 28127734 | T1: =MAX(T2:T1013) -> 10
A2: Stock Inicial | B2: NOMBRE COMPLETO | C2: CALIDAD | D2: ESTILO-DETALLE | E2: Costo Compra Unidad | F2: Costo Compra Total | G2: Precio Venta | H2: Margen Bruto | I2: Valor Total | J2: valor compra | K2: LINEA | L2: CATEGORIA | M2: GENERO | N2: ESTILO-DETALLE | O2: COLOR | P2: TALLA | Q2: PROVEEDOR-MARCA | R2: CODIGO DE BARRAS | S2: SKU | T2: LARGO | U2: NOMBRE COMPLETO
A3: 2 | B3: jean dama gris 4 botones | D3: 4 BOTONES | E3: 32000 | F3: =E3*A3 -> 64000 | G3: =(E3*100%)+E3 -> 64000 | K3: ROPA DAMA | L3: JEANS | M3: DAMA | N3: 4 BOTONES | O3: GRIS | P3: 10 | Q3: R TREIK | R3: =IFERROR(CONCATENATE("*",VLOOKUP(L3,PARAM!D:E,2,0),VLOOKUP(M3,PARAM!J:K,2,0),VLOOKUP(N3,PARAM!G:H,2,0),VLOOKUP(P3,PARAM!P:Q,2,0),"*"),"") -> *1143* | S3: =IFERROR(CONCATENATE(VLOOKUP(L3,PARAM!D:E,2,0),VLOOKUP(M3,PARAM!J:K,2,0),VLOOKUP(N3,PARAM!G:H,2,0),VLOOKUP(O3,PARAM!M:N,2,0),VLOOKUP(P3,PARAM!P:Q,2,0)),"") -> 114103 | T3: =LEN(R3) -> 6 | U3: =CONCATENATE(L3," ",M3," ",N3," ",O3,IF(P3="-","",CONCATENATE(" TALLA ",P3))) -> JEANS DAMA 4 BOTONES GRIS TALLA 10
A4: 1 | B4: jean dama gris 4 botones | D4: 4 BOTONES | E4: 32000 | F4: =E4*A4 -> 32000 | G4: =(E4*100%)+E4 -> 64000 | K4: ROPA DAMA | L4: JEANS | M4: DAMA | N4: 4 BOTONES | O4: GRIS | P4: 8 | Q4: R TREIK | R4: =IFERROR(CONCATENATE("*",VLOOKUP(L4,PARAM!D:E,2,0),VLOOKUP(M4,PARAM!J:K,2,0),VLOOKUP(N4,PARAM!G:H,2,0),VLOOKUP(P4,PARAM!P:Q,2,0),"*"),"") -> *1142* | S4: =IFERROR(CONCATENATE(VLOOKUP(L4,PARAM!D:E,2,0),VLOOKUP(M4,PARAM!J:K,2,0),VLOOKUP(N4,PARAM!G:H,2,0),VLOOKUP(O4,PARAM!M:N,2,0),VLOOKUP(P4,PARAM!P:Q,2,0)),"") -> 114102 | T4: =LEN(R4) -> 6 | U4: =CONCATENATE(L4," ",M4," ",N4," ",O4,IF(P4="-","",CONCATENATE(" TALLA ",P4))) -> JEANS DAMA 4 BOTONES GRIS TALLA 8
A5: 1 | B5: jean dama gris 4 botones | D5: sin bolsillo | E5: 32000 | F5: =E5*A5 -> 32000 | G5: =(E5*100%)+E5 -> 64000 | K5: ROPA DAMA | L5: JEANS | M5: DAMA | N5: 4 BOTONES SIN BOLSILLO | O5: GRIS | P5: 8 | Q5: R TREIK | R5: =IFERROR(CONCATENATE("*",VLOOKUP(L5,PARAM!D:E,2,0),VLOOKUP(M5,PARAM!J:K,2,0),VLOOKUP(N5,PARAM!G:H,2,0),VLOOKUP(P5,PARAM!P:Q,2,0),"*"),"") -> *1152* | S5: =IFERROR(CONCATENATE(VLOOKUP(L5,PARAM!D:E,2,0),VLOOKUP(M5,PARAM!J:K,2,0),VLOOKUP(N5,PARAM!G:H,2,0),VLOOKUP(O5,PARAM!M:N,2,0),VLOOKUP(P5,PARAM!P:Q,2,0)),"") -> 115102 | T5: =LEN(R5) -> 6 | U5: =CONCATENATE(L5," ",M5," ",N5," ",O5,IF(P5="-","",CONCATENATE(" TALLA ",P5))) -> JEANS DAMA 4 BOTONES SIN BOLSILLO GRIS TALLA 8
A6: 2 | B6: jean dama gris 4 botones | D6: 4 BOTONES | E6: 32000 | F6: =E6*A6 -> 64000 | G6: =(E6*100%)+E6 -> 64000 | K6: ROPA DAMA | L6: JEANS | M6: DAMA | N6: 4 BOTONES | O6: GRIS | P6: 16 | Q6: R TREIK | R6: =IFERROR(CONCATENATE("*",VLOOKUP(L6,PARAM!D:E,2,0),VLOOKUP(M6,PARAM!J:K,2,0),VLOOKUP(N6,PARAM!G:H,2,0),VLOOKUP(P6,PARAM!P:Q,2,0),"*"),"") -> *1146* | S6: =IFERROR(CONCATENATE(VLOOKUP(L6,PARAM!D:E,2,0),VLOOKUP(M6,PARAM!J:K,2,0),VLOOKUP(N6,PARAM!G:H,2,0),VLOOKUP(O6,PARAM!M:N,2,0),VLOOKUP(P6,PARAM!P:Q,2,0)),"") -> 114106 | T6: =LEN(R6) -> 6 | U6: =CONCATENATE(L6," ",M6," ",N6," ",O6,IF(P6="-","",CONCATENATE(" TALLA ",P6))) -> JEANS DAMA 4 BOTONES GRIS TALLA 16
A7: 1 | B7: jean dama gris 4 botones | D7: sin bolsillo | E7: 32000 | F7: =E7*A7 -> 32000 | G7: =(E7*100%)+E7 -> 64000 | K7: ROPA DAMA | L7: JEANS | M7: DAMA | N7: 4 BOTONES SIN BOLSILLO | O7: GRIS | P7: 16 | Q7: R TREIK | R7: =IFERROR(CONCATENATE("*",VLOOKUP(L7,PARAM!D:E,2,0),VLOOKUP(M7,PARAM!J:K,2,0),VLOOKUP(N7,PARAM!G:H,2,0),VLOOKUP(P7,PARAM!P:Q,2,0),"*"),"") -> *1156* | S7: =IFERROR(CONCATENATE(VLOOKUP(L7,PARAM!D:E,2,0),VLOOKUP(M7,PARAM!J:K,2,0),VLOOKUP(N7,PARAM!G:H,2,0),VLOOKUP(O7,PARAM!M:N,2,0),VLOOKUP(P7,PARAM!P:Q,2,0)),"") -> 115106 | T7: =LEN(R7) -> 6 | U7: =CONCATENATE(L7," ",M7," ",N7," ",O7,IF(P7="-","",CONCATENATE(" TALLA ",P7))) -> JEANS DAMA 4 BOTONES SIN BOLSILLO GRIS TALLA 16
A8: 1 | B8: jean dama gris 1 boton | D8: 1 BOTON | E8: 32000 | F8: =E8*A8 -> 32000 | G8: =(E8*100%)+E8 -> 64000 | K8: ROPA DAMA | L8: JEANS | M8: DAMA | N8: 1 BOTON | O8: GRIS | P8: 12 | Q8: R TREIK | R8: =IFERROR(CONCATENATE("*",VLOOKUP(L8,PARAM!D:E,2,0),VLOOKUP(M8,PARAM!J:K,2,0),VLOOKUP(N8,PARAM!G:H,2,0),VLOOKUP(P8,PARAM!P:Q,2,0),"*"),"") -> *1114* | S8: =IFERROR(CONCATENATE(VLOOKUP(L8,PARAM!D:E,2,0),VLOOKUP(M8,PARAM!J:K,2,0),VLOOKUP(N8,PARAM!G:H,2,0),VLOOKUP(O8,PARAM!M:N,2,0),VLOOKUP(P8,PARAM!P:Q,2,0)),"") -> 111104 | T8: =LEN(R8) -> 6 | U8: =CONCATENATE(L8," ",M8," ",N8," ",O8,IF(P8="-","",CONCATENATE(" TALLA ",P8))) -> JEANS DAMA 1 BOTON GRIS TALLA 12
A9: 1 | B9: jean dama gris 4 botones | D9: 4 BOTONES | E9: 32000 | F9: =E9*A9 -> 32000 | G9: =(E9*100%)+E9 -> 64000 | K9: ROPA DAMA | L9: JEANS | M9: DAMA | N9: 4 BOTONES | O9: GRIS | P9: 14 | Q9: R TREIK | R9: =IFERROR(CONCATENATE("*",VLOOKUP(L9,PARAM!D:E,2,0),VLOOKUP(M9,PARAM!J:K,2,0),VLOOKUP(N9,PARAM!G:H,2,0),VLOOKUP(P9,PARAM!P:Q,2,0),"*"),"") -> *1145* | S9: =IFERROR(CONCATENATE(VLOOKUP(L9,PARAM!D:E,2,0),VLOOKUP(M9,PARAM!J:K,2,0),VLOOKUP(N9,PARAM!G:H,2,0),VLOOKUP(O9,PARAM!M:N,2,0),VLOOKUP(P9,PARAM!P:Q,2,0)),"") -> 114105 | T9: =LEN(R9) -> 6 | U9: =CONCATENATE(L9," ",M9," ",N9," ",O9,IF(P9="-","",CONCATENATE(" TALLA ",P9))) -> JEANS DAMA 4 BOTONES GRIS TALLA 14
A10: 2 | B10: jean dama negro 1 boton | D10: bota recta | E10: 38000 | F10: =E10*A10 -> 76000 | G10: =(E10*100%)+E10 -> 76000 | K10: ROPA DAMA | L10: JEANS | M10: DAMA | N10: 1 BOTON BOTA RECTA | O10: NEGRO | P10: 14 | Q10: R TREIK | R10: =IFERROR(CONCATENATE("*",VLOOKUP(L10,PARAM!D:E,2,0),VLOOKUP(M10,PARAM!J:K,2,0),VLOOKUP(N10,PARAM!G:H,2,0),VLOOKUP(P10,PARAM!P:Q,2,0),"*"),"") -> *1125* | S10: =IFERROR(CONCATENATE(VLOOKUP(L10,PARAM!D:E,2,0),VLOOKUP(M10,PARAM!J:K,2,0),VLOOKUP(N10,PARAM!G:H,2,0),VLOOKUP(O10,PARAM!M:N,2,0),VLOOKUP(P10,PARAM!P:Q,2,0)),"") -> 112125 | T10: =LEN(R10) -> 6 | U10: =CONCATENATE(L10," ",M10," ",N10," ",O10,IF(P10="-","",CONCATENATE(" TALLA ",P10))) -> JEANS DAMA 1 BOTON BOTA RECTA NEGRO TALLA 14
A11: 1 | B11: jean dama negro 1 boton | D11: bota recta | E11: 38000 | F11: =E11*A11 -> 38000 | G11: =(E11*100%)+E11 -> 76000 | K11: ROPA DAMA | L11: JEANS | M11: DAMA | N11: 1 BOTON BOTA RECTA | O11: NEGRO | P11: 10 | Q11: R TREIK | R11: =IFERROR(CONCATENATE("*",VLOOKUP(L11,PARAM!D:E,2,0),VLOOKUP(M11,PARAM!J:K,2,0),VLOOKUP(N11,PARAM!G:H,2,0),VLOOKUP(P11,PARAM!P:Q,2,0),"*"),"") -> *1123* | S11: =IFERROR(CONCATENATE(VLOOKUP(L11,PARAM!D:E,2,0),VLOOKUP(M11,PARAM!J:K,2,0),VLOOKUP(N11,PARAM!G:H,2,0),VLOOKUP(O11,PARAM!M:N,2,0),VLOOKUP(P11,PARAM!P:Q,2,0)),"") -> 112123 | T11: =LEN(R11) -> 6 | U11: =CONCATENATE(L11," ",M11," ",N11," ",O11,IF(P11="-","",CONCATENATE(" TALLA ",P11))) -> JEANS DAMA 1 BOTON BOTA RECTA NEGRO TALLA 10
A12: 1 | B12: jean dama negro 1 boton | D12: bota recta | E12: 38000 | F12: =E12*A12 -> 38000 | G12: =(E12*100%)+E12 -> 76000 | K12: ROPA DAMA | L12: JEANS | M12: DAMA | N12: 1 BOTON BOTA RECTA | O12: NEGRO | P12: 8 | Q12: R TREIK | R12: =IFERROR(CONCATENATE("*",VLOOKUP(L12,PARAM!D:E,2,0),VLOOKUP(M12,PARAM!J:K,2,0),VLOOKUP(N12,PARAM!G:H,2,0),VLOOKUP(P12,PARAM!P:Q,2,0),"*"),"") -> *1122* | S12: =IFERROR(CONCATENATE(VLOOKUP(L12,PARAM!D:E,2,0),VLOOKUP(M12,PARAM!J:K,2,0),VLOOKUP(N12,PARAM!G:H,2,0),VLOOKUP(O12,PARAM!M:N,2,0),VLOOKUP(P12,PARAM!P:Q,2,0)),"") -> 112122 | T12: =LEN(R12) -> 6 | U12: =CONCATENATE(L12," ",M12," ",N12," ",O12,IF(P12="-","",CONCATENATE(" TALLA ",P12))) -> JEANS DAMA 1 BOTON BOTA RECTA NEGRO TALLA 8
A13: 2 | B13: jean dama negro 1 boton | D13: 1 BOTON | E13: 32000 | F13: =E13*A13 -> 64000 | G13: =(E13*100%)+E13 -> 64000 | K13: ROPA DAMA | L13: JEANS | M13: DAMA | N13: 1 BOTON BOTA RECTA | O13: NEGRO | P13: 14 | Q13: R TREIK | R13: =IFERROR(CONCATENATE("*",VLOOKUP(L13,PARAM!D:E,2,0),VLOOKUP(M13,PARAM!J:K,2,0),VLOOKUP(N13,PARAM!G:H,2,0),VLOOKUP(P13,PARAM!P:Q,2,0),"*"),"") -> *1125* | S13: =IFERROR(CONCATENATE(VLOOKUP(L13,PARAM!D:E,2,0),VLOOKUP(M13,PARAM!J:K,2,0),VLOOKUP(N13,PARAM!G:H,2,0),VLOOKUP(O13,PARAM!M:N,2,0),VLOOKUP(P13,PARAM!P:Q,2,0)),"") -> 112125 | T13: =LEN(R13) -> 6 | U13: =CONCATENATE(L13," ",M13," ",N13," ",O13,IF(P13="-","",CONCATENATE(" TALLA ",P13))) -> JEANS DAMA 1 BOTON BOTA RECTA NEGRO TALLA 14
A14: 1 | B14: jean dama negro 4 botones | D14: sin bolsillo | E14: 32000 | F14: =E14*A14 -> 32000 | G14: =(E14*100%)+E14 -> 64000 | K14: ROPA DAMA | L14: JEANS | M14: DAMA | N14: 4 BOTONES SIN BOLSILLO | O14: NEGRO | P14: 14 | Q14: R TREIK | R14: =IFERROR(CONCATENATE("*",VLOOKUP(L14,PARAM!D:E,2,0),VLOOKUP(M14,PARAM!J:K,2,0),VLOOKUP(N14,PARAM!G:H,2,0),VLOOKUP(P14,PARAM!P:Q,2,0),"*"),"") -> *1155* | S14: =IFERROR(CONCATENATE(VLOOKUP(L14,PARAM!D:E,2,0),VLOOKUP(M14,PARAM!J:K,2,0),VLOOKUP(N14,PARAM!G:H,2,0),VLOOKUP(O14,PARAM!M:N,2,0),VLOOKUP(P14,PARAM!P:Q,2,0)),"") -> 115125 | T14: =LEN(R14) -> 6 | U14: =CONCATENATE(L14," ",M14," ",N14," ",O14,IF(P14="-","",CONCATENATE(" TALLA ",P14))) -> JEANS DAMA 4 BOTONES SIN BOLSILLO NEGRO TALLA 14
... A20: 1 | B20: jean dama azul 4 botones | D20: sin bolsillo | E20: 32000 | F20: =E20*A20 -> 32000 | G20: =(E20*100%)+E20 -> 64000 | K20: ROPA DAMA | L20: JEANS | M20: DAMA | N20: 4 BOTONES SIN BOLSILLO | O20: AZUL | P20: 8 | Q20: R TREIK | R20: =IFERROR(CONCATENATE("*",VLOOKUP(L20,PARAM!D:E,2,0),VLOOKUP(M20,PARAM!J:K,2,0),VLOOKUP(N20,PARAM!G:H,2,0),VLOOKUP(P20,PARAM!P:Q,2,0),"*"),"") -> *1152* | S20: =IFERROR(CONCATENATE(VLOOKUP(L20,PARAM!D:E,2,0),VLOOKUP(M20,PARAM!J:K,2,0),VLOOKUP(N20,PARAM!G:H,2,0),VLOOKUP(O20,PARAM!M:N,2,0),VLOOKUP(P20,PARAM!P:Q,2,0)),"") -> 11522 | T20: =LEN(R20) -> 6 | U20: =CONCATENATE(L20," ",M20," ",N20," ",O20,IF(P20="-","",CONCATENATE(" TALLA ",P20))) -> JEANS DAMA 4 BOTONES SIN BOLSILLO AZUL TALLA 8
A21: 6 | B21: blusas basicas algodon dama | D21: ALGODON DAMA | E21: 7000 | F21: =E21*A21 -> 42000 | G21: =(E21*100%)+E21 -> 14000 | K21: ROPA DAMA | L21: BLUSAS | M21: DAMA | N21: BASICA ALGODON | O21: VARIOS | P21: VA | Q21: LUZMAR | R21: =IFERROR(CONCATENATE("*",VLOOKUP(L21,PARAM!D:E,2,0),VLOOKUP(M21,PARAM!J:K,2,0),VLOOKUP(N21,PARAM!G:H,2,0),VLOOKUP(P21,PARAM!P:Q,2,0),"*"),"") -> *614531* | S21: =IFERROR(CONCATENATE(VLOOKUP(L21,PARAM!D:E,2,0),VLOOKUP(M21,PARAM!J:K,2,0),VLOOKUP(N21,PARAM!G:H,2,0),VLOOKUP(O21,PARAM!M:N,2,0),VLOOKUP(P21,PARAM!P:Q,2,0)),"") -> 61451631 | T21: =LEN(R21) -> 8 | U21: =CONCATENATE(L21," ",M21," ",N21," ",O21,IF(P21="-","",CONCATENATE(" TALLA ",P21))) -> BLUSAS DAMA BASICA ALGODON VARIOS TALLA VA
A22: 3 | B22: bicicletero algodon | D22: bicicletero algodon talla M-L | E22: 8500 | F22: =E22*A22 -> 25500 | G22: =(E22*100%)+E22 -> 17000 | K22: LICRA DEPORTIVA | L22: BICICLETERO | M22: DAMA | N22: ALGODON | O22: VARIOS | P22: M-L | Q22: LUZMAR | R22: =IFERROR(CONCATENATE("*",VLOOKUP(L22,PARAM!D:E,2,0),VLOOKUP(M22,PARAM!J:K,2,0),VLOOKUP(N22,PARAM!G:H,2,0),VLOOKUP(P22,PARAM!P:Q,2,0),"*"),"") -> *4311626* | S22: =IFERROR(CONCATENATE(VLOOKUP(L22,PARAM!D:E,2,0),VLOOKUP(M22,PARAM!J:K,2,0),VLOOKUP(N22,PARAM!G:H,2,0),VLOOKUP(O22,PARAM!M:N,2,0),VLOOKUP(P22,PARAM!P:Q,2,0)),"") -> 431161626 | T22: =LEN(R22) -> 9 | U22: =CONCATENATE(L22," ",M22," ",N22," ",O22,IF(P22="-","",CONCATENATE(" TALLA ",P22))) -> BICICLETERO DAMA ALGODON VARIOS TALLA M-L
A23: 4 | B23: bicicletero algodon | D23: bicicletero algodon talla 16-S | E23: 7500 | F23: =E23*A23 -> 30000 | G23: =(E23*100%)+E23 -> 15000 | K23: LICRA DEPORTIVA | L23: BICICLETERO | M23: DAMA | N23: ALGODON | O23: VARIOS | P23: 16-S | Q23: LUZMAR | R23: =IFERROR(CONCATENATE("*",VLOOKUP(L23,PARAM!D:E,2,0),VLOOKUP(M23,PARAM!J:K,2,0),VLOOKUP(N23,PARAM!G:H,2,0),VLOOKUP(P23,PARAM!P:Q,2,0),"*"),"") -> *4311618* | S23: =IFERROR(CONCATENATE(VLOOKUP(L23,PARAM!D:E,2,0),VLOOKUP(M23,PARAM!J:K,2,0),VLOOKUP(N23,PARAM!G:H,2,0),VLOOKUP(O23,PARAM!M:N,2,0),VLOOKUP(P23,PARAM!P:Q,2,0)),"") -> 431161618 | T23: =LEN(R23) -> 9 | U23: =CONCATENATE(L23," ",M23," ",N23," ",O23,IF(P23="-","",CONCATENATE(" TALLA ",P23))) -> BICICLETERO DAMA ALGODON VARIOS TALLA 16-S
A24: 2 | B24: bicicletero algodon | D24: bicicletero algodon talla 14 | E24: 7000 | F24: =E24*A24 -> 14000 | G24: =(E24*100%)+E24 -> 14000 | K24: LICRA DEPORTIVA | L24: BICICLETERO | M24: DAMA | N24: ALGODON | O24: VARIOS | P24: 14 | Q24: LUZMAR | R24: =IFERROR(CONCATENATE("*",VLOOKUP(L24,PARAM!D:E,2,0),VLOOKUP(M24,PARAM!J:K,2,0),VLOOKUP(N24,PARAM!G:H,2,0),VLOOKUP(P24,PARAM!P:Q,2,0),"*"),"") -> *431165* | S24: =IFERROR(CONCATENATE(VLOOKUP(L24,PARAM!D:E,2,0),VLOOKUP(M24,PARAM!J:K,2,0),VLOOKUP(N24,PARAM!G:H,2,0),VLOOKUP(O24,PARAM!M:N,2,0),VLOOKUP(P24,PARAM!P:Q,2,0)),"") -> 43116165 | T24: =LEN(R24) -> 8 | U24: =CONCATENATE(L24," ",M24," ",N24," ",O24,IF(P24="-","",CONCATENATE(" TALLA ",P24))) -> BICICLETERO DAMA ALGODON VARIOS TALLA 14
A25: 15 | B25: legins algodon | D25: legins algodon | E25: 17000 | F25: =E25*A25 -> 255000 | G25: =(E25*100%)+E25 -> 34000 | K25: LICRA DEPORTIVA | L25: LEGGINS | M25: DAMA | N25: ALGODON | O25: VARIOS | P25: XL | Q25: LUZMAR | R25: =IFERROR(CONCATENATE("*",VLOOKUP(L25,PARAM!D:E,2,0),VLOOKUP(M25,PARAM!J:K,2,0),VLOOKUP(N25,PARAM!G:H,2,0),VLOOKUP(P25,PARAM!P:Q,2,0),"*"),"") -> *4411632* | S25: =IFERROR(CONCATENATE(VLOOKUP(L25,PARAM!D:E,2,0),VLOOKUP(M25,PARAM!J:K,2,0),VLOOKUP(N25,PARAM!G:H,2,0),VLOOKUP(O25,PARAM!M:N,2,0),VLOOKUP(P25,PARAM!P:Q,2,0)),"") -> 441161632 | T25: =LEN(R25) -> 9 | U25: =CONCATENATE(L25," ",M25," ",N25," ",O25,IF(P25="-","",CONCATENATE(" TALLA ",P25))) -> LEGGINS DAMA ALGODON VARIOS TALLA XL
A26: 1 | B26: bermuda camuflada caballero | D26: bermuda camuflada | E26: 38000 | F26: =E26*A26 -> 38000 | G26: =(E26*100%)+E26 -> 76000 | K26: ROPA CABALLERO | L26: BERMUDAS | M26: CABALLERO | N26: CAMUFLADO | O26: BEIGE | P26: 36 | Q26: GOLDTEX | R26: =IFERROR(CONCATENATE("*",VLOOKUP(L26,PARAM!D:E,2,0),VLOOKUP(M26,PARAM!J:K,2,0),VLOOKUP(N26,PARAM!G:H,2,0),VLOOKUP(P26,PARAM!P:Q,2,0),"*"),"") -> *526616* | S26: =IFERROR(CONCATENATE(VLOOKUP(L26,PARAM!D:E,2,0),VLOOKUP(M26,PARAM!J:K,2,0),VLOOKUP(N26,PARAM!G:H,2,0),VLOOKUP(O26,PARAM!M:N,2,0),VLOOKUP(P26,PARAM!P:Q,2,0)),"") -> 5266516 | T26: =LEN(R26) -> 8 | U26: =CONCATENATE(L26," ",M26," ",N26," ",O26,IF(P26="-","",CONCATENATE(" TALLA ",P26))) -> BERMUDAS CABALLERO CAMUFLADO BEIGE TALLA 36
A27: 1 | B27: bermuda camuflada caballero | D27: camuflada bermuda | E27: 38000 | F27: =E27*A27 -> 38000 | G27: =(E27*100%)+E27 -> 76000 | K27: ROPA CABALLERO | L27: BERMUDAS | M27: CABALLERO | N27: CAMUFLADO | O27: CAQUI OSCURO | P27: 28 | Q27: GOLDTEX | R27: =IFERROR(CONCATENATE("*",VLOOKUP(L27,PARAM!D:E,2,0),VLOOKUP(M27,PARAM!J:K,2,0),VLOOKUP(N27,PARAM!G:H,2,0),VLOOKUP(P27,PARAM!P:Q,2,0),"*"),"") -> *526612* | S27: =IFERROR(CONCATENATE(VLOOKUP(L27,PARAM!D:E,2,0),VLOOKUP(M27,PARAM!J:K,2,0),VLOOKUP(N27,PARAM!G:H,2,0),VLOOKUP(O27,PARAM!M:N,2,0),VLOOKUP(P27,PARAM!P:Q,2,0)),"") -> 5266812 | T27: =LEN(R27) -> 8 | U27: =CONCATENATE(L27," ",M27," ",N27," ",O27,IF(P27="-","",CONCATENATE(" TALLA ",P27))) -> BERMUDAS CABALLERO CAMUFLADO CAQUI OSCURO TALLA 28
A28: 1 | B28: bermuda camuflada caballero | D28: bermuda camuflada | E28: 38000 | F28: =E28*A28 -> 38000 | G28: =(E28*100%)+E28 -> 76000 | K28: ROPA CABALLERO | L28: BERMUDAS | M28: CABALLERO | N28: CAMUFLADO | O28: AZUL NOCHE | P28: 30 | Q28: GOLDTEX | R28: =IFERROR(CONCATENATE("*",VLOOKUP(L28,PARAM!D:E,2,0),VLOOKUP(M28,PARAM!J:K,2,0),VLOOKUP(N28,PARAM!G:H,2,0),VLOOKUP(P28,PARAM!P:Q,2,0),"*"),"") -> *526613* | S28: =IFERROR(CONCATENATE(VLOOKUP(L28,PARAM!D:E,2,0),VLOOKUP(M28,PARAM!J:K,2,0),VLOOKUP(N28,PARAM!G:H,2,0),VLOOKUP(O28,PARAM!M:N,2,0),VLOOKUP(P28,PARAM!P:Q,2,0)),"") -> 5266413 | T28: =LEN(R28) -> 8 | U28: =CONCATENATE(L28," ",M28," ",N28," ",O28,IF(P28="-","",CONCATENATE(" TALLA ",P28))) -> BERMUDAS CABALLERO CAMUFLADO AZUL NOCHE TALLA 30
A29: 1 | B29: bermuda camuflada caballero | D29: bermuda camuflada | E29: 38000 | F29: =E29*A29 -> 38000 | G29: =(E29*100%)+E29 -> 76000 | K29: ROPA CABALLERO | L29: BERMUDAS | M29: CABALLERO | N29: CAMUFLADO | O29: VERDE | P29: 32 | Q29: GOLDTEX | R29: =IFERROR(CONCATENATE("*",VLOOKUP(L29,PARAM!D:E,2,0),VLOOKUP(M29,PARAM!J:K,2,0),VLOOKUP(N29,PARAM!G:H,2,0),VLOOKUP(P29,PARAM!P:Q,2,0),"*"),"") -> *526614* | S29: =IFERROR(CONCATENATE(VLOOKUP(L29,PARAM!D:E,2,0),VLOOKUP(M29,PARAM!J:K,2,0),VLOOKUP(N29,PARAM!G:H,2,0),VLOOKUP(O29,PARAM!M:N,2,0),VLOOKUP(P29,PARAM!P:Q,2,0)),"") -> 52661814 | T29: =LEN(R29) -> 8 | U29: =CONCATENATE(L29," ",M29," ",N29," ",O29,IF(P29="-","",CONCATENATE(" TALLA ",P29))) -> BERMUDAS CABALLERO CAMUFLADO VERDE TALLA 32
A30: 1 | B30: bermuda camuflada caballero | D30: bermuda camuflada | E30: 38000 | F30: =E30*A30 -> 38000 | G30: =(E30*100%)+E30 -> 76000 | K30: ROPA CABALLERO | L30: BERMUDAS | M30: CABALLERO | N30: CAMUFLADO | O30: NEGRO | P30: 34 | Q30: GOLDTEX | R30: =IFERROR(CONCATENATE("*",VLOOKUP(L30,PARAM!D:E,2,0),VLOOKUP(M30,PARAM!J:K,2,0),VLOOKUP(N30,PARAM!G:H,2,0),VLOOKUP(P30,PARAM!P:Q,2,0),"*"),"") -> *526615* | S30: =IFERROR(CONCATENATE(VLOOKUP(L30,PARAM!D:E,2,0),VLOOKUP(M30,PARAM!J:K,2,0),VLOOKUP(N30,PARAM!G:H,2,0),VLOOKUP(O30,PARAM!M:N,2,0),VLOOKUP(P30,PARAM!P:Q,2,0)),"") -> 52661215 | T30: =LEN(R30) -> 8 | U30: =CONCATENATE(L30," ",M30," ",N30," ",O30,IF(P30="-","",CONCATENATE(" TALLA ",P30))) -> BERMUDAS CABALLERO CAMUFLADO NEGRO TALLA 34
A31: 1 | B31: bermuda clasica caballero | D31: bermuda drill | E31: 36000 | F31: =E31*A31 -> 36000 | G31: =(E31*100%)+E31 -> 72000 | K31: ROPA CABALLERO | L31: BERMUDAS | M31: CABALLERO | N31: CLASICA DRILL | O31: NEGRO | P31: 34 | Q31: GOLDTEX | R31: =IFERROR(CONCATENATE("*",VLOOKUP(L31,PARAM!D:E,2,0),VLOOKUP(M31,PARAM!J:K,2,0),VLOOKUP(N31,PARAM!G:H,2,0),VLOOKUP(P31,PARAM!P:Q,2,0),"*"),"") -> *527515* | S31: =IFERROR(CONCATENATE(VLOOKUP(L31,PARAM!D:E,2,0),VLOOKUP(M31,PARAM!J:K,2,0),VLOOKUP(N31,PARAM!G:H,2,0),VLOOKUP(O31,PARAM!M:N,2,0),VLOOKUP(P31,PARAM!P:Q,2,0)),"") -> 52751215 | T31: =LEN(R31) -> 8 | U31: =CONCATENATE(L31," ",M31," ",N31," ",O31,IF(P31="-","",CONCATENATE(" TALLA ",P31))) -> BERMUDAS CABALLERO CLASICA DRILL NEGRO TALLA 34
A32: 1 | B32: bermuda clasica caballero | D32: bermuda clasica | E32: 36000 | F32: =E32*A32 -> 36000 | G32: =(E32*100%)+E32 -> 72000 | K32: ROPA CABALLERO | L32: BERMUDAS | M32: CABALLERO | N32: CLASICA DRILL | O32: CAQUI OSCURO | P32: 28 | Q32: GOLDTEX | R32: =IFERROR(CONCATENATE("*",VLOOKUP(L32,PARAM!D:E,2,0),VLOOKUP(M32,PARAM!J:K,2,0),VLOOKUP(N32,PARAM!G:H,2,0),VLOOKUP(P32,PARAM!P:Q,2,0),"*"),"") -> *527512* | S32: =IFERROR(CONCATENATE(VLOOKUP(L32,PARAM!D:E,2,0),VLOOKUP(M32,PARAM!J:K,2,0),VLOOKUP(N32,PARAM!G:H,2,0),VLOOKUP(O32,PARAM!M:N,2,0),VLOOKUP(P32,PARAM!P:Q,2,0)),"") -> 5275812 | T32: =LEN(R32) -> 8 | U32: =CONCATENATE(L32," ",M32," ",N32," ",O32,IF(P32="-","",CONCATENATE(" TALLA ",P32))) -> BERMUDAS CABALLERO CLASICA DRILL CAQUI OSCURO TALLA 28
A33: 1 | B33: bermuda clasica caballero | D33: bermuda clasica | E33: 36000 | F33: =E33*A33 -> 36000 | G33: =(E33*100%)+E33 -> 72000 | K33: ROPA CABALLERO | L33: BERMUDAS | M33: CABALLERO | N33: CLASICA DRILL | O33: AZUL CLARO | P33: 32 | Q33: GOLDTEX | R33: =IFERROR(CONCATENATE("*",VLOOKUP(L33,PARAM!D:E,2,0),VLOOKUP(M33,PARAM!J:K,2,0),VLOOKUP(N33,PARAM!G:H,2,0),VLOOKUP(P33,PARAM!P:Q,2,0),"*"),"") -> *527514* | S33: =IFERROR(CONCATENATE(VLOOKUP(L33,PARAM!D:E,2,0),VLOOKUP(M33,PARAM!J:K,2,0),VLOOKUP(N33,PARAM!G:H,2,0),VLOOKUP(O33,PARAM!M:N,2,0),VLOOKUP(P33,PARAM!P:Q,2,0)),"") -> 5275314 | T33: =LEN(R33) -> 8 | U33: =CONCATENATE(L33," ",M33," ",N33," ",O33,IF(P33="-","",CONCATENATE(" TALLA ",P33))) -> BERMUDAS CABALLERO CLASICA DRILL AZUL CLARO TALLA 32
A34: 1 | B34: bermuda clasica caballero | D34: bermuda clasica | E34: 36000 | F34: =E34*A34 -> 36000 | G34: =(E34*100%)+E34 -> 72000 | K34: ROPA CABALLERO | L34: BERMUDAS | M34: CABALLERO | N34: CLASICA DRILL | O34: VERDE OSCURO | P34: 30 | Q34: GOLDTEX | R34: =IFERROR(CONCATENATE("*",VLOOKUP(L34,PARAM!D:E,2,0),VLOOKUP(M34,PARAM!J:K,2,0),VLOOKUP(N34,PARAM!G:H,2,0),VLOOKUP(P34,PARAM!P:Q,2,0),"*"),"") -> *527513* | S34: =IFERROR(CONCATENATE(VLOOKUP(L34,PARAM!D:E,2,0),VLOOKUP(M34,PARAM!J:K,2,0),VLOOKUP(N34,PARAM!G:H,2,0),VLOOKUP(O34,PARAM!M:N,2,0),VLOOKUP(P34,PARAM!P:Q,2,0)),"") -> 52751913 | T34: =LEN(R34) -> 8 | U34: =CONCATENATE(L34," ",M34," ",N34," ",O34,IF(P34="-","",CONCATENATE(" TALLA ",P34))) -> BERMUDAS CABALLERO CLASICA DRILL VERDE OSCURO TALLA 30
A35: 3 | B35: short con aro | D35: short aro | E35: 26000 | F35: =E35*A35 -> 78000 | G35: =(E35*100%)+E35 -> 52000 | K35: ROPA DAMA | L35: SHORTS | M35: DAMA | N35: SHORT ARO | O35: VARIOS | P35: VA | Q35: GOLDTEX | R35: =IFERROR(CONCATENATE("*",VLOOKUP(L35,PARAM!D:E,2,0),VLOOKUP(M35,PARAM!J:K,2,0),VLOOKUP(N35,PARAM!G:H,2,0),VLOOKUP(P35,PARAM!P:Q,2,0),"*"),"") -> *4125131* | S35: =IFERROR(CONCATENATE(VLOOKUP(L35,PARAM!D:E,2,0),VLOOKUP(M35,PARAM!J:K,2,0),VLOOKUP(N35,PARAM!G:H,2,0),VLOOKUP(O35,PARAM!M:N,2,0),VLOOKUP(P35,PARAM!P:Q,2,0)),"") -> 412511631 | T35: =LEN(R35) -> 9 | U35: =CONCATENATE(L35," ",M35," ",N35," ",O35,IF(P35="-","",CONCATENATE(" TALLA ",P35))) -> SHORTS DAMA SHORT ARO VARIOS TALLA VA
A36: 3 | B36: short cinturon ancho | D36: cinturon ancho | E36: 26000 | F36: =E36*A36 -> 78000 | G36: =(E36*100%)+E36 -> 52000 | K36: ROPA DAMA | L36: SHORTS | M36: DAMA | N36: CINTURON ANCHO | O36: VARIOS | P36: VA | Q36: GOLDTEX | R36: =IFERROR(CONCATENATE("*",VLOOKUP(L36,PARAM!D:E,2,0),VLOOKUP(M36,PARAM!J:K,2,0),VLOOKUP(N36,PARAM!G:H,2,0),VLOOKUP(P36,PARAM!P:Q,2,0),"*"),"") -> *417431* | S36: =IFERROR(CONCATENATE(VLOOKUP(L36,PARAM!D:E,2,0),VLOOKUP(M36,PARAM!J:K,2,0),VLOOKUP(N36,PARAM!G:H,2,0),VLOOKUP(O36,PARAM!M:N,2,0),VLOOKUP(P36,PARAM!P:Q,2,0)),"") -> 41741631 | T36: =LEN(R36) -> 8 | U36: =CONCATENATE(L36," ",M36," ",N36," ",O36,IF(P36="-","",CONCATENATE(" TALLA ",P36))) -> SHORTS DAMA CINTURON ANCHO VARIOS TALLA VA
A37: 9 | B37: bermuda short dama | D37: bermuda short | E37: 26000 | F37: =E37*A37 -> 234000 | G37: =(E37*100%)+E37 -> 52000 | K37: ROPA DAMA | L37: BERMUDAS | M37: DAMA | N37: DRILL | O37: VARIOS | P37: VA | Q37: GOLDTEX | R37: =IFERROR(CONCATENATE("*",VLOOKUP(L37,PARAM!D:E,2,0),VLOOKUP(M37,PARAM!J:K,2,0),VLOOKUP(N37,PARAM!G:H,2,0),VLOOKUP(P37,PARAM!P:Q,2,0),"*"),"") -> *5112131* | S37: =IFERROR(CONCATENATE(VLOOKUP(L37,PARAM!D:E,2,0),VLOOKUP(M37,PARAM!J:K,2,0),VLOOKUP(N37,PARAM!G:H,2,0),VLOOKUP(O37,PARAM!M:N,2,0),VLOOKUP(P37,PARAM!P:Q,2,0)),"") -> 511211631 | T37: =LEN(R37) -> 9 | U37: =CONCATENATE(L37," ",M37," ",N37," ",O37,IF(P37="-","",CONCATENATE(" TALLA ",P37))) -> BERMUDAS DAMA DRILL VARIOS TALLA VA
A38: 9 | B38: splash pink mini | D38: PINK MINI | E38: 5000 | F38: =E38*A38 -> 45000 | G38: =(E38*100%)+E38 -> 10000 | K38: PERFUMERIA | L38: PERFUMES | M38: DAMA | N38: PINK MINI | O38: VARIOS | P38: - | R38: =IFERROR(CONCATENATE("*",VLOOKUP(L38,PARAM!D:E,2,0),VLOOKUP(M38,PARAM!J:K,2,0),VLOOKUP(N38,PARAM!G:H,2,0),VLOOKUP(P38,PARAM!P:Q,2,0),"*"),"") -> *1212110* | S38: =IFERROR(CONCATENATE(VLOOKUP(L38,PARAM!D:E,2,0),VLOOKUP(M38,PARAM!J:K,2,0),VLOOKUP(N38,PARAM!G:H,2,0),VLOOKUP(O38,PARAM!M:N,2,0),VLOOKUP(P38,PARAM!P:Q,2,0)),"") -> 121211160 | T38: =LEN(R38) -> 9 | U38: =CONCATENATE(L38," ",M38," ",N38," ",O38,IF(P38="-","",CONCATENATE(" TALLA ",P38))) -> PERFUMES DAMA PINK MINI VARIOS
A39: 6 | B39: brillo labial dama | D39: brillo labial | E39: 2500 | F39: =E39*A39 -> 15000 | G39: =(E39*100%)+E39 -> 5000 | K39: MAQUILLAJE | L39: BRILLO | M39: DAMA | N39: LABIAL | O39: VARIOS | P39: - | R39: =IFERROR(CONCATENATE("*",VLOOKUP(L39,PARAM!D:E,2,0),VLOOKUP(M39,PARAM!J:K,2,0),VLOOKUP(N39,PARAM!G:H,2,0),VLOOKUP(P39,PARAM!P:Q,2,0),"*"),"") -> *4711600* | S39: =IFERROR(CONCATENATE(VLOOKUP(L39,PARAM!D:E,2,0),VLOOKUP(M39,PARAM!J:K,2,0),VLOOKUP(N39,PARAM!G:H,2,0),VLOOKUP(O39,PARAM!M:N,2,0),VLOOKUP(P39,PARAM!P:Q,2,0)),"") -> 471160160 | T39: =LEN(R39) -> 9 | U39: =CONCATENATE(L39," ",M39," ",N39," ",O39,IF(P39="-","",CONCATENATE(" TALLA ",P39))) -> BRILLO DAMA LABIAL VARIOS
A40: 2 | B40: splash dama | D40: splash dama | E40: 8500 | F40: =E40*A40 -> 17000 | G40: =(E40*100%)+E40 -> 17000 | K40: PERFUMERIA | L40: SPLASH | M40: DAMA | N40: - | O40: VARIOS | P40: - | R40: =IFERROR(CONCATENATE("*",VLOOKUP(L40,PARAM!D:E,2,0),VLOOKUP(M40,PARAM!J:K,2,0),VLOOKUP(N40,PARAM!G:H,2,0),VLOOKUP(P40,PARAM!P:Q,2,0),"*"),"") -> *46100* | S40: =IFERROR(CONCATENATE(VLOOKUP(L40,PARAM!D:E,2,0),VLOOKUP(M40,PARAM!J:K,2,0),VLOOKUP(N40,PARAM!G:H,2,0),VLOOKUP(O40,PARAM!M:N,2,0),VLOOKUP(P40,PARAM!P:Q,2,0)),"") -> 4610160 | T40: =LEN(R40) -> 7 | U40: =CONCATENATE(L40," ",M40," ",N40," ",O40,IF(P40="-","",CONCATENATE(" TALLA ",P40))) -> SPLASH DAMA - VARIOS
A41: 2 | B41: splash caballero | D41: splash caballero | E41: 6500 | F41: =E41*A41 -> 13000 | G41: =(E41*100%)+E41 -> 13000 | K41: PERFUMERIA | L41: SPLASH | M41: CABALLERO | N41: - | O41: VARIOS | P41: - | R41: =IFERROR(CONCATENATE("*",VLOOKUP(L41,PARAM!D:E,2,0),VLOOKUP(M41,PARAM!J:K,2,0),VLOOKUP(N41,PARAM!G:H,2,0),VLOOKUP(P41,PARAM!P:Q,2,0),"*"),"") -> *46200* | S41: =IFERROR(CONCATENATE(VLOOKUP(L41,PARAM!D:E,2,0),VLOOKUP(M41,PARAM!J:K,2,0),VLOOKUP(N41,PARAM!G:H,2,0),VLOOKUP(O41,PARAM!M:N,2,0),VLOOKUP(P41,PARAM!P:Q,2,0)),"") -> 4620160 | T41: =LEN(R41) -> 7 | U41: =CONCATENATE(L41," ",M41," ",N41," ",O41,IF(P41="-","",CONCATENATE(" TALLA ",P41))) -> SPLASH CABALLERO - VARIOS
A42: 6 | B42: gorras de colombia | D42: gorras colombia | E42: 28000 | F42: =E42*A42 -> 168000 | G42: =(E42*100%)+E42 -> 56000 | K42: ACCESORIOS | L42: GORRAS | M42: UNISEX | N42: COLOMBIA | O42: VARIOS | P42: UN | Q42: GORRAS LOS ANGELES | R42: =IFERROR(CONCATENATE("*",VLOOKUP(L42,PARAM!D:E,2,0),VLOOKUP(M42,PARAM!J:K,2,0),VLOOKUP(N42,PARAM!G:H,2,0),VLOOKUP(P42,PARAM!P:Q,2,0),"*"),"") -> *1438630* | S42: =IFERROR(CONCATENATE(VLOOKUP(L42,PARAM!D:E,2,0),VLOOKUP(M42,PARAM!J:K,2,0),VLOOKUP(N42,PARAM!G:H,2,0),VLOOKUP(O42,PARAM!M:N,2,0),VLOOKUP(P42,PARAM!P:Q,2,0)),"") -> 143861630 | T42: =LEN(R42) -> 9 | U42: =CONCATENATE(L42," ",M42," ",N42," ",O42,IF(P42="-","",CONCATENATE(" TALLA ",P42))) -> GORRAS UNISEX COLOMBIA VARIOS TALLA UN
A43: 17 | B43: gorras varios | D43: gorras varios | E43: 16000 | F43: =E43*A43 -> 272000 | G43: =(E43*100%)+E43 -> 32000 | K43: ACCESORIOS | L43: GORRAS | M43: UNISEX | N43: VARIOS | O43: VARIOS | P43: UN | Q43: GORRAS LOS ANGELES | R43: =IFERROR(CONCATENATE("*",VLOOKUP(L43,PARAM!D:E,2,0),VLOOKUP(M43,PARAM!J:K,2,0),VLOOKUP(N43,PARAM!G:H,2,0),VLOOKUP(P43,PARAM!P:Q,2,0),"*"),"") -> *14327530* | S43: =IFERROR(CONCATENATE(VLOOKUP(L43,PARAM!D:E,2,0),VLOOKUP(M43,PARAM!J:K,2,0),VLOOKUP(N43,PARAM!G:H,2,0),VLOOKUP(O43,PARAM!M:N,2,0),VLOOKUP(P43,PARAM!P:Q,2,0)),"") -> 1432751630 | T43: =LEN(R43) -> 10 | U43: =CONCATENATE(L43," ",M43," ",N43," ",O43,IF(P43="-","",CONCATENATE(" TALLA ",P43))) -> GORRAS UNISEX VARIOS VARIOS TALLA UN
A44: 1 | B44: maleta spray ground | D44: spray ground | E44: 60000 | F44: =E44*A44 -> 60000 | G44: =(E44*100%)+E44 -> 120000 | K44: ACCESORIOS | L44: MALETAS | M44: UNISEX | N44: SPRAY GROUND | O44: VARIOS | P44: - | Q44: BALU BAGS | R44: =IFERROR(CONCATENATE("*",VLOOKUP(L44,PARAM!D:E,2,0),VLOOKUP(M44,PARAM!J:K,2,0),VLOOKUP(N44,PARAM!G:H,2,0),VLOOKUP(P44,PARAM!P:Q,2,0),"*"),"") -> *1532540* | S44: =IFERROR(CONCATENATE(VLOOKUP(L44,PARAM!D:E,2,0),VLOOKUP(M44,PARAM!J:K,2,0),VLOOKUP(N44,PARAM!G:H,2,0),VLOOKUP(O44,PARAM!M:N,2,0),VLOOKUP(P44,PARAM!P:Q,2,0)),"") -> 153254160 | T44: =LEN(R44) -> 9 | U44: =CONCATENATE(L44," ",M44," ",N44," ",O44,IF(P44="-","",CONCATENATE(" TALLA ",P44))) -> MALETAS UNISEX SPRAY GROUND VARIOS
A45: 6 | B45: llaveros bomba | D45: llaveros bomba | E45: 6000 | F45: =E45*A45 -> 36000 | G45: =(E45*100%)+E45 -> 12000 | K45: ACCESORIOS | L45: LLAVEROS | M45: DAMA | N45: BOMBA | O45: VARIOS | P45: - | Q45: BALU BAGS | R45: =IFERROR(CONCATENATE("*",VLOOKUP(L45,PARAM!D:E,2,0),VLOOKUP(M45,PARAM!J:K,2,0),VLOOKUP(N45,PARAM!G:H,2,0),VLOOKUP(P45,PARAM!P:Q,2,0),"*"),"") -> *161480* | S45: =IFERROR(CONCATENATE(VLOOKUP(L45,PARAM!D:E,2,0),VLOOKUP(M45,PARAM!J:K,2,0),VLOOKUP(N45,PARAM!G:H,2,0),VLOOKUP(O45,PARAM!M:N,2,0),VLOOKUP(P45,PARAM!P:Q,2,0)),"") -> 16148160 | T45: =LEN(R45) -> 8 | U45: =CONCATENATE(L45," ",M45," ",N45," ",O45,IF(P45="-","",CONCATENATE(" TALLA ",P45))) -> LLAVEROS DAMA BOMBA VARIOS
A46: 2 | B46: llaveros cerezas brillante | D46: cerezas brillante | E46: 17000 | F46: =E46*A46 -> 34000 | G46: =(E46*100%)+E46 -> 34000 | K46: ACCESORIOS | L46: LLAVEROS | M46: DAMA | N46: CEREZAS BRILLANTE | O46: VARIOS | P46: - | Q46: BALU BAGS | R46: =IFERROR(CONCATENATE("*",VLOOKUP(L46,PARAM!D:E,2,0),VLOOKUP(M46,PARAM!J:K,2,0),VLOOKUP(N46,PARAM!G:H,2,0),VLOOKUP(P46,PARAM!P:Q,2,0),"*"),"") -> *161720* | S46: =IFERROR(CONCATENATE(VLOOKUP(L46,PARAM!D:E,2,0),VLOOKUP(M46,PARAM!J:K,2,0),VLOOKUP(N46,PARAM!G:H,2,0),VLOOKUP(O46,PARAM!M:N,2,0),VLOOKUP(P46,PARAM!P:Q,2,0)),"") -> 16172160 | T46: =LEN(R46) -> 8 | U46: =CONCATENATE(L46," ",M46," ",N46," ",O46,IF(P46="-","",CONCATENATE(" TALLA ",P46))) -> LLAVEROS DAMA CEREZAS BRILLANTE VARIOS
A47: 1 | B47: baul negro | D47: baul negro | E47: 45000 | F47: =E47*A47 -> 45000 | G47: =(E47*100%)+E47 -> 90000 | K47: ACCESORIOS | L47: BOLSOS | M47: DAMA | N47: BAUL | O47: NEGRO | P47: - | Q47: BALU BAGS | R47: =IFERROR(CONCATENATE("*",VLOOKUP(L47,PARAM!D:E,2,0),VLOOKUP(M47,PARAM!J:K,2,0),VLOOKUP(N47,PARAM!G:H,2,0),VLOOKUP(P47,PARAM!P:Q,2,0),"*"),"") -> *171460* | S47: =IFERROR(CONCATENATE(VLOOKUP(L47,PARAM!D:E,2,0),VLOOKUP(M47,PARAM!J:K,2,0),VLOOKUP(N47,PARAM!G:H,2,0),VLOOKUP(O47,PARAM!M:N,2,0),VLOOKUP(P47,PARAM!P:Q,2,0)),"") -> 17146120 | T47: =LEN(R47) -> 8 | U47: =CONCATENATE(L47," ",M47," ",N47," ",O47,IF(P47="-","",CONCATENATE(" TALLA ",P47))) -> BOLSOS DAMA BAUL NEGRO
A48: 6 | B48: correas dama | D48: correas dama | E48: 9000 | F48: =E48*A48 -> 54000 | G48: =(E48*100%)+E48 -> 18000 | K48: ACCESORIOS | L48: CORREAS | M48: DAMA | N48: - | O48: VARIOS | P48: UN | Q48: BALU BAGS | R48: =IFERROR(CONCATENATE("*",VLOOKUP(L48,PARAM!D:E,2,0),VLOOKUP(M48,PARAM!J:K,2,0),VLOOKUP(N48,PARAM!G:H,2,0),VLOOKUP(P48,PARAM!P:Q,2,0),"*"),"") -> *221030* | S48: =IFERROR(CONCATENATE(VLOOKUP(L48,PARAM!D:E,2,0),VLOOKUP(M48,PARAM!J:K,2,0),VLOOKUP(N48,PARAM!G:H,2,0),VLOOKUP(O48,PARAM!M:N,2,0),VLOOKUP(P48,PARAM!P:Q,2,0)),"") -> 22101630 | T48: =LEN(R48) -> 8 | U48: =CONCATENATE(L48," ",M48," ",N48," ",O48,IF(P48="-","",CONCATENATE(" TALLA ",P48))) -> CORREAS DAMA - VARIOS TALLA UN
A49: 1 | B49: bolso cadena dorada | D49: cadena dorada | E49: 30000 | F49: =E49*A49 -> 30000 | G49: =(E49*100%)+E49 -> 60000 | K49: ACCESORIOS | L49: BOLSOS | M49: DAMA | N49: CADENA DORADA | O49: VARIOS | P49: - | Q49: BALU BAGS | R49: =IFERROR(CONCATENATE("*",VLOOKUP(L49,PARAM!D:E,2,0),VLOOKUP(M49,PARAM!J:K,2,0),VLOOKUP(N49,PARAM!G:H,2,0),VLOOKUP(P49,PARAM!P:Q,2,0),"*"),"") -> *171570* | S49: =IFERROR(CONCATENATE(VLOOKUP(L49,PARAM!D:E,2,0),VLOOKUP(M49,PARAM!J:K,2,0),VLOOKUP(N49,PARAM!G:H,2,0),VLOOKUP(O49,PARAM!M:N,2,0),VLOOKUP(P49,PARAM!P:Q,2,0)),"") -> 17157160 | T49: =LEN(R49) -> 8 | U49: =CONCATENATE(L49," ",M49," ",N49," ",O49,IF(P49="-","",CONCATENATE(" TALLA ",P49))) -> BOLSOS DAMA CADENA DORADA VARIOS
A50: 2 | B50: carriel adidas | D50: carriel adidas | E50: 24000 | F50: =E50*A50 -> 48000 | G50: =(E50*100%)+E50 -> 48000 | K50: ACCESORIOS | L50: CARRIEL | M50: UNISEX | N50: ADIDAS | O50: VARIOS | P50: - | Q50: BALU BAGS | R50: =IFERROR(CONCATENATE("*",VLOOKUP(L50,PARAM!D:E,2,0),VLOOKUP(M50,PARAM!J:K,2,0),VLOOKUP(N50,PARAM!G:H,2,0),VLOOKUP(P50,PARAM!P:Q,2,0),"*"),"") -> *183130* | S50: =IFERROR(CONCATENATE(VLOOKUP(L50,PARAM!D:E,2,0),VLOOKUP(M50,PARAM!J:K,2,0),VLOOKUP(N50,PARAM!G:H,2,0),VLOOKUP(O50,PARAM!M:N,2,0),VLOOKUP(P50,PARAM!P:Q,2,0)),"") -> 18313160 | T50: =LEN(R50) -> 8 | U50: =CONCATENATE(L50," ",M50," ",N50," ",O50,IF(P50="-","",CONCATENATE(" TALLA ",P50))) -> CARRIEL UNISEX ADIDAS VARIOS
A51: 3 | B51: pecheras | D51: DIFERENTES MARCAS | E51: 24000 | F51: =E51*A51 -> 72000 | G51: =(E51*100%)+E51 -> 48000 | K51: ACCESORIOS | L51: PECHERAS | M51: CABALLERO | N51: DIFERENTES MARCAS | O51: VARIOS | P51: - | Q51: BALU BAGS | R51: =IFERROR(CONCATENATE("*",VLOOKUP(L51,PARAM!D:E,2,0),VLOOKUP(M51,PARAM!J:K,2,0),VLOOKUP(N51,PARAM!G:H,2,0),VLOOKUP(P51,PARAM!P:Q,2,0),"*"),"") -> *1921180* | S51: =IFERROR(CONCATENATE(VLOOKUP(L51,PARAM!D:E,2,0),VLOOKUP(M51,PARAM!J:K,2,0),VLOOKUP(N51,PARAM!G:H,2,0),VLOOKUP(O51,PARAM!M:N,2,0),VLOOKUP(P51,PARAM!P:Q,2,0)),"") -> 192118160 | T51: =LEN(R51) -> 9 | U51: =CONCATENATE(L51," ",M51," ",N51," ",O51,IF(P51="-","",CONCATENATE(" TALLA ",P51))) -> PECHERAS CABALLERO DIFERENTES MARCAS VARIOS
A52: 1 | B52: canguro de brillo | D52: canguro brillo | E52: 38000 | F52: =E52*A52 -> 38000 | G52: =(E52*100%)+E52 -> 76000 | K52: ACCESORIOS | L52: CANGUROS | M52: DAMA | N52: BRILLO | O52: VARIOS | P52: - | Q52: BALU BAGS | R52: =IFERROR(CONCATENATE("*",VLOOKUP(L52,PARAM!D:E,2,0),VLOOKUP(M52,PARAM!J:K,2,0),VLOOKUP(N52,PARAM!G:H,2,0),VLOOKUP(P52,PARAM!P:Q,2,0),"*"),"") -> *201540* | S52: =IFERROR(CONCATENATE(VLOOKUP(L52,PARAM!D:E,2,0),VLOOKUP(M52,PARAM!J:K,2,0),VLOOKUP(N52,PARAM!G:H,2,0),VLOOKUP(O52,PARAM!M:N,2,0),VLOOKUP(P52,PARAM!P:Q,2,0)),"") -> 20154160 | T52: =LEN(R52) -> 8 | U52: =CONCATENATE(L52," ",M52," ",N52," ",O52,IF(P52="-","",CONCATENATE(" TALLA ",P52))) -> CANGUROS DAMA BRILLO VARIOS
A53: 2 | B53: canguro adidas | D53: canguro adidas | E53: 20000 | F53: =E53*A53 -> 40000 | G53: =(E53*100%)+E53 -> 40000 | K53: ACCESORIOS | L53: CANGUROS | M53: UNISEX | N53: ADIDAS | O53: VARIOS | P53: - | Q53: BALU BAGS | R53: =IFERROR(CONCATENATE("*",VLOOKUP(L53,PARAM!D:E,2,0),VLOOKUP(M53,PARAM!J:K,2,0),VLOOKUP(N53,PARAM!G:H,2,0),VLOOKUP(P53,PARAM!P:Q,2,0),"*"),"") -> *203130* | S53: =IFERROR(CONCATENATE(VLOOKUP(L53,PARAM!D:E,2,0),VLOOKUP(M53,PARAM!J:K,2,0),VLOOKUP(N53,PARAM!G:H,2,0),VLOOKUP(O53,PARAM!M:N,2,0),VLOOKUP(P53,PARAM!P:Q,2,0)),"") -> 20313160 | T53: =LEN(R53) -> 8 | U53: =CONCATENATE(L53," ",M53," ",N53," ",O53,IF(P53="-","",CONCATENATE(" TALLA ",P53))) -> CANGUROS UNISEX ADIDAS VARIOS
... A115: 1 | B115: chaqueta jean torera ovejera dama | D115: chaqueta torera | E115: 45000 | F115: =E115*A115 -> 45000 | G115: =(E115*100%)+E115 -> 90000 | K115: ROPA DAMA | L115: CHAQUETAS | M115: DAMA | N115: JEAN TORERA OVEJERA | O115: VARIOS | P115: M | Q115: KBU DENIM JACKETS | R115: =IFERROR(CONCATENATE("*",VLOOKUP(L115,PARAM!D:E,2,0),VLOOKUP(M115,PARAM!J:K,2,0),VLOOKUP(N115,PARAM!G:H,2,0),VLOOKUP(P115,PARAM!P:Q,2,0),"*"),"") -> *25115525* | S115: =IFERROR(CONCATENATE(VLOOKUP(L115,PARAM!D:E,2,0),VLOOKUP(M115,PARAM!J:K,2,0),VLOOKUP(N115,PARAM!G:H,2,0),VLOOKUP(O115,PARAM!M:N,2,0),VLOOKUP(P115,PARAM!P:Q,2,0)),"") -> 2511551625 | T115: =LEN(R115) -> 10 | U115: =CONCATENATE(L115," ",M115," ",N115," ",O115,IF(P115="-","",CONCATENATE(" TALLA ",P115))) -> CHAQUETAS DAMA JEAN TORERA OVEJERA VARIOS TALLA M
A116: 2 | B116: jean baggie dama | D116: jean baggi | E116: 55000 | F116: =E116*A116 -> 110000 | G116: =(E116*100%)+E116 -> 110000 | K116: ROPA DAMA | L116: JEANS | M116: DAMA | N116: BAGGI | O116: VARIOS | P116: 14 | Q116: CONFECCIONES GROWTH | R116: =IFERROR(CONCATENATE("*",VLOOKUP(L116,PARAM!D:E,2,0),VLOOKUP(M116,PARAM!J:K,2,0),VLOOKUP(N116,PARAM!G:H,2,0),VLOOKUP(P116,PARAM!P:Q,2,0),"*"),"") -> *11395* | S116: =IFERROR(CONCATENATE(VLOOKUP(L116,PARAM!D:E,2,0),VLOOKUP(M116,PARAM!J:K,2,0),VLOOKUP(N116,PARAM!G:H,2,0),VLOOKUP(O116,PARAM!M:N,2,0),VLOOKUP(P116,PARAM!P:Q,2,0)),"") -> 1139165 | T116: =LEN(R116) -> 7 | U116: =CONCATENATE(L116," ",M116," ",N116," ",O116,IF(P116="-","",CONCATENATE(" TALLA ",P116))) -> JEANS DAMA BAGGI VARIOS TALLA 14
A117: 2 | B117: jean baggie dama | D117: jean baggi | E117: 55000 | F117: =E117*A117 -> 110000 | G117: =(E117*100%)+E117 -> 110000 | K117: ROPA DAMA | L117: JEANS | M117: DAMA | N117: BAGGI | O117: VARIOS | P117: 12 | Q117: CONFECCIONES GROWTH | R117: =IFERROR(CONCATENATE("*",VLOOKUP(L117,PARAM!D:E,2,0),VLOOKUP(M117,PARAM!J:K,2,0),VLOOKUP(N117,PARAM!G:H,2,0),VLOOKUP(P117,PARAM!P:Q,2,0),"*"),"") -> *11394* | S117: =IFERROR(CONCATENATE(VLOOKUP(L117,PARAM!D:E,2,0),VLOOKUP(M117,PARAM!J:K,2,0),VLOOKUP(N117,PARAM!G:H,2,0),VLOOKUP(O117,PARAM!M:N,2,0),VLOOKUP(P117,PARAM!P:Q,2,0)),"") -> 1139164 | T117: =LEN(R117) -> 7 | U117: =CONCATENATE(L117," ",M117," ",N117," ",O117,IF(P117="-","",CONCATENATE(" TALLA ",P117))) -> JEANS DAMA BAGGI VARIOS TALLA 12
A118: 2 | B118: jean baggie dama | D118: jean baggi | E118: 55000 | F118: =E118*A118 -> 110000 | G118: =(E118*100%)+E118 -> 110000 | K118: ROPA DAMA | L118: JEANS | M118: DAMA | N118: BAGGI | O118: VARIOS | P118: 8 | Q118: CONFECCIONES GROWTH | R118: =IFERROR(CONCATENATE("*",VLOOKUP(L118,PARAM!D:E,2,0),VLOOKUP(M118,PARAM!J:K,2,0),VLOOKUP(N118,PARAM!G:H,2,0),VLOOKUP(P118,PARAM!P:Q,2,0),"*"),"") -> *11392* | S118: =IFERROR(CONCATENATE(VLOOKUP(L118,PARAM!D:E,2,0),VLOOKUP(M118,PARAM!J:K,2,0),VLOOKUP(N118,PARAM!G:H,2,0),VLOOKUP(O118,PARAM!M:N,2,0),VLOOKUP(P118,PARAM!P:Q,2,0)),"") -> 1139162 | T118: =LEN(R118) -> 7 | U118: =CONCATENATE(L118," ",M118," ",N118," ",O118,IF(P118="-","",CONCATENATE(" TALLA ",P118))) -> JEANS DAMA BAGGI VARIOS TALLA 8
A119: 2 | B119: jean baggie dama | D119: jean baggi | E119: 55000 | F119: =E119*A119 -> 110000 | G119: =(E119*100%)+E119 -> 110000 | K119: ROPA DAMA | L119: JEANS | M119: DAMA | N119: BAGGI | O119: VARIOS | P119: 10 | Q119: CONFECCIONES GROWTH | R119: =IFERROR(CONCATENATE("*",VLOOKUP(L119,PARAM!D:E,2,0),VLOOKUP(M119,PARAM!J:K,2,0),VLOOKUP(N119,PARAM!G:H,2,0),VLOOKUP(P119,PARAM!P:Q,2,0),"*"),"") -> *11393* | S119: =IFERROR(CONCATENATE(VLOOKUP(L119,PARAM!D:E,2,0),VLOOKUP(M119,PARAM!J:K,2,0),VLOOKUP(N119,PARAM!G:H,2,0),VLOOKUP(O119,PARAM!M:N,2,0),VLOOKUP(P119,PARAM!P:Q,2,0)),"") -> 1139163 | T119: =LEN(R119) -> 7 | U119: =CONCATENATE(L119," ",M119," ",N119," ",O119,IF(P119="-","",CONCATENATE(" TALLA ",P119))) -> JEANS DAMA BAGGI VARIOS TALLA 10
A120: 1 | B120: jean baggie dama | D120: con brillantes | E120: 55000 | F120: =E120*A120 -> 55000 | G120: =(E120*100%)+E120 -> 110000 | K120: ROPA DAMA | L120: JEANS | M120: DAMA | N120: BAGGI CON BRILLANTES | O120: VARIOS | P120: 16 | Q120: CONFECCIONES GROWTH | R120: =IFERROR(CONCATENATE("*",VLOOKUP(L120,PARAM!D:E,2,0),VLOOKUP(M120,PARAM!J:K,2,0),VLOOKUP(N120,PARAM!G:H,2,0),VLOOKUP(P120,PARAM!P:Q,2,0),"*"),"") -> *11406* | S120: =IFERROR(CONCATENATE(VLOOKUP(L120,PARAM!D:E,2,0),VLOOKUP(M120,PARAM!J:K,2,0),VLOOKUP(N120,PARAM!G:H,2,0),VLOOKUP(O120,PARAM!M:N,2,0),VLOOKUP(P120,PARAM!P:Q,2,0)),"") -> 1140166 | T120: =LEN(R120) -> 7 | U120: =CONCATENATE(L120," ",M120," ",N120," ",O120,IF(P120="-","",CONCATENATE(" TALLA ",P120))) -> JEANS DAMA BAGGI CON BRILLANTES VARIOS TALLA 16
A121: 2 | B121: camiseta dama con brillantes | D121: con brillantes | E121: 14000 | F121: =E121*A121 -> 28000 | G121: =(E121*100%)+E121 -> 28000 | K121: ROPA DAMA | L121: CAMISETAS | M121: DAMA | N121: CON BRILLANTES | O121: VARIOS | P121: S | Q121: - | R121: =IFERROR(CONCATENATE("*",VLOOKUP(L121,PARAM!D:E,2,0),VLOOKUP(M121,PARAM!J:K,2,0),VLOOKUP(N121,PARAM!G:H,2,0),VLOOKUP(P121,PARAM!P:Q,2,0),"*"),"") -> *1119127* | S121: =IFERROR(CONCATENATE(VLOOKUP(L121,PARAM!D:E,2,0),VLOOKUP(M121,PARAM!J:K,2,0),VLOOKUP(N121,PARAM!G:H,2,0),VLOOKUP(O121,PARAM!M:N,2,0),VLOOKUP(P121,PARAM!P:Q,2,0)),"") -> 111911627 | T121: =LEN(R121) -> 9 | U121: =CONCATENATE(L121," ",M121," ",N121," ",O121,IF(P121="-","",CONCATENATE(" TALLA ",P121))) -> CAMISETAS DAMA CON BRILLANTES VARIOS TALLA S
A122: 2 | B122: camiseta dama con brillantes | D122: con brillantes | E122: 14000 | F122: =E122*A122 -> 28000 | G122: =(E122*100%)+E122 -> 28000 | K122: ROPA DAMA | L122: CAMISETAS | M122: DAMA | N122: CON BRILLANTES | O122: VARIOS | P122: M | Q122: - | R122: =IFERROR(CONCATENATE("*",VLOOKUP(L122,PARAM!D:E,2,0),VLOOKUP(M122,PARAM!J:K,2,0),VLOOKUP(N122,PARAM!G:H,2,0),VLOOKUP(P122,PARAM!P:Q,2,0),"*"),"") -> *1119125* | S122: =IFERROR(CONCATENATE(VLOOKUP(L122,PARAM!D:E,2,0),VLOOKUP(M122,PARAM!J:K,2,0),VLOOKUP(N122,PARAM!G:H,2,0),VLOOKUP(O122,PARAM!M:N,2,0),VLOOKUP(P122,PARAM!P:Q,2,0)),"") -> 111911625 | T122: =LEN(R122) -> 9 | U122: =CONCATENATE(L122," ",M122," ",N122," ",O122,IF(P122="-","",CONCATENATE(" TALLA ",P122))) -> CAMISETAS DAMA CON BRILLANTES VARIOS TALLA M
A123: 3 | B123: camiseta dama con brillantes | D123: con brillantes | E123: 14000 | F123: =E123*A123 -> 42000 | G123: =(E123*100%)+E123 -> 28000 | K123: ROPA DAMA | L123: CAMISETAS | M123: DAMA | N123: CON BRILLANTES | O123: VARIOS | P123: L | Q123: - | R123: =IFERROR(CONCATENATE("*",VLOOKUP(L123,PARAM!D:E,2,0),VLOOKUP(M123,PARAM!J:K,2,0),VLOOKUP(N123,PARAM!G:H,2,0),VLOOKUP(P123,PARAM!P:Q,2,0),"*"),"") -> *1119123* | S123: =IFERROR(CONCATENATE(VLOOKUP(L123,PARAM!D:E,2,0),VLOOKUP(M123,PARAM!J:K,2,0),VLOOKUP(N123,PARAM!G:H,2,0),VLOOKUP(O123,PARAM!M:N,2,0),VLOOKUP(P123,PARAM!P:Q,2,0)),"") -> 111911623 | T123: =LEN(R123) -> 9 | U123: =CONCATENATE(L123," ",M123," ",N123," ",O123,IF(P123="-","",CONCATENATE(" TALLA ",P123))) -> CAMISETAS DAMA CON BRILLANTES VARIOS TALLA L
A124: 1 | B124: camiseta dama con brillantes | D124: con brillantes | E124: 14000 | F124: =E124*A124 -> 14000 | G124: =(E124*100%)+E124 -> 28000 | K124: ROPA DAMA | L124: CAMISETAS | M124: DAMA | N124: CON BRILLANTES | O124: VARIOS | P124: XL | Q124: - | R124: =IFERROR(CONCATENATE("*",VLOOKUP(L124,PARAM!D:E,2,0),VLOOKUP(M124,PARAM!J:K,2,0),VLOOKUP(N124,PARAM!G:H,2,0),VLOOKUP(P124,PARAM!P:Q,2,0),"*"),"") -> *1119132* | S124: =IFERROR(CONCATENATE(VLOOKUP(L124,PARAM!D:E,2,0),VLOOKUP(M124,PARAM!J:K,2,0),VLOOKUP(N124,PARAM!G:H,2,0),VLOOKUP(O124,PARAM!M:N,2,0),VLOOKUP(P124,PARAM!P:Q,2,0)),"") -> 111911632 | T124: =LEN(R124) -> 9 | U124: =CONCATENATE(L124," ",M124," ",N124," ",O124,IF(P124="-","",CONCATENATE(" TALLA ",P124))) -> CAMISETAS DAMA CON BRILLANTES VARIOS TALLA XL
A125: 1 | B125: jean baggie caballero | D125: jean caballero | E125: 55000 | F125: =E125*A125 -> 55000 | G125: =(E125*100%)+E125 -> 110000 | K125: ROPA CABALLERO | L125: JEANS | M125: CABALLERO | N125: BAGGI | O125: VARIOS | P125: 30 | Q125: CONFECCIONES GROWTH | R125: =IFERROR(CONCATENATE("*",VLOOKUP(L125,PARAM!D:E,2,0),VLOOKUP(M125,PARAM!J:K,2,0),VLOOKUP(N125,PARAM!G:H,2,0),VLOOKUP(P125,PARAM!P:Q,2,0),"*"),"") -> *123913* | S125: =IFERROR(CONCATENATE(VLOOKUP(L125,PARAM!D:E,2,0),VLOOKUP(M125,PARAM!J:K,2,0),VLOOKUP(N125,PARAM!G:H,2,0),VLOOKUP(O125,PARAM!M:N,2,0),VLOOKUP(P125,PARAM!P:Q,2,0)),"") -> 12391613 | T125: =LEN(R125) -> 8 | U125: =CONCATENATE(L125," ",M125," ",N125," ",O125,IF(P125="-","",CONCATENATE(" TALLA ",P125))) -> JEANS CABALLERO BAGGI VARIOS TALLA 30
A126: 1 | B126: jean baggie caballero | D126: jean caballero | E126: 55000 | F126: =E126*A126 -> 55000 | G126: =(E126*100%)+E126 -> 110000 | K126: ROPA CABALLERO | L126: JEANS | M126: CABALLERO | N126: BAGGI | O126: VARIOS | P126: 32 | Q126: CONFECCIONES GROWTH | R126: =IFERROR(CONCATENATE("*",VLOOKUP(L126,PARAM!D:E,2,0),VLOOKUP(M126,PARAM!J:K,2,0),VLOOKUP(N126,PARAM!G:H,2,0),VLOOKUP(P126,PARAM!P:Q,2,0),"*"),"") -> *123914* | S126: =IFERROR(CONCATENATE(VLOOKUP(L126,PARAM!D:E,2,0),VLOOKUP(M126,PARAM!J:K,2,0),VLOOKUP(N126,PARAM!G:H,2,0),VLOOKUP(O126,PARAM!M:N,2,0),VLOOKUP(P126,PARAM!P:Q,2,0)),"") -> 12391614 | T126: =LEN(R126) -> 8 | U126: =CONCATENATE(L126," ",M126," ",N126," ",O126,IF(P126="-","",CONCATENATE(" TALLA ",P126))) -> JEANS CABALLERO BAGGI VARIOS TALLA 32
A127: 1 | B127: jean baggie caballero | D127: jean caballero | E127: 55000 | F127: =E127*A127 -> 55000 | G127: =(E127*100%)+E127 -> 110000 | K127: ROPA CABALLERO | L127: JEANS | M127: CABALLERO | N127: BAGGI | O127: VARIOS | P127: 34 | Q127: CONFECCIONES GROWTH | R127: =IFERROR(CONCATENATE("*",VLOOKUP(L127,PARAM!D:E,2,0),VLOOKUP(M127,PARAM!J:K,2,0),VLOOKUP(N127,PARAM!G:H,2,0),VLOOKUP(P127,PARAM!P:Q,2,0),"*"),"") -> *123915* | S127: =IFERROR(CONCATENATE(VLOOKUP(L127,PARAM!D:E,2,0),VLOOKUP(M127,PARAM!J:K,2,0),VLOOKUP(N127,PARAM!G:H,2,0),VLOOKUP(O127,PARAM!M:N,2,0),VLOOKUP(P127,PARAM!P:Q,2,0)),"") -> 12391615 | T127: =LEN(R127) -> 8 | U127: =CONCATENATE(L127," ",M127," ",N127," ",O127,IF(P127="-","",CONCATENATE(" TALLA ",P127))) -> JEANS CABALLERO BAGGI VARIOS TALLA 34
A128: 2 | B128: camisa caballero | D128: camisa caballero | E128: 24000 | F128: =E128*A128 -> 48000 | G128: =(E128*100%)+E128 -> 48000 | K128: ROPA CABALLERO | L128: CAMISAS | M128: CABALLERO | N128: - | O128: VARIOS | P128: L | Q128: HHR ELIECER HERNANDEZ | R128: =IFERROR(CONCATENATE("*",VLOOKUP(L128,PARAM!D:E,2,0),VLOOKUP(M128,PARAM!J:K,2,0),VLOOKUP(N128,PARAM!G:H,2,0),VLOOKUP(P128,PARAM!P:Q,2,0),"*"),"") -> *102023* | S128: =IFERROR(CONCATENATE(VLOOKUP(L128,PARAM!D:E,2,0),VLOOKUP(M128,PARAM!J:K,2,0),VLOOKUP(N128,PARAM!G:H,2,0),VLOOKUP(O128,PARAM!M:N,2,0),VLOOKUP(P128,PARAM!P:Q,2,0)),"") -> 10201623 | T128: =LEN(R128) -> 8 | U128: =CONCATENATE(L128," ",M128," ",N128," ",O128,IF(P128="-","",CONCATENATE(" TALLA ",P128))) -> CAMISAS CABALLERO - VARIOS TALLA L
A129: 1 | B129: camisa jean caballero | D129: camisa jean | E129: 35000 | F129: =E129*A129 -> 35000 | G129: =(E129*100%)+E129 -> 70000 | K129: ROPA CABALLERO | L129: CAMISAS | M129: CABALLERO | N129: JEAN | O129: VARIOS | P129: L | Q129: HHR ELIECER HERNANDEZ | R129: =IFERROR(CONCATENATE("*",VLOOKUP(L129,PARAM!D:E,2,0),VLOOKUP(M129,PARAM!J:K,2,0),VLOOKUP(N129,PARAM!G:H,2,0),VLOOKUP(P129,PARAM!P:Q,2,0),"*"),"") -> *10215223* | S129: =IFERROR(CONCATENATE(VLOOKUP(L129,PARAM!D:E,2,0),VLOOKUP(M129,PARAM!J:K,2,0),VLOOKUP(N129,PARAM!G:H,2,0),VLOOKUP(O129,PARAM!M:N,2,0),VLOOKUP(P129,PARAM!P:Q,2,0)),"") -> 1021521623 | T129: =LEN(R129) -> 10 | U129: =CONCATENATE(L129," ",M129," ",N129," ",O129,IF(P129="-","",CONCATENATE(" TALLA ",P129))) -> CAMISAS CABALLERO JEAN VARIOS TALLA L
A130: 3 | B130: camisa caballero | D130: camisa caballero | E130: 24000 | F130: =E130*A130 -> 72000 | G130: =(E130*100%)+E130 -> 48000 | K130: ROPA CABALLERO | L130: CAMISAS | M130: CABALLERO | N130: - | O130: VARIOS | P130: M | Q130: HHR ELIECER HERNANDEZ | R130: =IFERROR(CONCATENATE("*",VLOOKUP(L130,PARAM!D:E,2,0),VLOOKUP(M130,PARAM!J:K,2,0),VLOOKUP(N130,PARAM!G:H,2,0),VLOOKUP(P130,PARAM!P:Q,2,0),"*"),"") -> *102025* | S130: =IFERROR(CONCATENATE(VLOOKUP(L130,PARAM!D:E,2,0),VLOOKUP(M130,PARAM!J:K,2,0),VLOOKUP(N130,PARAM!G:H,2,0),VLOOKUP(O130,PARAM!M:N,2,0),VLOOKUP(P130,PARAM!P:Q,2,0)),"") -> 10201625 | T130: =LEN(R130) -> 8 | U130: =CONCATENATE(L130," ",M130," ",N130," ",O130,IF(P130="-","",CONCATENATE(" TALLA ",P130))) -> CAMISAS CABALLERO - VARIOS TALLA M
A131: 1 | B131: camisa jean caballero | D131: camisa jean | E131: 35000 | F131: =E131*A131 -> 35000 | G131: =(E131*100%)+E131 -> 70000 | K131: ROPA CABALLERO | L131: CAMISAS | M131: CABALLERO | N131: JEAN | O131: VARIOS | P131: M | Q131: HHR ELIECER HERNANDEZ | R131: =IFERROR(CONCATENATE("*",VLOOKUP(L131,PARAM!D:E,2,0),VLOOKUP(M131,PARAM!J:K,2,0),VLOOKUP(N131,PARAM!G:H,2,0),VLOOKUP(P131,PARAM!P:Q,2,0),"*"),"") -> *10215225* | S131: =IFERROR(CONCATENATE(VLOOKUP(L131,PARAM!D:E,2,0),VLOOKUP(M131,PARAM!J:K,2,0),VLOOKUP(N131,PARAM!G:H,2,0),VLOOKUP(O131,PARAM!M:N,2,0),VLOOKUP(P131,PARAM!P:Q,2,0)),"") -> 1021521625 | T131: =LEN(R131) -> 10 | U131: =CONCATENATE(L131," ",M131," ",N131," ",O131,IF(P131="-","",CONCATENATE(" TALLA ",P131))) -> CAMISAS CABALLERO JEAN VARIOS TALLA M
A132: 2 | B132: camisa caballero | D132: camisa caballero | E132: 24000 | F132: =E132*A132 -> 48000 | G132: =(E132*100%)+E132 -> 48000 | K132: ROPA CABALLERO | L132: CAMISAS | M132: CABALLERO | N132: - | O132: VARIOS | P132: S | Q132: HHR ELIECER HERNANDEZ | R132: =IFERROR(CONCATENATE("*",VLOOKUP(L132,PARAM!D:E,2,0),VLOOKUP(M132,PARAM!J:K,2,0),VLOOKUP(N132,PARAM!G:H,2,0),VLOOKUP(P132,PARAM!P:Q,2,0),"*"),"") -> *102027* | S132: =IFERROR(CONCATENATE(VLOOKUP(L132,PARAM!D:E,2,0),VLOOKUP(M132,PARAM!J:K,2,0),VLOOKUP(N132,PARAM!G:H,2,0),VLOOKUP(O132,PARAM!M:N,2,0),VLOOKUP(P132,PARAM!P:Q,2,0)),"") -> 10201627 | T132: =LEN(R132) -> 8 | U132: =CONCATENATE(L132," ",M132," ",N132," ",O132,IF(P132="-","",CONCATENATE(" TALLA ",P132))) -> CAMISAS CABALLERO - VARIOS TALLA S
A133: 2 | B133: camisa caballero | D133: camisa caballero | E133: 24000 | F133: =E133*A133 -> 48000 | G133: =(E133*100%)+E133 -> 48000 | K133: ROPA CABALLERO | L133: CAMISAS | M133: CABALLERO | N133: - | O133: VARIOS | P133: XL | Q133: HHR ELIECER HERNANDEZ | R133: =IFERROR(CONCATENATE("*",VLOOKUP(L133,PARAM!D:E,2,0),VLOOKUP(M133,PARAM!J:K,2,0),VLOOKUP(N133,PARAM!G:H,2,0),VLOOKUP(P133,PARAM!P:Q,2,0),"*"),"") -> *102032* | S133: =IFERROR(CONCATENATE(VLOOKUP(L133,PARAM!D:E,2,0),VLOOKUP(M133,PARAM!J:K,2,0),VLOOKUP(N133,PARAM!G:H,2,0),VLOOKUP(O133,PARAM!M:N,2,0),VLOOKUP(P133,PARAM!P:Q,2,0)),"") -> 10201632 | T133: =LEN(R133) -> 8 | U133: =CONCATENATE(L133," ",M133," ",N133," ",O133,IF(P133="-","",CONCATENATE(" TALLA ",P133))) -> CAMISAS CABALLERO - VARIOS TALLA XL
A134: 1 | B134: body afelpado | D134: body afelpado | E134: 26000 | F134: =E134*A134 -> 26000 | G134: =(E134*100%)+E134 -> 52000 | K134: ROPA DAMA | L134: BODY | M134: DAMA | N134: AFELPADO | O134: VARIOS | P134: UN | Q134: SAMA | R134: =IFERROR(CONCATENATE("*",VLOOKUP(L134,PARAM!D:E,2,0),VLOOKUP(M134,PARAM!J:K,2,0),VLOOKUP(N134,PARAM!G:H,2,0),VLOOKUP(P134,PARAM!P:Q,2,0),"*"),"") -> *3811430* | S134: =IFERROR(CONCATENATE(VLOOKUP(L134,PARAM!D:E,2,0),VLOOKUP(M134,PARAM!J:K,2,0),VLOOKUP(N134,PARAM!G:H,2,0),VLOOKUP(O134,PARAM!M:N,2,0),VLOOKUP(P134,PARAM!P:Q,2,0)),"") -> 381141630 | T134: =LEN(R134) -> 9 | U134: =CONCATENATE(L134," ",M134," ",N134," ",O134,IF(P134="-","",CONCATENATE(" TALLA ",P134))) -> BODY DAMA AFELPADO VARIOS TALLA UN
A135: 3 | B135: blusa ambar brillante | D135: blusa brillante | E135: 26000 | F135: =E135*A135 -> 78000 | G135: =(E135*100%)+E135 -> 52000 | K135: ROPA DAMA | L135: BLUSAS | M135: DAMA | N135: BRILLANTE | O135: VARIOS | P135: UN | Q135: SAMA | R135: =IFERROR(CONCATENATE("*",VLOOKUP(L135,PARAM!D:E,2,0),VLOOKUP(M135,PARAM!J:K,2,0),VLOOKUP(N135,PARAM!G:H,2,0),VLOOKUP(P135,PARAM!P:Q,2,0),"*"),"") -> *615230* | S135: =IFERROR(CONCATENATE(VLOOKUP(L135,PARAM!D:E,2,0),VLOOKUP(M135,PARAM!J:K,2,0),VLOOKUP(N135,PARAM!G:H,2,0),VLOOKUP(O135,PARAM!M:N,2,0),VLOOKUP(P135,PARAM!P:Q,2,0)),"") -> 61521630 | T135: =LEN(R135) -> 8 | U135: =CONCATENATE(L135," ",M135," ",N135," ",O135,IF(P135="-","",CONCATENATE(" TALLA ",P135))) -> BLUSAS DAMA BRILLANTE VARIOS TALLA UN
A136: 2 | B136: blusas mariposa | D136: blusa mariposa | E136: 18000 | F136: =E136*A136 -> 36000 | G136: =(E136*100%)+E136 -> 36000 | K136: ROPA DAMA | L136: BLUSAS | M136: DAMA | N136: MARIPOSA | O136: VARIOS | P136: UN | Q136: SAMA | R136: =IFERROR(CONCATENATE("*",VLOOKUP(L136,PARAM!D:E,2,0),VLOOKUP(M136,PARAM!J:K,2,0),VLOOKUP(N136,PARAM!G:H,2,0),VLOOKUP(P136,PARAM!P:Q,2,0),"*"),"") -> *6118430* | S136: =IFERROR(CONCATENATE(VLOOKUP(L136,PARAM!D:E,2,0),VLOOKUP(M136,PARAM!J:K,2,0),VLOOKUP(N136,PARAM!G:H,2,0),VLOOKUP(O136,PARAM!M:N,2,0),VLOOKUP(P136,PARAM!P:Q,2,0)),"") -> 611841630 | T136: =LEN(R136) -> 9 | U136: =CONCATENATE(L136," ",M136," ",N136," ",O136,IF(P136="-","",CONCATENATE(" TALLA ",P136))) -> BLUSAS DAMA MARIPOSA VARIOS TALLA UN
A137: 7 | B137: blusa ambar | D137: ambar blusa | E137: 23000 | F137: =E137*A137 -> 161000 | G137: =(E137*100%)+E137 -> 46000 | K137: ROPA DAMA | L137: BLUSAS | M137: DAMA | N137: AMBAR | O137: VARIOS | P137: UN | Q137: SAMA | R137: =IFERROR(CONCATENATE("*",VLOOKUP(L137,PARAM!D:E,2,0),VLOOKUP(M137,PARAM!J:K,2,0),VLOOKUP(N137,PARAM!G:H,2,0),VLOOKUP(P137,PARAM!P:Q,2,0),"*"),"") -> *612430* | S137: =IFERROR(CONCATENATE(VLOOKUP(L137,PARAM!D:E,2,0),VLOOKUP(M137,PARAM!J:K,2,0),VLOOKUP(N137,PARAM!G:H,2,0),VLOOKUP(O137,PARAM!M:N,2,0),VLOOKUP(P137,PARAM!P:Q,2,0)),"") -> 61241630 | T137: =LEN(R137) -> 8 | U137: =CONCATENATE(L137," ",M137," ",N137," ",O137,IF(P137="-","",CONCATENATE(" TALLA ",P137))) -> BLUSAS DAMA AMBAR VARIOS TALLA UN
A138: 2 | B138: body cosmo | D138: body cosmo | E138: 23000 | F138: =E138*A138 -> 46000 | G138: =(E138*100%)+E138 -> 46000 | K138: ROPA DAMA | L138: BODY | M138: DAMA | N138: BODY COSMO | O138: VARIOS | P138: UN | Q138: SAMA | R138: =IFERROR(CONCATENATE("*",VLOOKUP(L138,PARAM!D:E,2,0),VLOOKUP(M138,PARAM!J:K,2,0),VLOOKUP(N138,PARAM!G:H,2,0),VLOOKUP(P138,PARAM!P:Q,2,0),"*"),"") -> *3814730* | S138: =IFERROR(CONCATENATE(VLOOKUP(L138,PARAM!D:E,2,0),VLOOKUP(M138,PARAM!J:K,2,0),VLOOKUP(N138,PARAM!G:H,2,0),VLOOKUP(O138,PARAM!M:N,2,0),VLOOKUP(P138,PARAM!P:Q,2,0)),"") -> 381471630 | T138: =LEN(R138) -> 9 | U138: =CONCATENATE(L138," ",M138," ",N138," ",O138,IF(P138="-","",CONCATENATE(" TALLA ",P138))) -> BODY DAMA BODY COSMO VARIOS TALLA UN
A139: 1 | B139: body otra clase | D139: otra clase | E139: 23000 | F139: =E139*A139 -> 23000 | G139: =(E139*100%)+E139 -> 46000 | K139: ROPA DAMA | L139: BODY | M139: DAMA | N139: OTRA CLASE | O139: VARIOS | P139: UN | Q139: SAMA | R139: =IFERROR(CONCATENATE("*",VLOOKUP(L139,PARAM!D:E,2,0),VLOOKUP(M139,PARAM!J:K,2,0),VLOOKUP(N139,PARAM!G:H,2,0),VLOOKUP(P139,PARAM!P:Q,2,0),"*"),"") -> *38119930* | S139: =IFERROR(CONCATENATE(VLOOKUP(L139,PARAM!D:E,2,0),VLOOKUP(M139,PARAM!J:K,2,0),VLOOKUP(N139,PARAM!G:H,2,0),VLOOKUP(O139,PARAM!M:N,2,0),VLOOKUP(P139,PARAM!P:Q,2,0)),"") -> 3811991630 | T139: =LEN(R139) -> 10 | U139: =CONCATENATE(L139," ",M139," ",N139," ",O139,IF(P139="-","",CONCATENATE(" TALLA ",P139))) -> BODY DAMA OTRA CLASE VARIOS TALLA UN
... A153: 2 | B153: polo caballero seda fria | D153: polo seda | E153: 24000 | F153: =E153*A153 -> 48000 | G153: =(E153*100%)+E153 -> 48000 | K153: ROPA CABALLERO | L153: CAMISETAS | M153: CABALLERO | N153: POLO SEDA FRIA | O153: VARIOS | P153: XL | Q153: DRAGMA | R153: =IFERROR(CONCATENATE("*",VLOOKUP(L153,PARAM!D:E,2,0),VLOOKUP(M153,PARAM!J:K,2,0),VLOOKUP(N153,PARAM!G:H,2,0),VLOOKUP(P153,PARAM!P:Q,2,0),"*"),"") -> *11221832* | S153: =IFERROR(CONCATENATE(VLOOKUP(L153,PARAM!D:E,2,0),VLOOKUP(M153,PARAM!J:K,2,0),VLOOKUP(N153,PARAM!G:H,2,0),VLOOKUP(O153,PARAM!M:N,2,0),VLOOKUP(P153,PARAM!P:Q,2,0)),"") -> 1122181632 | T153: =LEN(R153) -> 10 | U153: =CONCATENATE(L153," ",M153," ",N153," ",O153,IF(P153="-","",CONCATENATE(" TALLA ",P153))) -> CAMISETAS CABALLERO POLO SEDA FRIA VARIOS TALLA XL
A154: 2 | B154: pantalon noche dama | D154: pantalon noche | E154: 46000 | F154: =E154*A154 -> 92000 | G154: =(E154*100%)+E154 -> 92000 | K154: ROPA DAMA | L154: PANTALONES | M154: DAMA | N154: NOCHE | O154: VARIOS | P154: 12 | Q154: R&D | R154: =IFERROR(CONCATENATE("*",VLOOKUP(L154,PARAM!D:E,2,0),VLOOKUP(M154,PARAM!J:K,2,0),VLOOKUP(N154,PARAM!G:H,2,0),VLOOKUP(P154,PARAM!P:Q,2,0),"*"),"") -> *211974* | S154: =IFERROR(CONCATENATE(VLOOKUP(L154,PARAM!D:E,2,0),VLOOKUP(M154,PARAM!J:K,2,0),VLOOKUP(N154,PARAM!G:H,2,0),VLOOKUP(O154,PARAM!M:N,2,0),VLOOKUP(P154,PARAM!P:Q,2,0)),"") -> 21197164 | T154: =LEN(R154) -> 8 | U154: =CONCATENATE(L154," ",M154," ",N154," ",O154,IF(P154="-","",CONCATENATE(" TALLA ",P154))) -> PANTALONES DAMA NOCHE VARIOS TALLA 12
A155: 1 | B155: pantalon noche dama | D155: pantalon noche | E155: 46000 | F155: =E155*A155 -> 46000 | G155: =(E155*100%)+E155 -> 92000 | K155: ROPA DAMA | L155: PANTALONES | M155: DAMA | N155: NOCHE | O155: VARIOS | P155: 14 | Q155: R&D | R155: =IFERROR(CONCATENATE("*",VLOOKUP(L155,PARAM!D:E,2,0),VLOOKUP(M155,PARAM!J:K,2,0),VLOOKUP(N155,PARAM!G:H,2,0),VLOOKUP(P155,PARAM!P:Q,2,0),"*"),"") -> *211975* | S155: =IFERROR(CONCATENATE(VLOOKUP(L155,PARAM!D:E,2,0),VLOOKUP(M155,PARAM!J:K,2,0),VLOOKUP(N155,PARAM!G:H,2,0),VLOOKUP(O155,PARAM!M:N,2,0),VLOOKUP(P155,PARAM!P:Q,2,0)),"") -> 21197165 | T155: =LEN(R155) -> 8 | U155: =CONCATENATE(L155," ",M155," ",N155," ",O155,IF(P155="-","",CONCATENATE(" TALLA ",P155))) -> PANTALONES DAMA NOCHE VARIOS TALLA 14
A156: 1 | B156: pantalon noche dama | D156: pantalon noche | E156: 46000 | F156: =E156*A156 -> 46000 | G156: =(E156*100%)+E156 -> 92000 | K156: ROPA DAMA | L156: PANTALONES | M156: DAMA | N156: NOCHE | O156: VARIOS | P156: 10 | Q156: R&D | R156: =IFERROR(CONCATENATE("*",VLOOKUP(L156,PARAM!D:E,2,0),VLOOKUP(M156,PARAM!J:K,2,0),VLOOKUP(N156,PARAM!G:H,2,0),VLOOKUP(P156,PARAM!P:Q,2,0),"*"),"") -> *211973* | S156: =IFERROR(CONCATENATE(VLOOKUP(L156,PARAM!D:E,2,0),VLOOKUP(M156,PARAM!J:K,2,0),VLOOKUP(N156,PARAM!G:H,2,0),VLOOKUP(O156,PARAM!M:N,2,0),VLOOKUP(P156,PARAM!P:Q,2,0)),"") -> 21197163 | T156: =LEN(R156) -> 8 | U156: =CONCATENATE(L156," ",M156," ",N156," ",O156,IF(P156="-","",CONCATENATE(" TALLA ",P156))) -> PANTALONES DAMA NOCHE VARIOS TALLA 10
A157: 1 | B157: falda gamusa dama | D157: falda gamusa | E157: 48000 | F157: =E157*A157 -> 48000 | G157: =(E157*100%)+E157 -> 96000 | K157: ROPA DAMA | L157: FALDAS | M157: DAMA | N157: GAMUSA | O157: VARIOS | P157: 6 | Q157: R&D | R157: =IFERROR(CONCATENATE("*",VLOOKUP(L157,PARAM!D:E,2,0),VLOOKUP(M157,PARAM!J:K,2,0),VLOOKUP(N157,PARAM!G:H,2,0),VLOOKUP(P157,PARAM!P:Q,2,0),"*"),"") -> *911371* | S157: =IFERROR(CONCATENATE(VLOOKUP(L157,PARAM!D:E,2,0),VLOOKUP(M157,PARAM!J:K,2,0),VLOOKUP(N157,PARAM!G:H,2,0),VLOOKUP(O157,PARAM!M:N,2,0),VLOOKUP(P157,PARAM!P:Q,2,0)),"") -> 91137161 | T157: =LEN(R157) -> 8 | U157: =CONCATENATE(L157," ",M157," ",N157," ",O157,IF(P157="-","",CONCATENATE(" TALLA ",P157))) -> FALDAS DAMA GAMUSA VARIOS TALLA 6
